Workbook

Sheet README
A1: CVR Engineering — Phase 1 Baseline Model
A2: v2: GL financial statements through 6/30/2026 incorporated. Generated by scripts/build_phase1_workbook.py.
A4: PURPOSE
A5: Phase 1 of the financial model build: a quantified current-state baseline reconciled to the
A6: KPI report (7/11/2026), the 2026 rate sheet, and the GL financial statements through 6/30/2026.
A8: TABS
A9: Assumptions — global inputs (blue). Overhead, interest, and burden now sourced from GL.
A10: Rates — 2026 rate sheet, effective January 2026.
A11: Roster & Hours — people, classifications, YTD hours and utilization vs target, value at card rates.
A12: Labor Cost — per-person standard cost rates (COINS timesheet report), loaded cost, and margin by role.
A13: Baseline P&L — CVR monthly actuals vs budget, Jan–Jun 2026 (Jan–May per KPI report, June per GL).
A14: GL Income Stmt — full line-item income statement, June and YTD, actual vs budget vs prior year.
... A32: data/CVR_Timesheet_Costs_Jul2026_JC016755.pdf

Sheet Assumptions
A1: Global Assumptions
A2: Blue cells are inputs. GL-sourced values are black.
A4: Assumption | B4: Value | C4: Notes
A5: Standard hours per FTE-year | B5: 2080 | C5: 40 hrs x 52 wks; adjust for PTO/holiday policy if preferred
A6: Median target billable utilization | B6: 0.75 | C6: KPI report gauge target (median of per-person targets)
A7: Active billable headcount (current) | B7: 10 | C7: People with recorded hours in the KPI report
A8: Hours-to-June-30 adjustment factor | B8: 0.949 | C8: KPI hours run through 7/11 (~27.4 wks); scales to Jan–Jun (26 wks) to match the GL period
A9: Employment burden load (computed from GL) | B9: 0.338 | C9: YTD burden (FICA, UI, WC, health, pension, benefits, vac/hol = $157.4K) ÷ total wages ($465.4K); refine with salary detail
A10: Corporate overhead allocation ($/month) | B10: 17250 | C10: GL actual — flat monthly, matches budget ($103,500 YTD)
A11: Interest expense ($/month avg) | B11: 5015 | C11: GL: $30,087 YTD ÷ 6, on Note Payable-Parent of $3.44M (not in budget)
A12: Year-2 divisional sales goal ($K) | B12: 6000 | C12: Divisional business target
A13: Year-2 OILI return target | B13: 0.2 | C13: OILI / revenue

Sheet Rates
A1: CVR Engineering — Hourly Rates and Charges
A2: Effective January 2026. Source: data/CVR_Rate_Sheet_2026.pdf
A4: Classification | B4: Rate / hr
A5: Administrative Assistant | B5: 59.62
A6: Graphics Technician | B6: 76.14
A7: Project Manager | B7: 159.86
A8: Designer I | B8: 79.91
A9: Designer II | B9: 95.7
A10: Senior Designer | B10: 105.01
A11: Engineer I | B11: 112.27
A12: Engineer II | B12: 138.09
A13: Engineer III | B13: 152.21
A14: Engineer IV | B14: 172.37
A15: Senior Engineer | B15: 241.57
A16: Principal Engineer | B16: 360.72
A18: • Travel time in the interest of the work billed at full rates.
A19: • No overtime multipliers — excess hours billed at standard rates.
A20: • Mileage at IRS rate; ground/air travel and living expenses at cost.
A21: • Purchases, out-of-scope subcontract work and other expenses at cost + 10%.

Sheet Roster & Hours
A1: Roster, YTD Hours and Utilization (2026 through week ending 7/11)
A2: Hours and splits from the KPI report utilization page. Orange classifications are assumptions pending confirmation.
A4: Name | B4: Billing classification | C4: Class source | D4: Rate / hr | E4: Total hrs YTD | F4: Billable % | G4: Non-billable % | H4: Bids % | I4: Billable hrs | J4: Target util % | K4: Util vs target | L4: Billable value @ card
A5: Craig Peterson | B5: Engineer I | C5: org chart | D5: =Rates!B11 | E5: 1017 | F5: 0.796 | G5: 0.204 | H5: 0 | I5: =E5*F5 | J5: 0.754 | K5: =F5-J5 | L5: =I5*D5
A6: Bhkti Patel | B6: Engineer III | C6: org chart | D6: =Rates!B13 | E6: 1045 | F6: 0.744 | G6: 0.202 | H6: 0.055 | I6: =E6*F6 | J6: 0.707 | K6: =F6-J6 | L6: =I6*D6
A7: Taylor Nelson | B7: Engineer II | C7: ASSUMED — confirm | D7: =Rates!B12 | E7: 1045 | F7: 0.61 | G7: 0.337 | H7: 0.054 | I7: =E7*F7 | J7: 0.801 | K7: =F7-J7 | L7: =I7*D7
A8: Hayley Worthen | B8: Senior Engineer | C8: org chart | D8: =Rates!B15 | E8: 952 | F8: 0.669 | G8: 0.162 | H8: 0.169 | I8: =E8*F8 | J8: 0.613 | K8: =F8-J8 | L8: =I8*D8
A9: Francis Wagner | B9: Engineer III | C9: org chart | D9: =Rates!B13 | E9: 992 | F9: 0.625 | G9: 0.343 | H9: 0.032 | I9: =E9*F9 | J9: 0.707 | K9: =F9-J9 | L9: =I9*D9
A10: Collin Allen | B10: Graphics Technician | C10: org chart | D10: =Rates!B6 | E10: 985.25 | F10: 0.576 | G10: 0.424 | H10: 0 | I10: =E10*F10 | J10: 0.801 | K10: =F10-J10 | L10: =I10*D10
A11: Kevin Metts | B11: Designer II | C11: ASSUMED — confirm | D11: =Rates!B9 | E11: 890 | F11: 0.384 | G11: 0.598 | H11: 0.018 | I11: =E11*F11 | J11: 0.754 | K11: =F11-J11 | L11: =I11*D11
A12: Roy Pierce | B12: Principal Engineer | C12: ASSUMED billing class | D12: =Rates!B16 | E12: 847 | F12: 0.327 | G12: 0.591 | H12: 0.082 | I12: =E12*F12 | J12: 0.424 | K12: =F12-J12 | L12: =I12*D12
A13: Randy Pynenberg | B13: Engineer IV | C13: org chart | D13: =Rates!B14 | E13: 68 | F13: 0.897 | G13: 0 | H13: 0.103 | I13: =E13*F13 | J13: 0.95 | K13: =F13-J13 | L13: =I13*D13
A14: Auston Hopson | B14: Graphics Technician | C14: org chart | D14: =Rates!B6 | E14: 18 | F14: 1 | G14: 0 | H14: 0 | I14: =E14*F14 | J14: 1 | K14: =F14-J14 | L14: =I14*D14
A15: Tom Little | B15: Engineer IV | C15: org chart — no hours in KPI report | D15: =Rates!B14
A16: Erin Bryden | B16: Engineer IV | C16: org chart — no hours in KPI report | D16: =Rates!B14
A17: Patrick Nicholson | B17: Senior Designer | C17: org chart — no hours in KPI report | D17: =Rates!B10
A18: TOTAL / blended | D18: =L18/I18 | E18: =SUM(E5:E17) | I18: =SUM(I5:I17) | L18: =SUM(L5:L17)
A20: KPI report totals: 8,052.25 total hrs · 4,747 billable · 2,896 non-billable · 405 bids · 59.0% total billable utilization. Roster above sums slightly lower (~193 hrs unattributed on the report page).

Sheet Labor Cost
A1: Labor Cost — standard rates and margin by person
A2: Cost rates from COINS Timesheet Costs Report (JC016755), Jul 2026. Loaded cost = raw × (1 + burden). Burden on Assumptions.
A4: Name | B4: Billing classification | C4: Bill rate / hr | D4: Raw cost / hr | E4: Loaded cost / hr | F4: Margin / hr (bill − loaded) | G4: Cost multiplier (bill ÷ loaded) | H4: Billable value @ card
A5: Roy Pierce | B5: Principal Engineer | C5: =Rates!B16 | D5: 149.57 | E5: =D5*(1+Assumptions!$B$9) | F5: =C5-E5 | G5: =C5/E5 | H5: ='Roster & Hours'!L12
A6: Hayley Worthen | B6: Senior Engineer | C6: =Rates!B15 | D6: 138.05 | E6: =D6*(1+Assumptions!$B$9) | F6: =C6-E6 | G6: =C6/E6 | H6: ='Roster & Hours'!L8
A7: Bhkti Patel | B7: Engineer III | C7: =Rates!B13 | D7: 107.6 | E7: =D7*(1+Assumptions!$B$9) | F7: =C7-E7 | G7: =C7/E7 | H7: ='Roster & Hours'!L6
A8: Francis Wagner | B8: Engineer III | C8: =Rates!B13 | D8: 107.6 | E8: =D8*(1+Assumptions!$B$9) | F8: =C8-E8 | G8: =C8/E8 | H8: ='Roster & Hours'!L9
A9: Kevin Metts | B9: Designer II | C9: =Rates!B9 | D9: 92.39 | E9: =D9*(1+Assumptions!$B$9) | F9: =C9-E9 | G9: =C9/E9 | H9: ='Roster & Hours'!L11
A10: Craig Peterson | B10: Engineer I | C10: =Rates!B11 | D10: 77.16 | E10: =D10*(1+Assumptions!$B$9) | F10: =C10-E10 | G10: =C10/E10 | H10: ='Roster & Hours'!L5
A11: Taylor Nelson | B11: Engineer II | C11: =Rates!B12 | D11: 77.16 | E11: =D11*(1+Assumptions!$B$9) | F11: =C11-E11 | G11: =C11/E11 | H11: ='Roster & Hours'!L7
A12: Collin Allen | B12: Graphics Technician | C12: =Rates!B6 | D12: 51.11 | E12: =D12*(1+Assumptions!$B$9) | F12: =C12-E12 | G12: =C12/E12 | H12: ='Roster & Hours'!L10
A13: Randy Pynenberg | B13: Engineer IV | C13: =Rates!B14 | D13: TBD | H13: ='Roster & Hours'!L13
A14: Auston Hopson | B14: Graphics Technician | C14: =Rates!B6 | D14: TBD | H14: ='Roster & Hours'!L14
A15: Blended (weighted by billable hrs) | D15: =SUMPRODUCT('Roster & Hours'!I5:I12,D5:D12)/SUM('Roster & Hours'!I5:I12) | E15: =D15*(1+Assumptions!$B$9)
A17: RAW vs BURDENED — assessment: these are base/pay rates, burden-EXCLUSIVE. Two tells:
A18: 1. The GL books burden (FICA, UI, WC, health, pension, benefits, vac/hol = $157.4K YTD) as separate
A19: operating-expense lines, NOT inside Cost of Revenues. If the job-cost rate were fully loaded, that
A20: burden would sit in COGS instead — it cannot be in both. So the rate feeding COGS is burden-free.
A21: 2. On the COINS internal-labor job (9715), PTO, holiday and sick hours are booked at the SAME per-person
A22: rate. A fully-burdened rate would double-count fringe when vacation/holiday time is also charged at it.
A23: Therefore: loaded cost = raw × (1 + burden%), burden ≈ 33.8% blended (Assumptions!B9). Note the blend is
A24: approximate — health insurance is ~flat $/head (heavier on lower-paid staff) and payroll taxes cap on high
A25: earners, so true burden % is higher at the bottom of the roster and lower at the top.
A26: TO CONFIRM DEFINITIVELY: ask payroll/COINS admin what the standard cost rate includes, or reconcile the
A27: timesheet direct-labor total to the GL 'Labor-Design Services' line ($428.5K YTD).
A28: Cost rates cluster by grade (both Engineer IIIs = $107.60), a good validation. Taylor Nelson costs at the
A29: Engineer I rate ($77.16) despite the assumed Engineer II billing class — worth confirming.

Sheet Baseline P&L
A1: CVR — Baseline P&L, January–June 2026 (all figures $K)
A2: Jan–May monthlies from the KPI report; June from the GL statements (cross-tied on Checks tab). COGS/OpEx derived Jan–May.
A4: CVR ACTUALS ($K) | B4: Jan | C4: Feb | D4: Mar | E4: Apr | F4: May | G4: Jun | H4: YTD
A5: Revenue | B5: 110.5 | C5: 96.8 | D5: 39.3 | E5: 94.6 | F5: 85.5 | G5: 124.4 | H5: =SUM(B5:G5)
A6: Cost of Sales (derived) | B6: =B5-B7 | C6: =C5-C7 | D6: =D5-D7 | E6: =E5-E7 | F6: =F5-F7 | G6: =G5-G7 | H6: =SUM(B6:G6)
A7: Gross Profit | B7: 52.6 | C7: 24.2 | D7: -15.7 | E7: 33.7 | F7: -18 | G7: 45.8 | H7: =SUM(B7:G7)
A8: Gross margin % | B8: =B7/B5 | C8: =C7/C5 | D8: =D7/D5 | E8: =E7/E5 | F8: =F7/F5 | G8: =G7/G5 | H8: =H7/H5
A9: Operating Expenses (derived) | B9: =B7-B10 | C9: =C7-C10 | D9: =D7-D10 | E9: =E7-E10 | F9: =F7-F10 | G9: =G7-G10 | H9: =SUM(B9:G9)
A10: Net Income / (Loss) | B10: -41.7 | C10: -49.1 | D10: -98.8 | E10: -60.5 | F10: -54.5 | G10: -15.8 | H10: =SUM(B10:G10)
A11: Net margin % | B11: =B10/B5 | C11: =C10/C5 | D11: =D10/D5 | E11: =E10/E5 | F11: =F10/F5 | G11: =G10/G5 | H11: =H10/H5
A13: BUDGET ($K, monthly = Δ of published YTD) | B13: Jan | C13: Feb | D13: Mar | E13: Apr | F13: May | G13: Jun | H13: YTD
A14: Revenue — budget | B14: 169.1 | C14: 169.1 | D14: 169.1 | E14: 169.1 | F14: 169.1 | G14: 169.1 | H14: =SUM(B14:G14)
A15: Gross Profit — budget | B15: 104.1 | C15: 104.1 | D15: 104.1 | E15: 104.2 | F15: 104.1 | G15: 104.1 | H15: =SUM(B15:G15)
A16: Net Income — budget | B16: 11.6 | C16: 11.6 | D16: 11.7 | E16: 11.6 | F16: 11.6 | G16: 11.6 | H16: =SUM(B16:G16)
A18: VARIANCE — YTD ($K) | B18: Actual | C18: Budget | D18: Act − Bud
A19: Revenue | B19: =H5 | C19: =H14 | D19: =B19-C19
A20: Gross Profit | B20: =H7 | C20: =H15 | D20: =B20-C20
A21: Net Income | B21: =H10 | C21: =H16 | D21: =B21-C21
A23: June was the best month YTD: 36.8% gross margin and a near-breakeven operating result (−$9.8K before interest). Note the June budget expects 61.6% GP — the actual/budget gap is labor cost vs revenue (see Realization).

Sheet GL Income Stmt
A1: CVR Engineering — GL Income Statement, period ending 6/30/2026 (all figures $)
A2: Source: data/CVR_Financial_Statements_2026-06-30.pdf (COINS GL Reporter). This is the line-item structure Phase 2 forecasts against.
A4: Line | B4: Jun Actual | C4: Jun Budget | D4: Jun PY | E4: YTD Actual | F4: YTD Budget | G4: YTD PY
A5: Sales-Design Services | B5: 124360 | C5: 169094 | D5: 86705 | E5: 551013 | F5: 1014563 | G5: 399143
A6: Subcontract | B6: 0 | C6: 0 | D6: 0 | E6: 0 | F6: 0 | G6: 218460
A7: Labor-Design Services | B7: 78573 | C7: 64980 | D7: 43947 | E7: 428498 | F7: 389882 | G7: 462051
A8: Direct Cost of Revenues Earned | B8: 78573 | C8: 64980 | D8: 43947 | E8: 428498 | F8: 389882 | G8: 680511
A9: Gross Profit | B9: 45787 | C9: 104114 | D9: 42757 | E9: 122514 | F9: 624681 | G9: -281368
A10: Labor-Indirect | B10: -6078 | C10: 22236 | D10: 41879 | E10: 36890 | F10: 133414 | G10: 86024
A11: FICA Expense | B11: 5841 | C11: 7003 | D11: 7460 | E11: 38930 | F11: 42018 | G11: 45315
A12: Federal Unemployment Expense | B12: 6 | C12: 37 | D12: 0 | E12: 184 | F12: 224 | G12: 407
A13: State Unemployment Expense | B13: 23 | C13: 209 | D13: 0 | E13: 324 | F13: 1252 | G13: 2298
A14: Mileage Expense | B14: 54 | C14: 0 | D14: 10 | E14: 188 | F14: 0 | G14: 96
A15: Repair & Maint. Equip. | B15: 16 | C15: 19 | D15: 343 | E15: 527 | F15: 114 | G15: 368
A16: Fuel Expense | B16: 33 | C16: 20 | D16: 34 | E16: 185 | F16: 121 | G16: 171
... A50: Net Income (Loss) | B50: -15845 | C50: 11617 | D50: -84993 | E50: -320537 | F50: 69699 | G50: -922542
A51: OILI (Operating Income less Interest) | B51: =B48-B49 | C51: =C48-C49 | D51: =D48-D49 | E51: =E48-E49 | F51: =F48-F49 | G51: =G48-G49
A52: OILI return % (OILI ÷ revenue) | B52: =IF(B5=0,"n/a",(B48-B49)/B5) | C52: =IF(C5=0,"n/a",(C48-C49)/C5) | D52: =IF(D5=0,"n/a",(D48-D49)/D5) | E52: =IF(E5=0,"n/a",(E48-E49)/E5) | F52: =IF(F5=0,"n/a",(F48-F49)/F5) | G52: =IF(G5=0,"n/a",(G48-G49)/G5)
A54: June Labor-Indirect is negative (−$6,078): a reclass/credit month — worth confirming with accounting.
A55: Budget carries no interest expense; actual interest (~$5K/mo) accrues on the $3.44M parent note, so OILI
A56: and Net Income diverge from budget by that amount even at budgeted operating performance.
A57: Prior year YTD included $218K subcontract cost at a −70% gross margin; 2026 has no subcontract activity.

Sheet Balance Sheet
A1: CVR Engineering — Balance Sheet, 6/30/2026 (all figures $)
A2: Source: data/CVR_Financial_Statements_2026-06-30.pdf
A4: Line | B4: Current | C4: One Year Ago | D4: Annual Budget
A5: ASSETS
A6: Accounts Receivable-Trade | B6: 139807 | C6: 46065 | D6: 30000
A7: Prepaid Expenses | B7: 2000 | C7: 0 | D7: 6000
A8: Total Current Assets | B8: 141807 | C8: 46065 | D8: 36000
A9: Fixed / ROU / Other Assets | B9: 0 | C9: 0 | D9: 0
A10: Total Assets | B10: 141807 | C10: 46065 | D10: 36000
A11: LIABILITIES
A12: Accounts Payable | B12: 0 | C12: 340 | D12: 0
A13: Accrued Payroll | B13: 19598 | C13: 28388 | D13: 40000
A14: Accrued PTO | B14: 14049 | C14: 0 | D14: 10000
A15: Accrued Bonus | B15: 0 | C15: 38508 | D15: 54740
A16: Accrued Insurance Payable | B16: -19465 | C16: -14099 | D16: -5000
A17: Accrued Health Insurance Payable | B17: 7373 | C17: 2635 | D17: 5000
A18: Accrued Interest Payable | B18: 16104 | C18: 16681 | D18: 0
A19: Accrued Pension | B19: 13459 | C19: 32339 | D19: 15000
A20: Payroll Withholdings & Taxes Payable | B20: 1426 | C20: 2105 | D20: 2000
A21: Total Current Liabilities | B21: 52544 | C21: 106898 | D21: 121740
A22: Note Payable Parent | B22: 3436622 | C22: 3401478 | D22: 2801685
A23: Total Liabilities | B23: 3489166 | C23: 3508376 | D23: 2923425
A24: EQUITY
A25: Paid In Surplus | B25: 500 | C25: 500 | D25: 500
A26: Retained Earnings | B26: -3027323 | C26: -2540270 | D26: -3027324
A27: Net Income | B27: -320537 | C27: -922542 | D27: 139399
A28: Total Shareholders' Equity | B28: -3347360 | C28: -3462311 | D28: -2887425
A29: Total Liabilities & Equity | B29: 141807 | C29: 46065 | D29: 36000
A31: CVR holds no cash, fixed assets, or leases — the balance sheet is essentially AR funded by the parent note.
A32: Cumulative deficit: retained earnings −$3.03M plus current-year loss = equity of −$3.35M. This is the
A33: historic cost of running engineering as a loss-leader, quantified — and the baseline the turnaround is measured against.
A34: AR tripled year-over-year ($46K → $140K), consistent with growing external billing activity.

Sheet Cash Flow & Customers
A1: Six-Month Cash Flow Summary and Sales by Customer (all figures $)
A2: Source: data/CVR_Financial_Statements_2026-06-30.pdf
A4: Cash flow line | B4: Actual thru 6/30/26 | C4: Budget thru 12/31/26
A5: Net Income / (Loss) | B5: -320537 | C5: 139399
A6: Δ Accounts Receivable-Billed | B6: -98921 | C6: 10886
A7: Δ Prepaid Expenses | B7: 4000 | C7: 0
A8: Δ Accrued Expenses | B8: -61697 | C8: 7497
A9: Net Cash from Operating Activities | B9: -477155 | C9: 157782
A10: Net Increase/(Decrease) to Note Payable-USC | B10: 477155 | C10: -157782
A11: Net Change in Cash | B11: 0 | C11: 0
A13: Every operating dollar CVR consumes is funded by drawing on the USC parent note — $477K drawn in six months. The full-year budget expects a $158K paydown, which requires the budgeted H2 swing to +$139K net income.
A15: SALES BY CUSTOMER — YTD 6/30/2026
A16: Customer | B16: Sales $ | C16: % of total | D16: Type
A17: CenterPoint Energy (job 017-0001) | B17: 383956 | C17: =B17/$B$24 | D17: external
A18: Hydaker Wheatlake — DTE-New Baltimore (001-0003) | B18: 40187 | C18: =B18/$B$24 | D18: intercompany
A19: Hydaker Wheatlake — CE HVD Pole Replacement (005-0004) | B19: 71268 | C19: =B19/$B$24 | D19: intercompany
A20: Ambor Structures (022-0003) | B20: 19200 | C20: =B20/$B$24 | D20: external
A21: Steuben County REMC (019-0001) | B21: 15300 | C21: =B21/$B$24 | D21: external
A22: Great Lakes Energy (021-0001) | B22: 13377 | C22: =B22/$B$24 | D22: external
A23: Kokosing Industrial (005-0001) | B23: 7725 | C23: =B23/$B$24 | D23: external
A24: Total | B24: =SUM(B17:B23)
A25: Intercompany (HWC) share | B25: =(B18+B19)/B24
A26: CenterPoint share | B26: =B17/B24
A28: Answers a Phase-1 question: CVR hours on HWC jobs ARE revenue-credited as intercompany sales (~20% of YTD revenue). CenterPoint is ~70% of revenue — matching its ~70% share of billable hours.

Sheet HWC EPC Baseline
A1: HWC EPC — Baseline, January–May 2026 (all figures $K)
A2: Context for the engineering P&L: design quality and constructability directly affect these outcomes.
A4: HWC EPC ($K) | B4: Jan | C4: Feb | D4: Mar | E4: Apr | F4: May | G4: YTD
A5: Revenue | B5: 732.2 | C5: 207.7 | D5: -321 | E5: -125.1 | F5: 678.6 | G5: =SUM(B5:F5)
A6: Net Profit / (Loss) | B6: -318.3 | C6: -346.9 | D6: -672.8 | E6: -656.5 | F6: -114.8 | G6: =SUM(B6:F6)
A7: Net margin % (YTD) | G7: =G6/G5
A9: Negative revenue in March and April are billing adjustments/write-downs per the KPI report charts.
A10: Active EPC scorecard jobs (7/11/2026): 4 substation projects, PO $4.3M–$6.6M, plan margins 12.7%–16.4%,
A11: cost variance +3.6% to −19.8%. Engineering share of paired EPC pursuits runs ~4–5% of EPC job value.

Sheet Realization
A1: Realization Analysis — where does the rate card go?
A2: Compares billable-hour value at card rates against GL revenue through 6/30, plus the labor-multiplier view.
A4: Step | B4: Value | C4: Source / formula
A5: Billable hours YTD (through 7/11) | B5: ='Roster & Hours'!I18 | C5: Roster & Hours total (KPI report: 4,747)
A6: Adjustment factor to June 30 | B6: =Assumptions!B8 | C6: Assumptions — aligns hours window to the GL period
A7: Est. billable hours, Jan–Jun | B7: =B5*B6 | C7: calc
A8: Blended card rate ($/hr) | B8: ='Roster & Hours'!D18 | C8: mix-weighted from actual billable hours
A9: Value at card rates, Jan–Jun ($K) | B9: =B7*B8/1000 | C9: calc
A10: Actual revenue, Jan–Jun ($K) | B10: ='GL Income Stmt'!E5/1000 | C10: GL income statement
A11: Realization % | B11: =B10/B9 | C11: actual ÷ card value
A12: Implied realized rate ($/hr) | B12: =B10*1000/B7 | C12: calc
A13: Unexplained gap ($K) | B13: =B9-B10 | C13: to be decomposed below
A14: Direct labor cost ($K, GL) | B14: ='GL Income Stmt'!E7/1000 | C14: Labor-Design Services YTD
A15: Direct labor cost per billable hour | B15: =B14*1000/B7 | C15: calc
A16: Labor multiplier — actual (rev ÷ direct labor) | B16: =B10/B14 | C16: GL YTD
A17: Labor multiplier — budget | B17: ='GL Income Stmt'!F5/'GL Income Stmt'!F7 | C17: budget assumes 2.60x; industry-healthy is ~2.5–3.0x
A19: Gap decomposition — fill after the finance review (must sum to the unexplained gap):
A20: Unbilled WIP / billing lag ($K) | B20: 0
A21: Write-offs & discounts ($K) | B21: 0
A22: Intercompany work at reduced rates ($K) | B22: 0
A23: Other / unreconciled ($K) | B23: 0
A24: Decomposition vs gap | B24: =SUM(B20:B23)-B13 | C24: should be 0 when fully explained
A27: Annualized revenue grid ($K) — current roster, utilization × realization
A28: Utilization ↓ / Realization → | B28: 0.6 | C28: 0.75 | D28: 0.9 | E28: 1
A29: 0.59 | B29: =Assumptions!B7*Assumptions!B5*$A29*B$28*$B$8/1000 | C29: =Assumptions!B7*Assumptions!B5*$A29*C$28*$B$8/1000 | D29: =Assumptions!B7*Assumptions!B5*$A29*D$28*$B$8/1000 | E29: =Assumptions!B7*Assumptions!B5*$A29*E$28*$B$8/1000
A30: 0.65 | B30: =Assumptions!B7*Assumptions!B5*$A30*B$28*$B$8/1000 | C30: =Assumptions!B7*Assumptions!B5*$A30*C$28*$B$8/1000 | D30: =Assumptions!B7*Assumptions!B5*$A30*D$28*$B$8/1000 | E30: =Assumptions!B7*Assumptions!B5*$A30*E$28*$B$8/1000
A31: 0.7 | B31: =Assumptions!B7*Assumptions!B5*$A31*B$28*$B$8/1000 | C31: =Assumptions!B7*Assumptions!B5*$A31*C$28*$B$8/1000 | D31: =Assumptions!B7*Assumptions!B5*$A31*D$28*$B$8/1000 | E31: =Assumptions!B7*Assumptions!B5*$A31*E$28*$B$8/1000
A32: 0.75 | B32: =Assumptions!B7*Assumptions!B5*$A32*B$28*$B$8/1000 | C32: =Assumptions!B7*Assumptions!B5*$A32*C$28*$B$8/1000 | D32: =Assumptions!B7*Assumptions!B5*$A32*D$28*$B$8/1000 | E32: =Assumptions!B7*Assumptions!B5*$A32*E$28*$B$8/1000
A34: Grid = active billable FTEs × hrs/FTE-yr × utilization × realization × blended card rate, in $K.
A35: Bottom-right cell (75% util, 100% realization) is the current-roster ceiling; compare against the $6,000K
A36: Year-2 goal to size the hiring plan (Phase 2).
A37: Multiplier view: budget expects 2.60x revenue per direct-labor dollar; actual is running ~1.29x. Both
A38: realization (price) and labor cost per billable hour feed this — salary data will separate the two.

Sheet Checks & Open Items
A1: Tie-outs across the KPI report and GL statements, and open questions
A4: Check | B4: Model | C4: Source | D4: Status
A5: CVR revenue YTD Jun ($K) vs GL | B5: ='Baseline P&L'!H5 | C5: 551 | D5: =IF(ABS(B5-C5)<=1.0,"TIES","CHECK")
A6: CVR gross profit YTD Jun ($K) vs GL | B6: ='Baseline P&L'!H7 | C6: 122.5 | D6: =IF(ABS(B6-C6)<=1.0,"TIES","CHECK")
A7: CVR net income YTD Jun ($K) vs GL | B7: ='Baseline P&L'!H10 | C7: -320.5 | D7: =IF(ABS(B7-C7)<=1.0,"TIES","CHECK")
A8: KPI Jan–May revenue ($K) vs GL (YTD−Jun) | B8: =SUM('Baseline P&L'!B5:F5) | C8: 426.7 | D8: =IF(ABS(B8-C8)<=1.0,"TIES","CHECK")
A9: KPI Jan–May net income ($K) vs GL (YTD−Jun) | B9: =SUM('Baseline P&L'!B10:F10) | C9: -304.7 | D9: =IF(ABS(B9-C9)<=1.0,"TIES","CHECK")
A10: Sales by customer sums to GL revenue ($) | B10: ='Cash Flow & Customers'!B24 | C10: 551013 | D10: =IF(ABS(B10-C10)<=2,"TIES","CHECK")
A11: Balance sheet balances (assets = L+E, $) | B11: ='Balance Sheet'!B10 | C11: 141807 | D11: =IF(ABS(B11-C11)<=1,"TIES","CHECK")
A12: EPC revenue YTD May ($K) | B12: ='HWC EPC Baseline'!G5 | C12: 1172.4 | D12: =IF(ABS(B12-C12)<=1.0,"TIES","CHECK")
A13: EPC net profit YTD May ($K) | B13: ='HWC EPC Baseline'!G6 | C13: -2109.3 | D13: =IF(ABS(B13-C13)<=1.0,"TIES","CHECK")
A14: Billable hours YTD | B14: ='Roster & Hours'!I18 | C14: 4747 | D14: =IF(ABS(B14-C14)<=60,"TIES","CHECK")
A15: Billable-hours tolerance is wider: ~193 hrs on the KPI page are not attributed to a named employee.
A17: ANSWERED BY THE 6/30 GL STATEMENTS
A18: ✓ Corporate overhead allocation: $17,250/month flat ($103,500 YTD), same in budget.
A19: ✓ Interest basis: ~$5K/month accruing on the $3.44M Note Payable-Parent; not budgeted.
A20: ✓ Intercompany treatment: CVR hours on HWC jobs are revenue-credited as intercompany sales (~20% of YTD revenue).
A21: ✓ Employment burden: ~33.8% of total wages, computed from GL burden lines (refine with salary detail).
A22: ✓ Subcontract usage: none in 2026 (PY carried $218K at a loss).
A23: ✓ Full-year budget: +$139.4K net income, requiring a strong H2 swing.
A25: STILL OPEN (Phase 1 exit criteria)
A26: • Finance: salaries by person (to split the multiplier gap between price/realization and labor cost per hour).
A27: • Finance: what drives June's negative Labor-Indirect (−$6,078) — reclass or credit?
A28: • Confirm billing classifications for Taylor Nelson and Kevin Metts (not on the org chart).
... A32: • Confirm whether the intercompany rate for HWC work uses the standard card or a discounted schedule.

Sheet Charts
A1: Charts — wired to the data tabs
A2: Native Excel charts driven by cell values: edit the data tabs and these redraw. Data blocks feeding them start at row 40.
A40: CHART DATA — cumulative revenue ($K)
A41: Month | B41: Jan 26 | C41: Feb 26 | D41: Mar 26 | E41: Apr 26 | F41: May 26 | G41: Jun 26
A42: Actual (cumulative) | B42: ='Baseline P&L'!B5 | C42: =B42+'Baseline P&L'!C5 | D42: =C42+'Baseline P&L'!D5 | E42: =D42+'Baseline P&L'!E5 | F42: =E42+'Baseline P&L'!F5 | G42: =F42+'Baseline P&L'!G5
A43: Plan (cumulative) | B43: ='Baseline P&L'!B14 | C43: =B43+'Baseline P&L'!C14 | D43: =C43+'Baseline P&L'!D14 | E43: =D43+'Baseline P&L'!E14 | F43: =E43+'Baseline P&L'!F14 | G43: =F43+'Baseline P&L'!G14
A44: Prior year (pace) | B44: 66.5 | C44: 133 | D44: 199.6 | E44: 266.1 | F44: 332.6 | G44: 399.1
A46: CHART DATA — gross margin %
A47: Gross margin % | B47: ='Baseline P&L'!B8 | C47: ='Baseline P&L'!C8 | D47: ='Baseline P&L'!D8 | E47: ='Baseline P&L'!E8 | F47: ='Baseline P&L'!F8 | G47: ='Baseline P&L'!G8
A48: Budget assumption | B48: 0.6157 | C48: 0.6157 | D48: 0.6157 | E48: 0.6157 | F48: 0.6157 | G48: 0.6157
