Workbook
Name ALL: CVRIS!$A$1:$A$73
Name PRINT_AREA_MI: CVRIS!$A$1:$A$73

Sheet Key Assumptions
A1: Key Assumptions:
A2: Revenue to be calculated based on amount of Billable Hours
A3: Total Hrs = (52 wks x 40 hrs/wk) +
A4: Non-Billable Hours = administrative, down time, and other non-billable time - assumed at 15%
A5: Bids = preliminary design and proposal development efforts - assumed at 20%
A6: Bill Rate takes into account most conservativce hourly billing rate (e.g. Roy can be billed as Principal or Senior Engineer)
A7: CVR Engineering administrative tasks (invoicing, tracking, etc.) to be taken care of by Roy & Angelina
A8: USC Allocations based on time breakdown (%) as indicated on 2026 Special Projects Budget
A10: Budget File Review:
A11: Revenues and growth opportunities
A12: Expense Structure
A13: Balance Sheet
... A18: Successful bids
A22: CVR Sales | B22: 2026 Budget | C22: 2025 Actual | D22: 2025 Budget
B23: =CVRIS!T7 -> 2029126.3 | C23: =CVRIS!F7 -> 1827505 | D23: =CVRIS!D7 -> 2535921.5
A24: % Change | B24: =B23/C23-1 -> 0.11032599 | C24: =C23/D23-1 -> -0.2793527
A26: HW Sales by Region | B26: 2022 Budget | C26: 2021 Actual
A27: North | B27: =+#REF!+(1700000/3) -> #REF! | C27: =116442781+6826 -> 116449607
A28: South | B28: =+#REF!+(1700000/3) -> #REF! | C28: =66183990-253380 -> 65930610
A29: West | B29: =+#REF!+(1700000/3) -> #REF! | C29: 30792106
A30: Storm Chasers | B30: =+#REF! -> #REF! | C30: 34492771
A31: Storm - Mutual Aid | B31: =+#REF! -> #REF! | C31: 9524425
B32: =SUM(B27:B31) -> #REF! | C32: =SUM(C27:C31) -> 257189519
A34: CVR Billable Labor hours | B34: =B22 -> 2026 Budget | C34: =C22 -> 2025 Actual | D34: =D22 -> 2025 Budget
B35: ='Labor Rates-DP'!F45 -> 14205 | C35: 0 | D35: 16201
A36: % Change | B36: =B35/C35-1 -> #DIV/0! | C36: =C35/D35-1 -> -1
A38: CVR Non-Billable Labor hours | B38: =B22 -> 2026 Budget | C38: =C22 -> 2025 Actual | D38: =D22 -> 2025 Budget
B39: ='Labor Rates-DP'!B45-'Labor Rates-DP'!F45 -> 6015 | C39: 2740 | D39: =22382-16201 -> 6181
A40: % Change | B40: =B39/C39-1 -> 1.1952555 | C40: =C39/D39-1 -> -0.55670603
A42: CVR Gross Profit $ and % | B42: =B22 -> 2026 Budget | C42: 2022 Actual | D42: 2022 Budget
B43: =+CVRIS!T18 -> 1249362.8 | C43: =CVRIS!B18 -> 463486 | D43: 0
A44: % Change | B44: =B43/C43-1 -> 1.6955782 | C44: =C43/D43-1 -> #DIV/0!
A46: Gross Profit % | B46: =+B43/CVRIS!#REF! -> #REF! | C46: 0 | D46: 0
A48: CVR Net Income $ and % | B48: =B22 -> 2026 Budget | C48: =C22 -> 2025 Actual | D48: =D22 -> 2025 Budget
B49: =+CVRIS!T73 -> 139398.56 | C49: =CVRIS!F73 -> -487054 | D49: =CVRIS!D73 -> 215414.2
A50: % Change | B50: =B49/C49-1 -> -1.2862076 | C50: =C49/D49-1 -> -3.2610115
A52: Net Income as a % to sales | B52: =B49/B23 -> 0.068698808 | C52: =C49/C23 -> -0.26651309 | D52: =D49/D23 -> 0.084945138
A54: CVR Cap Ex | B54: =B22 -> 2026 Budget | C54: =C22 -> 2025 Actual | D54: =D22 -> 2025 Budget
B55: =CVRSCF!F22 -> 0 | C55: =CVRSCF!D22 -> 0 | D55: 0
A56: % Change | B56: 0 | C56: 0
A58: CVR Cash Flow | B58: =B22 -> 2026 Budget | C58: =C22 -> 2025 Actual | D58: =D22 -> 2025 Budget
B59: =+-CVRSCF!F31 -> 157782 | C59: =-CVRSCF!D31 -> -481997 | D59: -233401

Sheet CVRIS
B1: Actual | C1: % | D1: Budget | E1: % | F1: Actual | G1: % | T1: Annual | U1: %
B2: YTD | C2: To | D2: YTD | E2: To | F2: YTD | G2: To | T2: Budget | U2: To
B3: 45657 | C3: Sales | D3: 46022 | E3: Sales | F3: 46022 | G3: Sales | H3: Jan | I3: Feb | J3: Mar | K3: Apr | L3: May | M3: Jun | N3: July | O3: Aug | P3: Sept | Q3: Oct | R3: Nov | S3: Dec | T3: 46387 | U3: Sales
A4: CONTRACT REVENUES EARNED
A5: Sales-EPC | B5: 1044746 | C5: =B5/B7*100 -> 100 | D5: 2535921.5 | E5: =D5/D7*100 -> 100 | F5: 1827505 | G5: =F5/F7*100 -> 100 | H5: ='06-60 EPC'!C59 -> 169093.86 | I5: ='06-60 EPC'!D59 -> 169093.86 | J5: ='06-60 EPC'!E59 -> 169093.86 | K5: ='06-60 EPC'!F59 -> 169093.86 | L5: ='06-60 EPC'!G59 -> 169093.86 | M5: ='06-60 EPC'!H59 -> 169093.86 | N5: ='06-60 EPC'!I59 -> 169093.86 | O5: ='06-60 EPC'!J59 -> 169093.86 | ... S5: ='06-60 EPC'!N59 -> 169093.86 | T5: =SUM(H5:S5) -> 2029126.3 | U5: =T5/T7*100 -> 100
A6: Work in Process Adjmt.-Labor | B6: 0 | C6: =B6/B7*100 -> 0 | D6: 0 | E6: =D6/D7*100 -> 0 | F6: 0 | G6: =F6/F7*100 -> 0 | H6: 0 | I6: 0 | J6: 0 | K6: 0 | L6: 0 | M6: 0 | N6: 0 | O6: 0 | P6: 0 | Q6: 0 | R6: 0 | S6: 0 | T6: =SUM(H6:S6) -> 0 | U6: =T6/T7*100 -> 0
A7: Total Revenues | B7: =SUM(B5:B6) -> 1044746 | C7: =B7/B7*100 -> 100 | D7: =SUM(D5:D6) -> 2535921.5 | E7: =D7/D7*100 -> 100 | F7: =SUM(F5:F6) -> 1827505 | G7: =F7/F7*100 -> 100 | H7: =SUM(H5:H6) -> 169093.86 | I7: =SUM(I5:I6) -> 169093.86 | J7: =SUM(J5:J6) -> 169093.86 | K7: =SUM(K5:K6) -> 169093.86 | L7: =SUM(L5:L6) -> 169093.86 | M7: =SUM(M5:M6) -> 169093.86 | N7: =SUM(N5:N6) -> 169093.86 | O7: =SUM(O5:O6) -> 169093.86 | ... T7: =SUM(T5:T6) -> 2029126.3 | U7: =T7/T7*100 -> 100
B8: 0 | D8: 0 | F8: 0 | H8: =IF(H7='Revenue and Direct Lbr'!B14," ",H7-'Revenue and Direct Lbr'!B14) | I8: =IF(I7='Revenue and Direct Lbr'!F14," ",I7-'Revenue and Direct Lbr'!F14) | J8: =IF(J7='Revenue and Direct Lbr'!J14," ",J7-'Revenue and Direct Lbr'!J14) | K8: =IF(K7='Revenue and Direct Lbr'!N14," ",K7-'Revenue and Direct Lbr'!N14) | L8: =IF(L7='Revenue and Direct Lbr'!R14," ",L7-'Revenue and Direct Lbr'!R14) | M8: =IF(M7='Revenue and Direct Lbr'!V14," ",M7-'Revenue and Direct Lbr'!V14) | N8: =IF(N7='Revenue and Direct Lbr'!Z14," ",N7-'Revenue and Direct Lbr'!Z14) | O8: =IF(O7='Revenue and Direct Lbr'!AD14," ",O7-'Revenue and Direct Lbr'!AD14) | P8: =IF(P7='Revenue and Direct Lbr'!AH14," ",P7-'Revenue and Direct Lbr'!AH14) | Q8: =IF(Q7='Revenue and Direct Lbr'!AL14," ",Q7-'Revenue and Direct Lbr'!AL14) | R8: =IF(R7='Revenue and Direct Lbr'!AP14," ",R7-'Revenue and Direct Lbr'!AP14) | S8: =IF(S7='Revenue and Direct Lbr'!AT14," ",S7-'Revenue and Direct Lbr'!AT14)
A10: COST OF REVENUES EARNED
C11: Labor | E11: Labor | G11: Labor
A12: DIRECT LABOR | C12: Ratio | E12: Ratio | G12: Ratio
A13: Labor-EPC | B13: 581260 | C13: =IF(B13=0,0,B5/B13) -> 1.7973816 | D13: 976681.13 | E13: =IF(D13=0,0,D5/D13) -> 2.5964682 | F13: 1128553 | G13: =IF(F13=0,0,F5/F13) -> 1.6193347 | H13: =+'06-60 EPC'!C67 -> 64980.295 | I13: ='06-60 EPC'!D67 -> 64980.295 | J13: ='06-60 EPC'!E67 -> 64980.295 | K13: ='06-60 EPC'!F67 -> 64980.295 | L13: ='06-60 EPC'!G67 -> 64980.295 | M13: ='06-60 EPC'!H67 -> 64980.295 | N13: ='06-60 EPC'!I67 -> 64980.295 | O13: ='06-60 EPC'!J67 -> 64980.295 | P13: ='06-60 EPC'!K67 -> 64980.295 | ... S13: ='06-60 EPC'!N67 -> 64980.295 | T13: =+SUM(H13:S13) -> 779763.54 | U13: =IF(T13=0,0,T5/T13) -> 2.6022328
A14: Total Direct Labor | B14: =SUM(B13:B13) -> 581260 | C14: =(B7/B14) -> 1.7973816 | D14: =SUM(D13:D13) -> 976681.13 | E14: =(D7/D14) -> 2.5964682 | F14: =SUM(F13:F13) -> 1128553 | G14: =(F7/F14) -> 1.6193347 | H14: =SUM(H13:H13) -> 64980.295 | I14: =SUM(I13:I13) -> 64980.295 | J14: =SUM(J13:J13) -> 64980.295 | K14: =SUM(K13:K13) -> 64980.295 | L14: =SUM(L13:L13) -> 64980.295 | M14: =SUM(M13:M13) -> 64980.295 | N14: =SUM(N13:N13) -> 64980.295 | O14: =SUM(O13:O13) -> 64980.295 | ... T14: =SUM(T13:T13) -> 779763.54 | U14: =(T7/T14) -> 2.6022328
B15: 0 | D15: 0 | F15: 0 | H15: =IF(H14='Revenue and Direct Lbr'!D14," ",H14-'Revenue and Direct Lbr'!D14) | I15: =IF(I14='Revenue and Direct Lbr'!H14," ",I14-'Revenue and Direct Lbr'!H14) | J15: =IF(J14='Revenue and Direct Lbr'!L14," ",J14-'Revenue and Direct Lbr'!L14) | K15: =IF(K14='Revenue and Direct Lbr'!P14," ",K14-'Revenue and Direct Lbr'!P14) | L15: =IF(L14='Revenue and Direct Lbr'!T14," ",L14-'Revenue and Direct Lbr'!T14) | M15: =IF(M14='Revenue and Direct Lbr'!X14," ",M14-'Revenue and Direct Lbr'!X14) | N15: =IF(N14='Revenue and Direct Lbr'!AB14," ",N14-'Revenue and Direct Lbr'!AB14) | O15: =IF(O14='Revenue and Direct Lbr'!AF14," ",O14-'Revenue and Direct Lbr'!AF14) | P15: =IF(P14='Revenue and Direct Lbr'!AJ14," ",P14-'Revenue and Direct Lbr'!AJ14) | Q15: =IF(Q14='Revenue and Direct Lbr'!AN14," ",Q14-'Revenue and Direct Lbr'!AN14) | R15: =IF(R14='Revenue and Direct Lbr'!AR14," ",R14-'Revenue and Direct Lbr'!AR14) | S15: =IF(S14='Revenue and Direct Lbr'!AV14," ",S14-'Revenue and Direct Lbr'!AV14) | T15: =T14/T7 -> 0.38428536
A18: Gross Profit | B18: =B7-B14 -> 463486 | C18: =B18/B7*100 -> 44.36351 | D18: =D7-D14 -> 1559240.4 | E18: =D18/D7*100 -> 61.486146 | F18: =F7-F14 -> 698952 | G18: =F18/F7*100 -> 38.246243 | H18: =H7-H14 -> 104113.56 | I18: =I7-I14 -> 104113.56 | J18: =J7-J14 -> 104113.56 | K18: =K7-K14 -> 104113.56 | L18: =L7-L14 -> 104113.56 | M18: =M7-M14 -> 104113.56 | N18: =N7-N14 -> 104113.56 | O18: =O7-O14 -> 104113.56 | ... T18: =T7-T14 -> 1249362.8 | U18: =T18/T7*100 -> 61.571464
A21: OPERATING EXPENSES
A22: Labor- Indirect | B22: 143759 | C22: =B22/$B$7*100 -> 13.760187 | D22: 372623.05 | E22: =D22/$D$7*100 -> 14.693793 | F22: =163088+3 -> 163091 | G22: =F22/$F$7*100 -> 8.9242437 | H22: ='Operating Exp'!B8 -> 22235.646 | I22: ='Operating Exp'!C8 -> 22235.646 | J22: ='Operating Exp'!D8 -> 22235.646 | K22: ='Operating Exp'!E8 -> 22235.646 | L22: ='Operating Exp'!F8 -> 22235.646 | M22: ='Operating Exp'!G8 -> 22235.646 | N22: ='Operating Exp'!H8 -> 22235.646 | O22: ='Operating Exp'!I8 -> 22235.646 | ... S22: ='Operating Exp'!M8 -> 22235.646 | T22: =SUM(H22:S22) -> 266827.75 | U22: =T22/$T$7*100 -> 13.149884
A23: Employee Vac and Hol Pay | B23: 0 | C23: =B23/$B$7*100 -> 0 | D23: 0 | E23: =D23/$D$7*100 -> 0 | F23: 145865 | G23: =F23/$F$7*100 -> 7.9816471 | H23: ='Operating Exp'!B9 -> 5279.7697 | I23: ='Operating Exp'!C9 -> 5279.7697 | J23: ='Operating Exp'!D9 -> 5279.7697 | K23: ='Operating Exp'!E9 -> 5279.7697 | L23: ='Operating Exp'!F9 -> 5279.7697 | M23: ='Operating Exp'!G9 -> 5279.7697 | N23: ='Operating Exp'!H9 -> 5279.7697 | O23: ='Operating Exp'!I9 -> 5279.7697 | ... S23: ='Operating Exp'!M9 -> 5279.7697 | T23: =SUM(H23:S23) -> 63357.237 | U23: =T23/$T$7*100 -> 3.12239
A24: FICA Expense | B24: 62045 | C24: =B24/$B$7*100 -> 5.9387641 | D24: 100152.63 | E24: =D24/$D$7*100 -> 3.9493585 | F24: 90211 | G24: =F24/$F$7*100 -> 4.9362929 | H24: ='Operating Exp'!B10 -> 7003.0694 | I24: ='Operating Exp'!C10 -> 7003.0694 | J24: ='Operating Exp'!D10 -> 7003.0694 | K24: ='Operating Exp'!E10 -> 7003.0694 | L24: ='Operating Exp'!F10 -> 7003.0694 | M24: ='Operating Exp'!G10 -> 7003.0694 | N24: ='Operating Exp'!H10 -> 7003.0694 | O24: ='Operating Exp'!I10 -> 7003.0694 | ... S24: ='Operating Exp'!M10 -> 7003.0694 | T24: =SUM(H24:S24) -> 84036.832 | U24: =T24/$T$7*100 -> 4.1415279
A25: FUTA Expense | B25: 503 | C25: =B25/$B$7*100 -> 0.048145674 | D25: 728 | E25: =D25/$D$7*100 -> 0.028707513 | F25: 646 | G25: =F25/$F$7*100 -> 0.03534874 | H25: ='Operating Exp'!B11 -> 37.37821 | I25: ='Operating Exp'!C11 -> 37.37821 | J25: ='Operating Exp'!D11 -> 37.37821 | K25: ='Operating Exp'!E11 -> 37.37821 | L25: ='Operating Exp'!F11 -> 37.37821 | M25: ='Operating Exp'!G11 -> 37.37821 | N25: ='Operating Exp'!H11 -> 37.37821 | O25: ='Operating Exp'!I11 -> 37.37821 | ... S25: ='Operating Exp'!M11 -> 37.37821 | T25: =SUM(H25:S25) -> 448.53852 | U25: =T25/$T$7*100 -> 0.022105007
A26: State Unemployment Expense | B26: 4099 | C26: =B26/$B$7*100 -> 0.39234417 | D26: 10822.5 | E26: =D26/$D$7*100 -> 0.42676794 | F26: 2636 | G26: =F26/$F$7*100 -> 0.14424037 | H26: ='Operating Exp'!B12 -> 208.70194 | I26: ='Operating Exp'!C12 -> 208.70194 | J26: ='Operating Exp'!D12 -> 208.70194 | K26: ='Operating Exp'!E12 -> 208.70194 | L26: ='Operating Exp'!F12 -> 208.70194 | M26: ='Operating Exp'!G12 -> 208.70194 | N26: ='Operating Exp'!H12 -> 208.70194 | O26: ='Operating Exp'!I12 -> 208.70194 | ... S26: ='Operating Exp'!M12 -> 208.70194 | T26: =SUM(H26:S26) -> 2504.4233 | U26: =T26/$T$7*100 -> 0.12342373
A27: Mileage Expense | B27: 49 | C27: =B27/$B$7*100 -> 0.0046901352 | D27: 0 | E27: =D27/$D$7*100 -> 0 | F27: 186 | G27: =F27/$F$7*100 -> 0.010177811 | H27: ='Operating Exp'!B13 -> 0 | I27: ='Operating Exp'!C13 -> 0 | J27: ='Operating Exp'!D13 -> 0 | K27: ='Operating Exp'!E13 -> 0 | L27: ='Operating Exp'!F13 -> 0 | M27: ='Operating Exp'!G13 -> 0 | N27: ='Operating Exp'!H13 -> 0 | O27: ='Operating Exp'!I13 -> 0 | ... S27: ='Operating Exp'!M13 -> 0 | T27: =SUM(H27:S27) -> 0 | U27: =T27/$T$7*100 -> 0
A28: Repair & Maint Equip | B28: 92 | C28: =B28/$B$7*100 -> 0.0088059681 | D28: 92 | E28: =D28/$D$7*100 -> 0.0036278725 | F28: 397 | G28: =F28/$F$7*100 -> 0.021723607 | H28: ='Operating Exp'!B14 -> 19.027778 | I28: ='Operating Exp'!C14 -> 19.027778 | J28: ='Operating Exp'!D14 -> 19.027778 | K28: ='Operating Exp'!E14 -> 19.027778 | L28: ='Operating Exp'!F14 -> 19.027778 | M28: ='Operating Exp'!G14 -> 19.027778 | N28: ='Operating Exp'!H14 -> 19.027778 | O28: ='Operating Exp'!I14 -> 19.027778 | ... S28: ='Operating Exp'!M14 -> 19.027778 | T28: =SUM(H28:S28) -> 228.33333 | U28: =T28/$T$7*100 -> 0.011252791
A29: Fuel Expense | B29: 267 | C29: =B29/$B$7*100 -> 0.025556451 | D29: 0 | E29: =D29/$D$7*100 -> 0 | F29: 330 | G29: =F29/$F$7*100 -> 0.018057406 | H29: ='Operating Exp'!B15 -> 20.194444 | I29: ='Operating Exp'!C15 -> 20.194444 | J29: ='Operating Exp'!D15 -> 20.194444 | K29: ='Operating Exp'!E15 -> 20.194444 | L29: ='Operating Exp'!F15 -> 20.194444 | M29: ='Operating Exp'!G15 -> 20.194444 | N29: ='Operating Exp'!H15 -> 20.194444 | O29: ='Operating Exp'!I15 -> 20.194444 | ... S29: ='Operating Exp'!M15 -> 20.194444 | T29: =SUM(H29:S29) -> 242.33333 | U29: =T29/$T$7*100 -> 0.011942743
A30: Licenses & Permits | B30: 9790 | C30: =B30/$B$7*100 -> 0.93706987 | D30: 4200 | E30: =D30/$D$7*100 -> 0.16562027 | F30: 606 | G30: =F30/$F$7*100 -> 0.033159964 | H30: ='Operating Exp'!B16 -> 183.33333 | I30: ='Operating Exp'!C16 -> 183.33333 | J30: ='Operating Exp'!D16 -> 183.33333 | K30: ='Operating Exp'!E16 -> 183.33333 | L30: ='Operating Exp'!F16 -> 183.33333 | M30: ='Operating Exp'!G16 -> 183.33333 | N30: ='Operating Exp'!H16 -> 183.33333 | O30: ='Operating Exp'!I16 -> 183.33333 | ... S30: ='Operating Exp'!M16 -> 183.33333 | T30: =SUM(H30:S30) -> 2200 | U30: =T30/$T$7*100 -> 0.10842105
A31: Machinery Rental | B31: 546 | C31: =B31/$B$7*100 -> 0.052261507 | D31: 0 | E31: =D31/$D$7*100 -> 0 | F31: 830 | G31: =F31/$F$7*100 -> 0.045417112 | H31: ='Operating Exp'!B17 -> 47.5 | I31: ='Operating Exp'!C17 -> 47.5 | J31: ='Operating Exp'!D17 -> 47.5 | K31: ='Operating Exp'!E17 -> 47.5 | L31: ='Operating Exp'!F17 -> 47.5 | M31: ='Operating Exp'!G17 -> 47.5 | N31: ='Operating Exp'!H17 -> 47.5 | O31: ='Operating Exp'!I17 -> 47.5 | ... S31: ='Operating Exp'!M17 -> 47.5 | T31: =SUM(H31:S31) -> 570 | U31: =T31/$T$7*100 -> 0.028090908
A32: Safety Expense | B32: 80 | C32: =B32/$B$7*100 -> 0.0076573636 | D32: 0 | E32: =D32/$D$7*100 -> 0 | F32: 99 | G32: =F32/$F$7*100 -> 0.0054172218 | H32: ='Operating Exp'!B18 -> 70.166667 | I32: ='Operating Exp'!C18 -> 70.166667 | J32: ='Operating Exp'!D18 -> 70.166667 | K32: ='Operating Exp'!E18 -> 70.166667 | L32: ='Operating Exp'!F18 -> 70.166667 | M32: ='Operating Exp'!G18 -> 70.166667 | N32: ='Operating Exp'!H18 -> 70.166667 | O32: ='Operating Exp'!I18 -> 70.166667 | ... S32: ='Operating Exp'!M18 -> 70.166667 | T32: =SUM(H32:S32) -> 842 | U32: =T32/$T$7*100 -> 0.041495692
A33: General Insurance | B33: 34640 | C33: =B33/$B$7*100 -> 3.3156384 | D33: 38000 | E33: =D33/$D$7*100 -> 1.4984691 | F33: 35810 | G33: =F33/$F$7*100 -> 1.9595022 | H33: ='Operating Exp'!B19 -> 5000 | I33: ='Operating Exp'!C19 -> 5000 | J33: ='Operating Exp'!D19 -> 5000 | K33: ='Operating Exp'!E19 -> 5000 | L33: ='Operating Exp'!F19 -> 5000 | M33: ='Operating Exp'!G19 -> 5000 | N33: ='Operating Exp'!H19 -> 5000 | O33: ='Operating Exp'!I19 -> 5000 | ... S33: ='Operating Exp'!M19 -> 5000 | T33: =SUM(H33:S33) -> 60000 | U33: =T33/$T$7*100 -> 2.9569377
A34: Work Comp Insurance | B34: 9056 | C34: =B34/$B$7*100 -> 0.86681356 | D34: 13167.22 | E34: =D34/$D$7*100 -> 0.51922821 | F34: 13308 | G34: =F34/$F$7*100 -> 0.72820594 | H34: ='Operating Exp'!B20 -> 924.9571 | I34: ='Operating Exp'!C20 -> 924.9571 | J34: ='Operating Exp'!D20 -> 924.9571 | K34: ='Operating Exp'!E20 -> 924.9571 | L34: ='Operating Exp'!F20 -> 924.9571 | M34: ='Operating Exp'!G20 -> 924.9571 | N34: ='Operating Exp'!H20 -> 924.9571 | O34: ='Operating Exp'!I20 -> 924.9571 | ... S34: ='Operating Exp'!M20 -> 924.9571 | T34: =SUM(H34:S34) -> 11099.485 | U34: =T34/$T$7*100 -> 0.5470081
... A58: Corporate Overhead Allocation | B58: 369009 | C58: =B58/$B$7*100 -> 35.320451 | D58: 276996 | E58: =D58/$D$7*100 -> 10.922893 | F58: 278036 | G58: =F58/$F$7*100 -> 15.213967 | H58: ='Operating Exp'!B44 -> 17250 | I58: ='Operating Exp'!C44 -> 17250 | J58: ='Operating Exp'!D44 -> 17250 | K58: ='Operating Exp'!E44 -> 17250 | L58: ='Operating Exp'!F44 -> 17250 | M58: ='Operating Exp'!G44 -> 17250 | N58: ='Operating Exp'!H44 -> 17250 | O58: ='Operating Exp'!I44 -> 17250 | ... S58: ='Operating Exp'!M44 -> 17250 | T58: =SUM(H58:S58) -> 207000 | U58: =T58/$T$7*100 -> 10.201435
A59: Total Operating Expenses | B59: =SUM(B22:B58) -> 1084600 | C59: =B59/$B$7*100 -> 103.81471 | D59: =SUM(D22:D58) -> 1343826.2 | E59: =D59/$D$7*100 -> 52.991632 | F59: =SUM(F22:F58) -> 1129514 | G59: =F59/$F$7*100 -> 61.806343 | H59: =SUM(H22:H58) -> 92497.017 | I59: =SUM(I22:I58) -> 92497.017 | J59: =SUM(J22:J58) -> 92497.017 | K59: =SUM(K22:K58) -> 92497.017 | L59: =SUM(L22:L58) -> 92497.017 | M59: =SUM(M22:M58) -> 92497.017 | N59: =SUM(N22:N58) -> 92497.017 | O59: =SUM(O22:O58) -> 92497.017 | ... T59: =SUM(T22:T58) -> 1109964.2 | U59: =T59/$T$7*100 -> 54.701583
A61: Operating Income/(Loss) | B61: =B18-B59 -> -621114 | C61: =B61/$B$7*100 -> -59.451197 | D61: =D18-D59 -> 215414.2 | E61: =D61/$D$7*100 -> 8.4945138 | F61: =F18-F59 -> -430562 | G61: =F61/$F$7*100 -> -23.5601 | H61: =H18-H59 -> 11616.546 | I61: =I18-I59 -> 11616.546 | J61: =J18-J59 -> 11616.546 | K61: =K18-K59 -> 11616.546 | L61: =L18-L59 -> 11616.546 | M61: =M18-M59 -> 11616.546 | N61: =N18-N59 -> 11616.546 | O61: =O18-O59 -> 11616.546 | ... T61: =T18-T59 -> 139398.56 | U61: =T61/$T$7*100 -> 6.8698808
A63: OTHER (INCOME)/EXPENSE
A64: Interest Income | B64: 0 | C64: =B64/$B$7*100 -> 0 | D64: 0 | E64: =D64/$D$7*100 -> 0 | F64: 0 | G64: =F64/$F$7*100 -> 0 | H64: 0 | I64: 0 | J64: 0 | K64: 0 | L64: 0 | M64: 0 | N64: 0 | O64: 0 | P64: 0 | Q64: 0 | R64: 0 | S64: 0 | T64: =SUM(H64:S64) -> 0 | U64: =T64/$T$7*100 -> 0
A65: Interest Expense | B65: 53840 | C65: =B65/$B$7*100 -> 5.1534057 | D65: 0 | E65: =D65/$D$7*100 -> 0 | F65: 56492 | G65: =F65/$F$7*100 -> 3.0912091 | H65: =+'Corp OH Alloc & Interest Exp'!$C$5/12 -> 0 | I65: =+'Corp OH Alloc & Interest Exp'!$C$5/12 -> 0 | J65: =+'Corp OH Alloc & Interest Exp'!$C$5/12 -> 0 | K65: =+'Corp OH Alloc & Interest Exp'!$C$5/12 -> 0 | L65: =+'Corp OH Alloc & Interest Exp'!$C$5/12 -> 0 | M65: =+'Corp OH Alloc & Interest Exp'!$C$5/12 -> 0 | N65: =+'Corp OH Alloc & Interest Exp'!$C$5/12 -> 0 | O65: =+'Corp OH Alloc & Interest Exp'!$C$5/12 -> 0 | ... S65: =+'Corp OH Alloc & Interest Exp'!$C$5/12 -> 0 | T65: =SUM(H65:S65) -> 0 | U65: =T65/$T$7*100 -> 0
A66: (Gain)/Loss on Sale of Assets | B66: 0 | C66: =B66/$B$7*100 -> 0 | D66: 0 | E66: =D66/$D$7*100 -> 0 | F66: 0 | G66: =F66/$F$7*100 -> 0 | H66: 0 | I66: 0 | J66: 0 | K66: 0 | L66: 0 | M66: 0 | N66: 0 | O66: 0 | P66: 0 | Q66: 0 | R66: 0 | S66: 0 | T66: =SUM(H66:S66) -> 0 | U66: =T66/$T$7*100 -> 0
A67: Total Other (Income)/Expense | B67: =SUM(B64:B66) -> 53840 | C67: =B67/$B$7*100 -> 5.1534057 | D67: =SUM(D64:D66) -> 0 | E67: =D67/$D$7*100 -> 0 | F67: =SUM(F64:F66) -> 56492 | G67: =F67/$F$7*100 -> 3.0912091 | H67: =SUM(H64:H66) -> 0 | I67: =SUM(I64:I66) -> 0 | J67: =SUM(J64:J66) -> 0 | K67: =SUM(K64:K66) -> 0 | L67: =SUM(L64:L66) -> 0 | M67: =SUM(M64:M66) -> 0 | N67: =SUM(N64:N66) -> 0 | O67: =SUM(O64:O66) -> 0 | ... T67: =SUM(T64:T66) -> 0 | U67: =T67/$T$7*100 -> 0
A69: Income Before Income Taxes | B69: =B61-B67 -> -674954 | C69: =B69/$B$7*100 -> -64.604602 | D69: =D61-D67 -> 215414.2 | E69: =D69/$D$7*100 -> 8.4945138 | F69: =F61-F67 -> -487054 | G69: =F69/$F$7*100 -> -26.651309 | H69: =H61-H67 -> 11616.546 | I69: =I61-I67 -> 11616.546 | J69: =J61-J67 -> 11616.546 | K69: =K61-K67 -> 11616.546 | L69: =L61-L67 -> 11616.546 | M69: =M61-M67 -> 11616.546 | N69: =N61-N67 -> 11616.546 | O69: =O61-O67 -> 11616.546 | ... T69: =T61-T67 -> 139398.56 | U69: =T69/$T$7*100 -> 6.8698808
A71: Federal Income Tax Exp. | B71: =B69*0 -> 0 | C71: =B71/$B$7*100 -> 0 | D71: =D69*0 -> 0 | E71: =D71/$D$7*100 -> 0 | F71: =F69*0 -> 0 | G71: =F71/$F$7*100 -> 0 | H71: =H69*0 -> 0 | I71: =I69*0 -> 0 | J71: =J69*0 -> 0 | K71: =K69*0 -> 0 | L71: =L69*0 -> 0 | M71: =M69*0 -> 0 | N71: =N69*0 -> 0 | O71: =O69*0 -> 0 | ... T71: =T69*0 -> 0 | U71: =T71/$T$7*100 -> 0
A73: Net Income/(Loss) | B73: =B69-B71 -> -674954 | C73: =B73/$B$7*100 -> -64.604602 | D73: =D69-D71 -> 215414.2 | E73: =D73/$D$7*100 -> 8.4945138 | F73: =F69-F71 -> -487054 | G73: =F73/$F$7*100 -> -26.651309 | H73: =H69-H71 -> 11616.546 | I73: =I69-I71 -> 11616.546 | J73: =J69-J71 -> 11616.546 | K73: =K69-K71 -> 11616.546 | L73: =L69-L71 -> 11616.546 | M73: =M69-M71 -> 11616.546 | N73: =N69-N71 -> 11616.546 | O73: =O69-O71 -> 11616.546 | ... T73: =T69-T71 -> 139398.56 | U73: =T73/$T$7*100 -> 6.8698808

Sheet CVRBS
B1: Actual | D1: Actual | F1: Budgeted
B2: At | D2: At | E2: 2026 | F2: At
B3: 45657 | C3: Change | D3: 46022 | E3: Change | F3: 46387
A4: ASSETS
A6: CURRENT ASSETS
A7: Cash | B7: 0 | C7: 0 | D7: 0 | E7: 0 | F7: =SUM(D7:E7) -> 0
A8: Accounts Receivable (Budget = 60 days) | B8: 17987 | C8: 0 | D8: 40886 | E8: -10886 | F8: =SUM(D8:E8) -> 30000
A9: Contracts Receivable - Unbilled | B9: 0 | C9: 0 | D9: 0 | E9: 0 | F9: =SUM(D9:E9) -> 0
A10: WIP-Cost + Earnings > Billings | B10: 0 | C10: 0 | D10: 0 | E10: 0 | F10: =SUM(D10:E10) -> 0
A11: Material Inventory | B11: 0 | C11: 0 | D11: 0 | E11: 0 | F11: =SUM(D11:E11) -> 0
A12: Prepaid Consulting Fees | B12: 0 | C12: 0 | D12: 0 | E12: 0 | F12: =SUM(D12:E12) -> 0
A13: Prepaid Insurance | B13: 0 | C13: 0 | D13: 6000 | E13: 0 | F13: =SUM(D13:E13) -> 6000
A14: Total Current Assets | B14: =SUM(B7:B13) -> 17987 | C14: =SUM(C7:C13) -> 0 | D14: =SUM(D7:D13) -> 46886 | E14: =SUM(E7:E13) -> -10886 | F14: =SUM(F7:F13) -> 36000
A16: FIXED ASSETS
A17: Buildings & Improvements | B17: 0 | C17: 0 | D17: 0 | E17: 0 | F17: =SUM(D17:E17) -> 0
A18: Assets In Progress | B18: 0 | C18: 0 | D18: 0 | E18: 0 | F18: =SUM(D18:E18) -> 0
A19: Machinery & Equipment | B19: 0 | C19: 0 | D19: 0 | E19: 0 | F19: =SUM(D19:E19) -> 0
A20: Office Equipment | B20: 0 | C20: 0 | D20: 0 | E20: 0 | F20: =SUM(D20:E20) -> 0
A21: Tools | B21: 0 | C21: 0 | D21: 0 | E21: 0 | F21: =SUM(D21:E21) -> 0
A22: Total Cost | B22: =SUM(B17:B21) -> 0 | C22: =SUM(C17:C21) -> 0 | D22: =SUM(D17:D21) -> 0 | E22: =SUM(E17:E21) -> 0 | F22: =SUM(F17:F21) -> 0
A23: Accumulated Depreciation | B23: 0 | C23: 0 | D23: =SUM(B23:C23) -> 0 | E23: 0 | F23: =SUM(D23:E23) -> 0
A25: Net Fixed Asset | B25: =B22+B23 -> 0 | C25: =(C22+C23) -> 0 | D25: =(D22+D23) -> 0 | E25: =(E22+E23) -> 0 | F25: =(F22+F23) -> 0
A27: OTHER ASSETS
A28: Note Receivable-Parent-USC | B28: 0 | C28: 0 | D28: 0 | E28: 0 | F28: =SUM(D28:E28) -> 0
A29: Deferred Tax Asset | B29: 0 | C29: 0 | D29: 0 | E29: 0 | F29: =SUM(D29:E29) -> 0
B30: =SUM(B28:B29) -> 0 | C30: =SUM(C28:C29) -> 0 | D30: =SUM(D28:D29) -> 0 | E30: =SUM(E28:E29) -> 0 | F30: =SUM(F28:F29) -> 0
A32: Total Assets | B32: =(B14+B25+B30) -> 17987 | C32: =(C14+C25+C30) -> 0 | D32: =(D14+D25+D30) -> 46886 | E32: =(E14+E25+E30) -> -10886 | F32: =(F14+F25+F30) -> 36000
A34: LIABILITIES AND EQUITY
A36: CURRENT LIABILITIES
A37: Accounts Payable | B37: 81 | C37: 0 | D37: 0 | E37: 0 | F37: =SUM(D37:E37) -> 0
A38: Accrued Salaries and Wages | B38: =20250 -> 20250 | C38: 0 | D38: =40871+14049 -> 54920 | E38: -4920 | F38: =SUM(D38:E38) -> 50000 | G38: 10 to PTO, 40 to wages
A39: Accrued Bonus | B39: 70690 | C39: 0 | D39: 27300 | E39: =Labor!W16-D39 -> 27440.432 | F39: =SUM(D39:E39) -> 54740.432
A40: Accrued Insurance | B40: -34977 | C40: 0 | D40: -2365 | E40: -2635 | F40: =SUM(D40:E40) -> -5000
A41: Accrued Health Insurance Payable | B41: 2635 | C41: 0 | D41: 7373 | E41: =-2373 -> -2373 | F41: =SUM(D41:E41) -> 5000
A42: Accrued Interest | B42: 5539 | C42: 0 | D42: 11922 | E42: -11922 | F42: =SUM(D42:E42) -> 0
A43: Accrued Property Taxes | B43: 0 | C43: 0 | D43: 0 | E43: 0 | F43: =SUM(D43:E43) -> 0
A44: Accrued Payroll | B44: 0 | C44: 0 | D44: 3596 | E44: -1596 | F44: =SUM(D44:E44) -> 2000
A45: Accrued Employee Pension | B45: 16069 | C45: 0 | D45: 11497 | E45: 3503 | F45: =SUM(D45:E45) -> 15000
A46: Accrued Union Fringes | B46: 0 | C46: 0 | D46: 0 | E46: 0 | F46: =SUM(D46:E46) -> 0
A47: WIP-Billings > Cost + Earnings | B47: 0 | C47: 0 | D47: 0 | E47: 0 | F47: =SUM(D47:E47) -> 0
A48: Accrued Other Taxes Payable | B48: 0 | C48: 0 | D48: 0 | E48: 0 | F48: =SUM(D48:E48) -> 0
A49: Total Current Liabilities | B49: =SUM(B37:B48) -> 80287 | C49: =SUM(C37:C48) -> 0 | D49: =SUM(D37:D48) -> 114243 | E49: =SUM(E37:E48) -> 7497.4315 | F49: =SUM(F37:F48) -> 121740.43
A51: DEFERRED INCOME TAXES | B51: 0 | C51: 0 | D51: =SUM(B51:C51) -> 0 | E51: 0 | F51: =SUM(D51:E51) -> 0
A53: LONG-TERM DEBT
A54: Note Payable-Parent-USC | B54: 2477470 | C54: 0 | D54: 2959467 | E54: =CVRSCF!F31 -> -157782 | F54: =SUM(D54:E54) -> 2801685
A55: Note Payable-CBC | B55: 0 | C55: 0 | D55: 0 | E55: 0 | F55: =SUM(D55:E55) -> 0
A56: Total Long Term Debt | B56: =SUM(B54:B55) -> 2477470 | C56: =SUM(C54:C55) -> 0 | D56: =SUM(D54:D55) -> 2959467 | E56: =SUM(E54:E55) -> -157782 | F56: =SUM(F54:F55) -> 2801685
A58: Total Liabilities | B58: =(B49+B51+B56) -> 2557757 | C58: =(C49+C51+C56) -> 0 | D58: =(D49+D51+D56) -> 3073710 | E58: =(E49+E51+E56) -> -150284.57 | F58: =(F49+F51+F56) -> 2923425.4
A60: SHAREHOLDERS' EQUITY
A61: Common Stock | B61: 0 | C61: 0 | D61: 0 | E61: 0 | F61: =SUM(D61:E61) -> 0
A62: Membership Interest | B62: 500 | C62: 0 | D62: 500 | E62: 0 | F62: =SUM(D62:E62) -> 500
A63: Retained Earnings | B63: -1865315 | C63: 0 | D63: =B63+B64 -> -2540270 | E63: 0 | F63: =SUM(D63:D64) -> -3027324
A64: Net Income or (Loss) | B64: =CVRIS!B73-1 -> -674955 | C64: 0 | D64: =CVRIS!F73 -> -487054 | E64: =F64 -> 139398.56 | F64: =+CVRIS!T73 -> 139398.56
A66: Total Shareholders' Equity | B66: =SUM(B61:B64) -> -2539770 | C66: =SUM(C61:C64) -> 0 | D66: =SUM(D61:D64) -> -3026824 | E66: =SUM(E61:E64) -> 139398.56 | F66: =SUM(F61:F64) -> -2887425.4
A68: Total Liabilities and Equity | B68: =(B58+B66) -> 17987 | C68: =(C58+C66) -> 0 | D68: =(D58+D66) -> 46886 | E68: =(E58+E66) -> -10886.011 | F68: =(F58+F66) -> 35999.989 | G68: =F68-F32 -> -0.011145779
A71: Working Capital Ratio | B71: =(B14/B49) -> 0.22403378 | D71: =(D14/D49) -> 0.41040589 | F71: =(F14/F49) -> 0.29571113
A72: Debt to Equity Ratio | B72: =(B58/B66) -> -1.0070821 | D72: =(D58/D66) -> -1.0154902 | F72: =(F58/F66) -> -1.0124679
A73: Return on BOY Equity | B73: =IFERROR(B64/0,0) -> 0 | D73: =IFERROR(D64/0,0) -> 0 | F73: =IFERROR(F64/D66,0) -> -0.046054398
A74: EBITDA (CVR Only) | B74: =CVRIS!B73+CVRIS!B65 -> -621114 | D74: =CVRIS!F73+CVRIS!F65 -> -430562 | F74: =CVRIS!T73 -> 139398.56

Sheet CVRSCF
B1: Actual | D1: Actual | F1: Budgeted
B2: YTD | D2: YTD | F2: At
B3: 46022 | C3: Change | D3: =+CVRBS!D3 -> 46022 | F3: =+CVRBS!F3 -> 46387
A4: Cash Flows from Operating Activities
A5: Net Income/(Loss) | B5: -487054 | C5: =CVRBS!C63 -> 0 | D5: =SUM(B5:C5) -> -487054 | F5: =+CVRIS!T73 -> 139398.56
A6: Adjustments to reconcile net income to
A7: net cash used by operating activities:
A8: Depreciation | B8: 0 | C8: =-CVRBS!C23 -> 0 | D8: =SUM(B8:C8) -> 0 | F8: =-CVRBS!F23 -> 0
A9: (Gain)/Loss on Sale of Property and Eqpt. | B9: 0 | C9: 0 | D9: =SUM(B9:C9) -> 0 | F9: =+CVRIS!T66 -> 0
A10: Changes in operating assets and liabilities:
A11: Accounts Receivable | B11: -22899 | C11: 0 | D11: =SUM(B11:C11) -> -22899 | F11: =-CVRBS!E8 -> 10886
A12: Contracts Receivable | B12: 0 | C12: 0 | D12: =SUM(B12:C12) -> 0 | F12: =-CVRBS!E9 -> 0
A13: WIP-Cost + Earnings > Billings | B13: 0 | C13: 0 | D13: =SUM(B13:C13) -> 0 | F13: =-CVRBS!E10 -> 0
A14: Material Inventory | B14: 0 | C14: 0 | D14: =SUM(B14:C14) -> 0 | F14: 0
A15: Prepaid Expenses | B15: -6000 | C15: 0 | D15: =SUM(B15:C15) -> -6000 | F15: =-CVRBS!E13 -> 0
A16: Accounts Payable | B16: -81 | C16: 0 | D16: =SUM(B16:C16) -> -81 | F16: =CVRBS!E37 -> 0
A17: Accrued Expenses | B17: 34037 | C17: 0 | D17: =SUM(B17:C17) -> 34037 | F17: =SUM(CVRBS!E38:E46) -> 7497.4315
A18: WIP-Billings > Cost + Earnings | B18: 0 | C18: 0 | D18: =SUM(B18:C18) -> 0 | F18: =CVRBS!E47 -> 0
A19: Net Cash Provided (Used) by Operating Activities | B19: =SUM(B5:B18) -> -481997 | C19: =SUM(C5:C18) -> 0 | D19: =SUM(D5:D18) -> -481997 | F19: =SUM(F5:F18) -> 157781.99
A21: Cash Flows from Investing Activities
A22: Additions to Property and Equipment | B22: 0 | C22: 0 | D22: =SUM(B22:C22) -> 0 | F22: 0
A23: Net (Increase)/Decrease to Note Receivable-USC | B23: 0 | C23: 0 | D23: =SUM(B23:C23) -> 0 | F23: =+-CVRBS!E28 -> 0
A24: Proceeds from Sale of Property and Eqpt. | B24: 0 | C24: 0 | D24: =SUM(B24:C24) -> 0 | F24: 0
A25: Collections of Note Receivable-Shareholder | B25: 0 | C25: 0 | D25: =SUM(B25:C25) -> 0 | F25: 0
A26: Net Cash Provided (Used) by Investing Activities | B26: =SUM(B22:B25) -> 0 | C26: =SUM(C22:C25) -> 0 | D26: =SUM(D22:D25) -> 0 | F26: =SUM(F22:F25) -> 0
A28: Cash Flows from Financing Activities
A29: Net Increase/(Decrease) to Term Debt | B29: 0 | C29: 0 | D29: =SUM(B29:C29) -> 0 | F29: 0
A30: Proceeds from Membership Interest | B30: 0 | C30: 0 | D30: =SUM(B30:C30) -> 0 | F30: 0
A31: Net Increase/(Decrease) to Note Payable-USC | B31: 481997 | C31: 0 | D31: =SUM(B31:C31) -> 481997 | F31: -157782
A32: Proceeds from Issuance of Common Stock | B32: 0 | C32: 0 | D32: =SUM(B32:C32) -> 0 | F32: 0
A33: Net Cash Provided (Used) by Financing Activities | B33: =SUM(B29:B32) -> 481997 | C33: =SUM(C29:C32) -> 0 | D33: =SUM(D29:D32) -> 481997 | F33: =SUM(F29:F32) -> -157782
A35: Increase/(Decrease) in Cash | B35: =B19+B26+B33 -> 0 | C35: =C19+C26+C33 -> 0 | D35: =D19+D26+D33 -> 0 | F35: =F19+F26+F33 -> -0.011145779
A37: Cash at Beginning of Year | B37: 0 | C37: 0 | D37: =B37 -> 0 | F37: =D39 -> 0
A39: Cash at End of Year | B39: =(B35+B37) -> 0 | C39: =(C35+C37) -> 0 | D39: =(D35+D37) -> 0 | F39: =(F35+F37) -> -0.011145779

Sheet Labor
A1: Last Name | B1: First Name | C1: Business Unit | D1: Title | E1: Annual Base Salary | F1: 2026 Annual Base Salary | G1: 2026 Wage Adjustment % | H1: 2026 Wages | I1: 2026 Hourly Rate | J1: S/H | K1: Benefits | L1: Class | M1: Health Ins | N1: Annual Health Ins cost | O1: FUTA | P1: SUTA | Q1: Social Security | R1: Medicare | S1: Work Comp | T1: Safe Harbor 3% | U1: Profit Sharing 2% | V1: X-Mas Gift Eligible | W1: Bonus | X1: Bonus %
B2: Roy | C2: CVR Engineering | D2: VP of Engineering | E2: 192816 | F2: =+E2 -> 192816 | G2: 0.03 | H2: =+F2*(1+G2) -> 198600.48 | J2: S | K2: Y | L2: FT | M2: =IF(K2=K2,1100,"") -> 1100 | N2: =+M2*12 -> 13200 | O2: =MIN(H2*0.006,(7000*0.006)) -> 42 | P2: =MIN(H2*0.027,(9000*0.027)) -> 243 | Q2: =IF(H2>184500,184500*0.062,H2*0.062) -> 11439 | R2: =+H2*0.0145 -> 2879.707 | S2: =+H2*1/100 -> 1986.0048 | T2: =+H2*0.03 -> 5958.0144 | U2: =+H2*0.02 -> 3972.0096 | W2: =+H2*X2 -> 29790.072 | X2: 0.15
B3: Hayley | C3: CVR Engineering | D3: Senior Engineer | E3: 161491 | F3: =+E3 -> 161491 | G3: 0.03 | H3: =+F3*(1+G3) -> 166335.73 | J3: S | K3: Y | L3: FT | M3: =IF(K3=K3,1100,"") -> 1100 | N3: =+M3*12 -> 13200 | O3: =MIN(H3*0.006,(7000*0.006)) -> 42 | P3: =MIN(H3*0.027,(9000*0.027)) -> 243 | Q3: =IF(H3>184500,184500*0.062,H3*0.062) -> 10312.815 | R3: =+H3*0.0145 -> 2411.8681 | S3: =+H3*1/100 -> 1663.3573 | T3: =+H3*0.03 -> 4990.0719 | U3: =+H3*0.02 -> 3326.7146 | W3: =+H3*X3 -> 24950.36 | X3: 0.15
B4: Bhkti | C4: CVR Engineering | D4: ENG - 3 | E4: 117000 | F4: =+E4 -> 117000 | G4: 0.03 | H4: =+F4*(1+G4) -> 120510 | J4: S | K4: Y | L4: FT | M4: =IF(K4=K4,1100,"") -> 1100 | N4: =+M4*12 -> 13200 | O4: =MIN(H4*0.006,(7000*0.006)) -> 42 | P4: =MIN(H4*0.027,(9000*0.027)) -> 243 | Q4: =IF(H4>184500,184500*0.062,H4*0.062) -> 7471.62 | R4: =+H4*0.0145 -> 1747.395 | S4: =+H4*1/100 -> 1205.1 | T4: =+H4*0.03 -> 3615.3 | U4: =+H4*0.02 -> 2410.2 | V4: 1500 | W4: =+H4*X4 -> 0 | X4: 0
B5: Joseph - PT | C5: CVR Engineering | D5: Priciple Eng | E5: 6240 | F5: =+E5 -> 6240 | G5: 0.03 | H5: =+F5*(1+G5) -> 6427.2 | J5: H | K5: N | L5: PT | M5: 0 | N5: =+M5*12 -> 0 | O5: =MIN(H5*0.006,(7000*0.006)) -> 38.5632 | P5: =MIN(H5*0.027,(9000*0.027)) -> 173.5344 | Q5: =IF(H5>184500,184500*0.062,H5*0.062) -> 398.4864 | R5: =+H5*0.0145 -> 93.1944 | S5: =+H5*1/100 -> 64.272 | T5: 0 | U5: 0 | V5: 0 | W5: =+H5*X5 -> 0 | X5: 0
B6: Kevin | C6: CVR Engineering | D6: ENG - 2 | E6: 122498.93 | F6: =+E6 -> 122498.93 | G6: 0.03 | H6: =+F6*(1+G6) -> 126173.9 | J6: S | K6: Y | L6: FT | M6: =IF(K6=K6,1100,"") -> 1100 | N6: =+M6*12 -> 13200 | O6: =MIN(H6*0.006,(7000*0.006)) -> 42 | P6: =MIN(H6*0.027,(9000*0.027)) -> 243 | Q6: =IF(H6>184500,184500*0.062,H6*0.062) -> 7822.7817 | R6: =+H6*0.0145 -> 1829.5215 | S6: =+H6*1/100 -> 1261.739 | T6: =+H6*0.03 -> 3785.2169 | U6: =+H6*0.02 -> 2523.478 | V6: 1500 | W6: =+H6*X6 -> 0 | X6: 0
B7: Craig | C7: CVR Engineering | D7: ENG - 1 | E7: 89600 | F7: =+E7 -> 89600 | G7: 0.03 | H7: =+F7*(1+G7) -> 92288 | J7: S | K7: Y | L7: FT | M7: =IF(K7=K7,1100,"") -> 1100 | N7: =+M7*12 -> 13200 | O7: =MIN(H7*0.006,(7000*0.006)) -> 42 | P7: =MIN(H7*0.027,(9000*0.027)) -> 243 | Q7: =IF(H7>184500,184500*0.062,H7*0.062) -> 5721.856 | R7: =+H7*0.0145 -> 1338.176 | S7: =+H7*1/100 -> 922.88 | T7: =+H7*0.03 -> 2768.64 | U7: =+H7*0.02 -> 1845.76 | V7: 1500 | W7: =+H7*X7 -> 0 | X7: 0
B8: Taylor | C8: CVR Engineering | D8: ENG - 1 | E8: 102500 | F8: =+E8 -> 102500 | G8: 0.03 | H8: =+F8*(1+G8) -> 105575 | J8: S | K8: Y | L8: FT | M8: =IF(K8=K8,1100,"") -> 1100 | N8: =+M8*12 -> 13200 | O8: =MIN(H8*0.006,(7000*0.006)) -> 42 | P8: =MIN(H8*0.027,(9000*0.027)) -> 243 | Q8: =IF(H8>184500,184500*0.062,H8*0.062) -> 6545.6498 | R8: =+H8*0.0145 -> 1530.8375 | S8: =+H8*1/100 -> 1055.75 | T8: =+H8*0.03 -> 3167.2499 | U8: =+H8*0.02 -> 2111.5 | V8: 1500 | W8: =+H8*X8 -> 0 | X8: 0
B9: Collin | C9: CVR Engineering | D9: Graphics Tech | E9: 62400 | F9: =+E9 -> 62400 | G9: 0.03 | H9: =+F9*(1+G9) -> 64272 | J9: S | K9: Y | L9: FT | M9: =IF(K9=K9,1100,"") -> 1100 | N9: =+M9*12 -> 13200 | O9: =MIN(H9*0.006,(7000*0.006)) -> 42 | P9: =MIN(H9*0.027,(9000*0.027)) -> 243 | Q9: =IF(H9>184500,184500*0.062,H9*0.062) -> 3984.864 | R9: =+H9*0.0145 -> 931.944 | S9: =+H9*1/100 -> 642.72 | T9: =+H9*0.03 -> 1928.16 | U9: =+H9*0.02 -> 1285.44 | V9: 1500 | W9: =+H9*X9 -> 0 | X9: 0
B10: Francis | C10: CVR Engineering | D10: ENG - 3 | E10: 128500 | F10: =+E10 -> 128500 | G10: 0.03 | H10: =+F10*(1+G10) -> 132355 | J10: S | K10: Y | L10: FT | M10: =IF(K10=K10,1100,"") -> 1100 | N10: =+M10*12 -> 13200 | O10: =MIN(H10*0.006,(7000*0.006)) -> 42 | P10: =MIN(H10*0.027,(9000*0.027)) -> 243 | Q10: =IF(H10>184500,184500*0.062,H10*0.062) -> 8206.0098 | R10: =+H10*0.0145 -> 1919.1475 | S10: =+H10*1/100 -> 1323.55 | T10: =+H10*0.03 -> 3970.6499 | U10: =+H10*0.02 -> 2647.1 | V10: 1500 | W10: =+H10*X10 -> 0 | X10: 0
B11: Alicia | C11: CVR Engineering | D11: Senior Desinger | E11: 89400.002 | F11: =+E11 -> 89400.002 | G11: 0.03 | H11: =+F11*(1+G11) -> 92082.002 | J11: S | K11: Y | L11: FT | M11: =IF(K11=K11,1100,"") -> 1100 | N11: =+M11*12 -> 13200 | O11: =MIN(H11*0.006,(7000*0.006)) -> 42 | P11: =MIN(H11*0.027,(9000*0.027)) -> 243 | Q11: =IF(H11>184500,184500*0.062,H11*0.062) -> 5709.0841 | R11: =+H11*0.0145 -> 1335.189 | S11: =+H11*1/100 -> 920.82002 | T11: =+H11*0.03 -> 2762.46 | U11: =+H11*0.02 -> 1841.64 | V11: 1500 | W11: =+H11*X11 -> 0 | X11: 0
B12: Auston - PT | C12: CVR Engineering | D12: Graphics Tech | E12: 1118 | F12: =+E12 -> 1118 | G12: 0.03 | H12: =+F12*(1+G12) -> 1151.54 | J12: H | K12: N | L12: PT | M12: 0 | N12: =+M12*12 -> 0 | O12: =MIN(H12*0.006,(7000*0.006)) -> 6.90924 | P12: =MIN(H12*0.027,(9000*0.027)) -> 31.09158 | Q12: =IF(H12>184500,184500*0.062,H12*0.062) -> 71.39548 | R12: =+H12*0.0145 -> 16.69733 | S12: =+H12*1/100 -> 11.5154 | T12: 0 | U12: 0 | V12: 0 | W12: =+H12*X12 -> 0 | X12: 0
B13: Randy - PT | C13: CVR Engineering | D13: Eng - 4 | E13: 4056 | F13: =+E13 -> 4056 | G13: 0.03 | H13: =+F13*(1+G13) -> 4177.68 | J13: H | K13: N | L13: PT | M13: 0 | N13: =+M13*12 -> 0 | O13: =MIN(H13*0.006,(7000*0.006)) -> 25.06608 | P13: =MIN(H13*0.027,(9000*0.027)) -> 112.79736 | Q13: =IF(H13>184500,184500*0.062,H13*0.062) -> 259.01616 | R13: =+H13*0.0145 -> 60.57636 | S13: =+H13*1/100 -> 41.7768 | T13: 0 | U13: 0 | V13: 0 | W13: 0 | X13: 0
A16: =+COUNTA(B2:B14) -> 12 | E16: =SUM(E2:E14) -> 1077619.9 | F16: =SUM(F2:F14) -> 1077619.9 | H16: =SUM(H2:H14) -> 1109948.5 | N16: =SUM(N2:N15) -> 118800 | O16: =SUM(O2:O15) -> 448.53852 | P16: =SUM(P2:P15) -> 2504.4233 | Q16: =SUM(Q2:Q15) -> 67942.579 | R16: =SUM(R2:R15) -> 16094.254 | S16: =SUM(S2:S15) -> 11099.485 | T16: =SUM(T2:T15) -> 32945.763 | U16: =SUM(U2:U15) -> 21963.842 | ... W16: =SUM(W2:W15) -> 54740.432
G17: Billable Hours | H17: =+'Labor Rates-DP'!F45 -> 14205
G18: Non-Billable | H18: =+'Labor Rates-DP'!C45+'Labor Rates-DP'!D45+'Labor Rates-DP'!E45 -> 6015 | T18: =+T16+U16 -> 54909.605 | V18: =28000+12000 -> 40000
G19: Toal Hours | H19: =SUM(H17:H18) -> 20220 | T19: Final | V19: Final
G20: DL Costing Rate | H20: =+H16/H19 -> 54.893597
N22: Total OPEX: | O22: =SUM(N16:S16)+T18+V18 -> 311798.88

Sheet Operating Exp
O2: 2026 | P2: $ | Q2: $ | R2: $ | S2: $ | T2: $ | U2: % | V2: % | W2: % | X2: % | Y2: %
B3: Jan | C3: Feb | D3: Mar | E3: Apr | F3: May | G3: Jun | H3: July | I3: Aug | J3: Sept | K3: Oct | L3: Nov | M3: Dec | N3: Total | O3: Used | P3: 3 Yr. Avg. | Q3: 2025 | R3: 2024 | S3: 2023 | T3: =+S3-1 -> 2022 | U3: Average | V3: =+Q3 -> 2025 | W3: =+R3 -> 2024 | X3: =+S3 -> 2023 | Y3: =+T3 -> 2022
A4: Total Revenue | B4: =CVRIS!H7 -> 169093.86 | C4: =CVRIS!I7 -> 169093.86 | D4: =CVRIS!J7 -> 169093.86 | E4: =CVRIS!K7 -> 169093.86 | F4: =CVRIS!L7 -> 169093.86 | G4: =CVRIS!M7 -> 169093.86 | H4: =CVRIS!N7 -> 169093.86 | I4: =CVRIS!O7 -> 169093.86 | ... M4: =CVRIS!S7 -> 169093.86 | N4: =SUM(B4:M4) -> 2029126.3 | O4: =CVRIS!T7 -> 2029126.3 | P4: =AVERAGE(Q4:S4) -> 994039.67 | Q4: =CVRIS!F7 -> 1827505 | R4: 1044746 | S4: 109868 | T4: 0 | U4: =IFERROR(AVERAGE(W4:Y4),0) -> 0.66666667 | V4: =IFERROR(Q4/$R$4,0) -> 1.7492338 | W4: =IFERROR(R4/$R$4,0) -> 1 | X4: =IFERROR(S4/$S$4,0) -> 1 | Y4: =IFERROR(T4/$T$4,0) -> 0 | Z4: Explanation
A6: Expenses
A8: Labor- Indirect | B8: ='06-60 EPC'!C68-B9 -> 22235.646 | C8: ='06-60 EPC'!D68-C9 -> 22235.646 | D8: ='06-60 EPC'!E68-D9 -> 22235.646 | E8: ='06-60 EPC'!F68-E9 -> 22235.646 | F8: ='06-60 EPC'!G68-F9 -> 22235.646 | G8: ='06-60 EPC'!H68-G9 -> 22235.646 | H8: ='06-60 EPC'!I68-H9 -> 22235.646 | I8: ='06-60 EPC'!J68-I9 -> 22235.646 | ... M8: ='06-60 EPC'!N68-M9 -> 22235.646 | N8: =SUM(B8:M8) -> 266827.75 | O8: =N8 -> 266827.75 | P8: =AVERAGE(Q8:S8) -> 377519.67 | Q8: =CVRIS!F22 -> 163091 | R8: 143759 | S8: 825709 | T8: 0.0001 | U8: =AVERAGE(W8:Y8) -> 2.551022 | V8: =IFERROR(Q8/$Q$4,0) -> 0.089242437 | W8: =IFERROR(R8/$R$4,0) -> 0.13760187 | X8: =IFERROR(S8/$S$4,0) -> 7.515464 | Y8: =IFERROR(T8/$T$4,0) -> 0
A9: Employee Vac and Hol Pay | B9: ='Labor Rates-DP'!$M$45/12 -> 5279.7697 | C9: ='Labor Rates-DP'!$M$45/12 -> 5279.7697 | D9: ='Labor Rates-DP'!$M$45/12 -> 5279.7697 | E9: ='Labor Rates-DP'!$M$45/12 -> 5279.7697 | F9: ='Labor Rates-DP'!$M$45/12 -> 5279.7697 | G9: ='Labor Rates-DP'!$M$45/12 -> 5279.7697 | H9: ='Labor Rates-DP'!$M$45/12 -> 5279.7697 | I9: ='Labor Rates-DP'!$M$45/12 -> 5279.7697 | ... M9: ='Labor Rates-DP'!$M$45/12 -> 5279.7697 | N9: =SUM(B9:M9) -> 63357.237 | O9: =N9 -> 63357.237 | P9: =AVERAGE(Q9:S9) -> 52477 | Q9: =CVRIS!F23 -> 145865 | R9: 0 | S9: 11566 | T9: 0.0001 | U9: =AVERAGE(W9:Y9) -> 0.035090594 | V9: =IFERROR(Q9/$Q$4,0) -> 0.079816471 | W9: =IFERROR(R9/$R$4,0) -> 0 | X9: =IFERROR(S9/$S$4,0) -> 0.10527178 | Y9: =IFERROR(T9/$T$4,0) -> 0
A10: FICA Expense | B10: =+(Labor!$Q$16+Labor!$R$16)/12 -> 7003.0694 | C10: =+(Labor!$Q$16+Labor!$R$16)/12 -> 7003.0694 | D10: =+(Labor!$Q$16+Labor!$R$16)/12 -> 7003.0694 | E10: =+(Labor!$Q$16+Labor!$R$16)/12 -> 7003.0694 | F10: =+(Labor!$Q$16+Labor!$R$16)/12 -> 7003.0694 | G10: =+(Labor!$Q$16+Labor!$R$16)/12 -> 7003.0694 | H10: =+(Labor!$Q$16+Labor!$R$16)/12 -> 7003.0694 | I10: =+(Labor!$Q$16+Labor!$R$16)/12 -> 7003.0694 | ... M10: =+(Labor!$Q$16+Labor!$R$16)/12 -> 7003.0694 | N10: =SUM(B10:M10) -> 84036.832 | O10: =N10 -> 84036.832 | P10: =AVERAGE(Q10:S10) -> 71562.667 | Q10: =CVRIS!F24 -> 90211 | R10: 62045 | S10: 62432 | T10: 0.0001 | U10: =AVERAGE(W10:Y10) -> 0.20921106 | V10: =IFERROR(Q10/$Q$4,0) -> 0.049362929 | W10: =IFERROR(R10/$R$4,0) -> 0.059387641 | X10: =IFERROR(S10/$S$4,0) -> 0.56824553 | Y10: =IFERROR(T10/$T$4,0) -> 0
A11: FUTA Expense | B11: =+Labor!$O$16/12 -> 37.37821 | C11: =+Labor!$O$16/12 -> 37.37821 | D11: =+Labor!$O$16/12 -> 37.37821 | E11: =+Labor!$O$16/12 -> 37.37821 | F11: =+Labor!$O$16/12 -> 37.37821 | G11: =+Labor!$O$16/12 -> 37.37821 | H11: =+Labor!$O$16/12 -> 37.37821 | I11: =+Labor!$O$16/12 -> 37.37821 | ... M11: =+Labor!$O$16/12 -> 37.37821 | N11: =SUM(B11:M11) -> 448.53852 | O11: =N11 -> 448.53852 | P11: =AVERAGE(Q11:S11) -> 523 | Q11: =CVRIS!F25 -> 646 | R11: 503 | S11: 420 | T11: 0.0001 | U11: =AVERAGE(W11:Y11) -> 0.001434742 | V11: =IFERROR(Q11/$Q$4,0) -> 0.0003534874 | W11: =IFERROR(R11/$R$4,0) -> 0.00048145674 | X11: =IFERROR(S11/$S$4,0) -> 0.0038227691 | Y11: =IFERROR(T11/$T$4,0) -> 0
A12: State Unemployment Expense | B12: =+Labor!$P$16/12 -> 208.70194 | C12: =+Labor!$P$16/12 -> 208.70194 | D12: =+Labor!$P$16/12 -> 208.70194 | E12: =+Labor!$P$16/12 -> 208.70194 | F12: =+Labor!$P$16/12 -> 208.70194 | G12: =+Labor!$P$16/12 -> 208.70194 | H12: =+Labor!$P$16/12 -> 208.70194 | I12: =+Labor!$P$16/12 -> 208.70194 | ... M12: =+Labor!$P$16/12 -> 208.70194 | N12: =SUM(B12:M12) -> 2504.4233 | O12: =N12 -> 2504.4233 | P12: =AVERAGE(Q12:S12) -> 3292 | Q12: =CVRIS!F26 -> 2636 | R12: 4099 | S12: 3141 | T12: 0.0001 | U12: =AVERAGE(W12:Y12) -> 0.010837431 | V12: =IFERROR(Q12/$Q$4,0) -> 0.0014424037 | W12: =IFERROR(R12/$R$4,0) -> 0.0039234417 | X12: =IFERROR(S12/$S$4,0) -> 0.028588852 | Y12: =IFERROR(T12/$T$4,0) -> 0
A13: Mileage Expense | B13: =$O13/12 -> 0 | C13: =$O13/12 -> 0 | D13: =$O13/12 -> 0 | E13: =$O13/12 -> 0 | F13: =$O13/12 -> 0 | G13: =$O13/12 -> 0 | H13: =$O13/12 -> 0 | I13: =$O13/12 -> 0 | ... M13: =$O13/12 -> 0 | N13: =SUM(B13:M13) -> 0 | O13: 0 | P13: =AVERAGE(Q13:S13) -> 78.333333 | Q13: =CVRIS!F27 -> 186 | R13: 49 | S13: 0 | T13: 0.0001 | U13: =AVERAGE(W13:Y13) -> 1.5633784e-05 | V13: =IFERROR(Q13/$Q$4,0) -> 0.00010177811 | W13: =IFERROR(R13/$R$4,0) -> 4.6901352e-05 | X13: =IFERROR(S13/$S$4,0) -> 0 | Y13: =IFERROR(T13/$T$4,0) -> 0
A14: Repair & Maint Equip | B14: =$O14/12 -> 19.027778 | C14: =$O14/12 -> 19.027778 | D14: =$O14/12 -> 19.027778 | E14: =$O14/12 -> 19.027778 | F14: =$O14/12 -> 19.027778 | G14: =$O14/12 -> 19.027778 | H14: =$O14/12 -> 19.027778 | I14: =$O14/12 -> 19.027778 | ... M14: =$O14/12 -> 19.027778 | N14: =SUM(B14:M14) -> 228.33333 | O14: =P14 -> 228.33333 | P14: =AVERAGE(Q14:S14) -> 228.33333 | Q14: =CVRIS!F28 -> 397 | R14: 92 | S14: 196 | T14: 0.0001 | U14: =AVERAGE(W14:Y14) -> 0.0006240062 | V14: =IFERROR(Q14/$Q$4,0) -> 0.00021723607 | W14: =IFERROR(R14/$R$4,0) -> 8.8059681e-05 | X14: =IFERROR(S14/$S$4,0) -> 0.0017839589 | Y14: =IFERROR(T14/$T$4,0) -> 0
A15: Fuel Expense | B15: =$O15/12 -> 20.194444 | C15: =$O15/12 -> 20.194444 | D15: =$O15/12 -> 20.194444 | E15: =$O15/12 -> 20.194444 | F15: =$O15/12 -> 20.194444 | G15: =$O15/12 -> 20.194444 | H15: =$O15/12 -> 20.194444 | I15: =$O15/12 -> 20.194444 | ... M15: =$O15/12 -> 20.194444 | N15: =SUM(B15:M15) -> 242.33333 | O15: =P15 -> 242.33333 | P15: =AVERAGE(Q15:S15) -> 242.33333 | Q15: =CVRIS!F29 -> 330 | R15: 267 | S15: 130 | T15: 0.0001 | U15: =AVERAGE(W15:Y15) -> 0.00047960086 | V15: =IFERROR(Q15/$Q$4,0) -> 0.00018057406 | W15: =IFERROR(R15/$R$4,0) -> 0.00025556451 | X15: =IFERROR(S15/$S$4,0) -> 0.0011832381 | Y15: =IFERROR(T15/$T$4,0) -> 0
A16: Licenses & Permits | B16: =$O16/12 -> 183.33333 | C16: =$O16/12 -> 183.33333 | D16: =$O16/12 -> 183.33333 | E16: =$O16/12 -> 183.33333 | F16: =$O16/12 -> 183.33333 | G16: =$O16/12 -> 183.33333 | H16: =$O16/12 -> 183.33333 | I16: =$O16/12 -> 183.33333 | ... M16: =$O16/12 -> 183.33333 | N16: =SUM(B16:M16) -> 2200 | O16: =+'Labor Rates-DP'!N19 -> 2200 | P16: =AVERAGE(Q16:S16) -> 4249 | Q16: =CVRIS!F30 -> 606 | R16: 9790 | S16: 2351 | T16: 0.0001 | U16: =AVERAGE(W16:Y16) -> 0.010256368 | V16: =IFERROR(Q16/$Q$4,0) -> 0.00033159964 | W16: =IFERROR(R16/$R$4,0) -> 0.0093706987 | X16: =IFERROR(S16/$S$4,0) -> 0.021398405 | Y16: =IFERROR(T16/$T$4,0) -> 0
A17: Machinery Rental | B17: =$O$17/12 -> 47.5 | C17: =$O$17/12 -> 47.5 | D17: =$O$17/12 -> 47.5 | E17: =$O$17/12 -> 47.5 | F17: =$O$17/12 -> 47.5 | G17: =$O$17/12 -> 47.5 | H17: =$O$17/12 -> 47.5 | I17: =$O$17/12 -> 47.5 | ... M17: =$O$17/12 -> 47.5 | N17: =SUM(B17:M17) -> 570 | O17: =P17 -> 570 | P17: =AVERAGE(Q17:S17) -> 570 | Q17: =CVRIS!F31 -> 830 | R17: 546 | S17: 334 | T17: 0.0001 | U17: =AVERAGE(W17:Y17) -> 0.0011875422 | V17: =IFERROR(Q17/$Q$4,0) -> 0.00045417112 | W17: =IFERROR(R17/$R$4,0) -> 0.00052261507 | X17: =IFERROR(S17/$S$4,0) -> 0.0030400117 | Y17: =IFERROR(T17/$T$4,0) -> 0
A18: Safety Expense | B18: =$O$18/12 -> 70.166667 | C18: =$O$18/12 -> 70.166667 | D18: =$O$18/12 -> 70.166667 | E18: =$O$18/12 -> 70.166667 | F18: =$O$18/12 -> 70.166667 | G18: =$O$18/12 -> 70.166667 | H18: =$O$18/12 -> 70.166667 | I18: =$O$18/12 -> 70.166667 | ... M18: =$O$18/12 -> 70.166667 | N18: =SUM(B18:M18) -> 842 | O18: =P18 -> 842 | P18: =AVERAGE(Q18:S18) -> 842 | Q18: =CVRIS!F32 -> 99 | R18: 80 | S18: 2347 | T18: 0.0001 | U18: =AVERAGE(W18:Y18) -> 0.0071461906 | V18: =IFERROR(Q18/$Q$4,0) -> 5.4172218e-05 | W18: =IFERROR(R18/$R$4,0) -> 7.6573636e-05 | X18: =IFERROR(S18/$S$4,0) -> 0.021361998 | Y18: =IFERROR(T18/$T$4,0) -> 0
A19: General Insurance | B19: =$O19/12 -> 5000 | C19: =$O19/12 -> 5000 | D19: =$O19/12 -> 5000 | E19: =$O19/12 -> 5000 | F19: =$O19/12 -> 5000 | G19: =$O19/12 -> 5000 | H19: =$O19/12 -> 5000 | I19: =$O19/12 -> 5000 | ... M19: =$O19/12 -> 5000 | N19: =SUM(B19:M19) -> 60000 | O19: ='Labor Rates-DP'!P21 -> 60000 | P19: =AVERAGE(Q19:S19) -> 35817 | Q19: =CVRIS!F33 -> 35810 | R19: 34640 | S19: 37001 | T19: 0.0001 | U19: =AVERAGE(W19:Y19) -> 0.12331108 | V19: =IFERROR(Q19/$Q$4,0) -> 0.019595022 | W19: =IFERROR(R19/$R$4,0) -> 0.033156384 | X19: =IFERROR(S19/$S$4,0) -> 0.33677686 | Y19: =IFERROR(T19/$T$4,0) -> 0
A20: Work Comp Insurance | B20: =+Labor!$S$16/12 -> 924.9571 | C20: =+Labor!$S$16/12 -> 924.9571 | D20: =+Labor!$S$16/12 -> 924.9571 | E20: =+Labor!$S$16/12 -> 924.9571 | F20: =+Labor!$S$16/12 -> 924.9571 | G20: =+Labor!$S$16/12 -> 924.9571 | H20: =+Labor!$S$16/12 -> 924.9571 | I20: =+Labor!$S$16/12 -> 924.9571 | ... M20: =+Labor!$S$16/12 -> 924.9571 | N20: =SUM(B20:M20) -> 11099.485 | O20: =N20 -> 11099.485 | P20: =AVERAGE(Q20:S20) -> 11112.667 | Q20: =CVRIS!F34 -> 13308 | R20: 9056 | S20: 10974 | T20: 0.0001 | U20: =AVERAGE(W20:Y20) -> 0.036183877 | V20: =IFERROR(Q20/$Q$4,0) -> 0.0072820594 | W20: =IFERROR(R20/$R$4,0) -> 0.0086681356 | X20: =IFERROR(S20/$S$4,0) -> 0.099883497 | Y20: =IFERROR(T20/$T$4,0) -> 0
A21: Accounting & Legal | B21: =$O21/12 -> 401.97222 | C21: =$O21/12 -> 401.97222 | D21: =$O21/12 -> 401.97222 | E21: =$O21/12 -> 401.97222 | F21: =$O21/12 -> 401.97222 | G21: =$O21/12 -> 401.97222 | H21: =$O21/12 -> 401.97222 | I21: =$O21/12 -> 401.97222 | ... M21: =$O21/12 -> 401.97222 | N21: =SUM(B21:M21) -> 4823.6667 | O21: =P21 -> 4823.6667 | P21: =AVERAGE(Q21:S21) -> 4823.6667 | Q21: =CVRIS!F35 -> 4284 | R21: 3655 | S21: 6532 | T21: 0.0001 | U21: =AVERAGE(W21:Y21) -> 0.020983873 | V21: =IFERROR(Q21/$Q$4,0) -> 0.0023441796 | W21: =IFERROR(R21/$R$4,0) -> 0.003498458 | X21: =IFERROR(S21/$S$4,0) -> 0.059453162 | Y21: =IFERROR(T21/$T$4,0) -> 0
A22: Advertising & Sales and Promotion | B22: =$O22/12 -> 112.5 | C22: =$O22/12 -> 112.5 | D22: =$O22/12 -> 112.5 | E22: =$O22/12 -> 112.5 | F22: =$O22/12 -> 112.5 | G22: =$O22/12 -> 112.5 | H22: =$O22/12 -> 112.5 | I22: =$O22/12 -> 112.5 | ... M22: =$O22/12 -> 112.5 | N22: =SUM(B22:M22) -> 1350 | O22: =P22 -> 1350 | P22: =AVERAGE(Q22:S22) -> 1350 | Q22: =CVRIS!F36 -> 1396 | R22: 1150 | S22: 1504 | T22: 0.0001 | U22: =AVERAGE(W22:Y22) -> 0.0049299668 | V22: =IFERROR(Q22/$Q$4,0) -> 0.000763883 | W22: =IFERROR(R22/$R$4,0) -> 0.001100746 | X22: =IFERROR(S22/$S$4,0) -> 0.013689154 | Y22: =IFERROR(T22/$T$4,0) -> 0
A23: Admin. Meals & Ent. | B23: =$O23/12 -> 1150 | C23: =$O23/12 -> 1150 | D23: =$O23/12 -> 1150 | E23: =$O23/12 -> 1150 | F23: =$O23/12 -> 1150 | G23: =$O23/12 -> 1150 | H23: =$O23/12 -> 1150 | I23: =$O23/12 -> 1150 | ... M23: =$O23/12 -> 1150 | N23: =SUM(B23:M23) -> 13800 | O23: =+'Labor Rates-DP'!H19 -> 13800 | P23: =AVERAGE(Q23:S23) -> 7744 | Q23: =CVRIS!F37 -> 10669 | R23: 6316 | S23: 6247 | T23: 0.0001 | U23: =AVERAGE(W23:Y23) -> 0.02096821 | V23: =IFERROR(Q23/$Q$4,0) -> 0.0058380141 | W23: =IFERROR(R23/$R$4,0) -> 0.0060454886 | X23: =IFERROR(S23/$S$4,0) -> 0.05685914 | Y23: =IFERROR(T23/$T$4,0) -> 0
A24: Admin.-Travel & Mileage | B24: =$O24/12 -> 3650 | C24: =$O24/12 -> 3650 | D24: =$O24/12 -> 3650 | E24: =$O24/12 -> 3650 | F24: =$O24/12 -> 3650 | G24: =$O24/12 -> 3650 | H24: =$O24/12 -> 3650 | I24: =$O24/12 -> 3650 | ... M24: =$O24/12 -> 3650 | N24: =SUM(B24:M24) -> 43800 | O24: =+'Labor Rates-DP'!L19+'Labor Rates-DP'!K19 -> 43800 | P24: =AVERAGE(Q24:S24) -> 36679.333 | Q24: =CVRIS!F38 -> 41872 | R24: 36369 | S24: 31797 | T24: 0.0001 | U24: =AVERAGE(W24:Y24) -> 0.10807409 | V24: =IFERROR(Q24/$Q$4,0) -> 0.022912112 | W24: =IFERROR(R24/$R$4,0) -> 0.034811332 | X24: =IFERROR(S24/$S$4,0) -> 0.28941093 | Y24: =IFERROR(T24/$T$4,0) -> 0
A25: Bank Charges | B25: =$O25/12 -> 268.44444 | C25: =$O25/12 -> 268.44444 | D25: =$O25/12 -> 268.44444 | E25: =$O25/12 -> 268.44444 | F25: =$O25/12 -> 268.44444 | G25: =$O25/12 -> 268.44444 | H25: =$O25/12 -> 268.44444 | I25: =$O25/12 -> 268.44444 | ... M25: =$O25/12 -> 268.44444 | N25: =SUM(B25:M25) -> 3221.3333 | O25: =P25 -> 3221.3333 | P25: =AVERAGE(Q25:S25) -> 3221.3333 | Q25: =CVRIS!F39 -> 5748 | R25: 2326 | S25: 1590 | T25: 0.0001 | U25: =AVERAGE(W25:Y25) -> 0.0055660967 | V25: =IFERROR(Q25/$Q$4,0) -> 0.0031452718 | W25: =IFERROR(R25/$R$4,0) -> 0.0022263785 | X25: =IFERROR(S25/$S$4,0) -> 0.014471912 | Y25: =IFERROR(T25/$T$4,0) -> 0
A26: Computer-Consulting Fees | B26: =$O26/12 -> 5000 | C26: =$O26/12 -> 5000 | D26: =$O26/12 -> 5000 | E26: =$O26/12 -> 5000 | F26: =$O26/12 -> 5000 | G26: =$O26/12 -> 5000 | H26: =$O26/12 -> 5000 | I26: =$O26/12 -> 5000 | ... M26: =$O26/12 -> 5000 | N26: =SUM(B26:M26) -> 60000 | O26: 60000 | P26: =AVERAGE(Q26:S26) -> 68244.667 | Q26: =CVRIS!F40 -> 74594 | R26: 84093 | S26: 46047 | T26: 0.0001 | U26: =AVERAGE(W26:Y26) -> 0.16653445 | V26: =IFERROR(Q26/$Q$4,0) -> 0.040817399 | W26: =IFERROR(R26/$R$4,0) -> 0.080491335 | X26: =IFERROR(S26/$S$4,0) -> 0.41911203 | Y26: =IFERROR(T26/$T$4,0) -> 0
A27: Computer-PC Hardware | B27: =$O27/12 -> 416.66667 | C27: =$O27/12 -> 416.66667 | D27: =$O27/12 -> 416.66667 | E27: =$O27/12 -> 416.66667 | F27: =$O27/12 -> 416.66667 | G27: =$O27/12 -> 416.66667 | H27: =$O27/12 -> 416.66667 | I27: =$O27/12 -> 416.66667 | ... M27: =$O27/12 -> 416.66667 | N27: =SUM(B27:M27) -> 5000 | O27: 5000 | P27: =AVERAGE(Q27:S27) -> 6427 | Q27: =CVRIS!F41 -> 10033 | R27: 6773 | S27: 2475 | T27: 0.0001 | U27: =AVERAGE(W27:Y27) -> 0.0096699826 | V27: =IFERROR(Q27/$Q$4,0) -> 0.0054899987 | W27: =IFERROR(R27/$R$4,0) -> 0.0064829155 | X27: =IFERROR(S27/$S$4,0) -> 0.022527032 | Y27: =IFERROR(T27/$T$4,0) -> 0
A28: Computer-PC Software | B28: =$O28/12 -> 2416.6667 | C28: =$O28/12 -> 2416.6667 | D28: =$O28/12 -> 2416.6667 | E28: =$O28/12 -> 2416.6667 | F28: =$O28/12 -> 2416.6667 | G28: =$O28/12 -> 2416.6667 | H28: =$O28/12 -> 2416.6667 | I28: =$O28/12 -> 2416.6667 | ... M28: =$O28/12 -> 2416.6667 | N28: =SUM(B28:M28) -> 29000 | O28: =+'Labor Rates-DP'!O19-O27-O26-O29 -> 29000 | P28: =AVERAGE(Q28:S28) -> 34715.667 | Q28: =CVRIS!F42 -> 10821 | R28: 17960 | S28: 75366 | T28: 0.0001 | U28: =AVERAGE(W28:Y28) -> 0.23438647 | V28: =IFERROR(Q28/$Q$4,0) -> 0.0059211876 | W28: =IFERROR(R28/$R$4,0) -> 0.017190781 | X28: =IFERROR(S28/$S$4,0) -> 0.68596862 | Y28: =IFERROR(T28/$T$4,0) -> 0
A29: Computer-Internet Expense | B29: =$O29/12 -> 166.66667 | C29: =$O29/12 -> 166.66667 | D29: =$O29/12 -> 166.66667 | E29: =$O29/12 -> 166.66667 | F29: =$O29/12 -> 166.66667 | G29: =$O29/12 -> 166.66667 | H29: =$O29/12 -> 166.66667 | I29: =$O29/12 -> 166.66667 | ... M29: =$O29/12 -> 166.66667 | N29: =SUM(B29:M29) -> 2000 | O29: 2000 | P29: =AVERAGE(Q29:S29) -> 3074 | Q29: =CVRIS!F43 -> 3600 | R29: 2972 | S29: 2650 | T29: 0.0001 | U29: =AVERAGE(W29:Y29) -> 0.0089881878 | V29: =IFERROR(Q29/$Q$4,0) -> 0.0019698989 | W29: =IFERROR(R29/$R$4,0) -> 0.0028447106 | X29: =IFERROR(S29/$S$4,0) -> 0.024119853 | Y29: =IFERROR(T29/$T$4,0) -> 0
A30: Contributions | B30: =$O30/12 -> 30.583333 | C30: =$O30/12 -> 30.583333 | D30: =$O30/12 -> 30.583333 | E30: =$O30/12 -> 30.583333 | F30: =$O30/12 -> 30.583333 | G30: =$O30/12 -> 30.583333 | H30: =$O30/12 -> 30.583333 | I30: =$O30/12 -> 30.583333 | ... M30: =$O30/12 -> 30.583333 | N30: =SUM(B30:M30) -> 367 | O30: =P30 -> 367 | P30: =AVERAGE(Q30:S30) -> 367 | Q30: =CVRIS!F44 -> 119 | R30: 724 | S30: 258 | T30: 0.0001 | U30: =AVERAGE(W30:Y30) -> 0.0010137546 | V30: =IFERROR(Q30/$Q$4,0) -> 6.5116101e-05 | W30: =IFERROR(R30/$R$4,0) -> 0.00069299141 | X30: =IFERROR(S30/$S$4,0) -> 0.0023482725 | Y30: =IFERROR(T30/$T$4,0) -> 0
A31: Dues & Subscriptions | B31: =$O31/12 -> 67.555556 | C31: =$O31/12 -> 67.555556 | D31: =$O31/12 -> 67.555556 | E31: =$O31/12 -> 67.555556 | F31: =$O31/12 -> 67.555556 | G31: =$O31/12 -> 67.555556 | H31: =$O31/12 -> 67.555556 | I31: =$O31/12 -> 67.555556 | ... M31: =$O31/12 -> 67.555556 | N31: =SUM(B31:M31) -> 810.66667 | O31: =P31 -> 810.66667 | P31: =AVERAGE(Q31:S31) -> 810.66667 | Q31: =CVRIS!F45 -> 905 | R31: 1170 | S31: 357 | T31: 0.0001 | U31: =AVERAGE(W31:Y31) -> 0.0014564144 | V31: =IFERROR(Q31/$Q$4,0) -> 0.00049521068 | W31: =IFERROR(R31/$R$4,0) -> 0.0011198894 | X31: =IFERROR(S31/$S$4,0) -> 0.0032493538 | Y31: =IFERROR(T31/$T$4,0) -> 0
A32: Employee Pre-Emp Physicals | B32: =$O32/12 -> 0 | C32: =$O32/12 -> 0 | D32: =$O32/12 -> 0 | E32: =$O32/12 -> 0 | F32: =$O32/12 -> 0 | G32: =$O32/12 -> 0 | H32: =$O32/12 -> 0 | I32: =$O32/12 -> 0 | ... M32: =$O32/12 -> 0 | N32: =SUM(B32:M32) -> 0 | O32: 0 | P32: =AVERAGE(Q32:S32) -> 216 | Q32: =CVRIS!F46 -> 617 | R32: 31 | S32: 0 | T32: 0.0001 | U32: =AVERAGE(W32:Y32) -> 9.8907613e-06 | V32: =IFERROR(Q32/$Q$4,0) -> 0.00033761878 | W32: =IFERROR(R32/$R$4,0) -> 2.9672284e-05 | X32: =IFERROR(S32/$S$4,0) -> 0 | Y32: =IFERROR(T32/$T$4,0) -> 0
A33: Employee Training & Seminars | B33: =$O33/12 -> 916.66667 | C33: =$O33/12 -> 916.66667 | D33: =$O33/12 -> 916.66667 | E33: =$O33/12 -> 916.66667 | F33: =$O33/12 -> 916.66667 | G33: =$O33/12 -> 916.66667 | H33: =$O33/12 -> 916.66667 | I33: =$O33/12 -> 916.66667 | ... M33: =$O33/12 -> 916.66667 | N33: =SUM(B33:M33) -> 11000 | O33: =+'Labor Rates-DP'!M19 -> 11000 | P33: =AVERAGE(Q33:S33) -> 5630.6667 | Q33: =CVRIS!F47 -> 6373 | R33: 3588 | S33: 6931 | T33: 0.0001 | U33: =AVERAGE(W33:Y33) -> 0.02217304 | V33: =IFERROR(Q33/$Q$4,0) -> 0.0034872682 | W33: =IFERROR(R33/$R$4,0) -> 0.0034343276 | X33: =IFERROR(S33/$S$4,0) -> 0.063084793 | Y33: =IFERROR(T33/$T$4,0) -> 0
A34: Employee Benefits | B34: =$O34/12 -> 0 | C34: =$O34/12 -> 0 | D34: =$O34/12 -> 0 | E34: =$O34/12 -> 0 | F34: =$O34/12 -> 0 | G34: =$O34/12 -> 0 | H34: =$O34/12 -> 0 | I34: =$O34/12 -> 0 | ... M34: =$O34/12 -> 0 | N34: =SUM(B34:M34) -> 0 | O34: 0 | P34: =AVERAGE(Q34:S34) -> 53354.667 | Q34: =CVRIS!F48 -> 48078 | R34: 56713 | S34: 55273 | T34: 0.0001 | U34: =AVERAGE(W34:Y34) -> 0.18578984 | V34: =IFERROR(Q34/$Q$4,0) -> 0.026307999 | W34: =IFERROR(R34/$R$4,0) -> 0.054284008 | X34: =IFERROR(S34/$S$4,0) -> 0.50308552 | Y34: =IFERROR(T34/$T$4,0) -> 0
A35: Insurance-Group Health & Life | B35: =$O35/12 -> 9900 | C35: =$O35/12 -> 9900 | D35: =$O35/12 -> 9900 | E35: =$O35/12 -> 9900 | F35: =$O35/12 -> 9900 | G35: =$O35/12 -> 9900 | H35: =$O35/12 -> 9900 | I35: =$O35/12 -> 9900 | ... M35: =$O35/12 -> 9900 | N35: =SUM(B35:M35) -> 118800 | O35: =+Labor!N16 -> 118800 | P35: =AVERAGE(Q35:S35) -> 67438.333 | Q35: =CVRIS!F49 -> 114358 | R35: 34713 | S35: 53244 | T35: 0.0001 | U35: =AVERAGE(W35:Y35) -> 0.17261472 | V35: =IFERROR(Q35/$Q$4,0) -> 0.062576026 | W35: =IFERROR(R35/$R$4,0) -> 0.033226258 | X35: =IFERROR(S35/$S$4,0) -> 0.48461791 | Y35: =IFERROR(T35/$T$4,0) -> 0
A36: Pension Expense | B36: =$O36/12 -> 4575.8004 | C36: =$O36/12 -> 4575.8004 | D36: =$O36/12 -> 4575.8004 | E36: =$O36/12 -> 4575.8004 | F36: =$O36/12 -> 4575.8004 | G36: =$O36/12 -> 4575.8004 | H36: =$O36/12 -> 4575.8004 | I36: =$O36/12 -> 4575.8004 | ... M36: =$O36/12 -> 4575.8004 | N36: =SUM(B36:M36) -> 54909.605 | O36: =+Labor!T18 -> 54909.605 | P36: =AVERAGE(Q36:S36) -> 21936.667 | Q36: =CVRIS!F50 -> 20249 | R36: 36262 | S36: 9299 | T36: 0.0001 | U36: =AVERAGE(W36:Y36) -> 0.039782281 | V36: =IFERROR(Q36/$Q$4,0) -> 0.011080134 | W36: =IFERROR(R36/$R$4,0) -> 0.034708915 | X36: =IFERROR(S36/$S$4,0) -> 0.084637929 | Y36: =IFERROR(T36/$T$4,0) -> 0
A37: Employee Bonus | B37: =$O37/12 -> 3333.3333 | C37: =$O37/12 -> 3333.3333 | D37: =$O37/12 -> 3333.3333 | E37: =$O37/12 -> 3333.3333 | F37: =$O37/12 -> 3333.3333 | G37: =$O37/12 -> 3333.3333 | H37: =$O37/12 -> 3333.3333 | I37: =$O37/12 -> 3333.3333 | ... M37: =$O37/12 -> 3333.3333 | N37: =SUM(B37:M37) -> 40000 | O37: =Labor!V18 -> 40000 | P37: =AVERAGE(Q37:S37) -> 63034.333 | Q37: =CVRIS!F51 -> 33235 | R37: 87683 | S37: 68185 | T37: 0.0001 | U37: =AVERAGE(W37:Y37) -> 0.23484531 | V37: =IFERROR(Q37/$Q$4,0) -> 0.018185997 | W37: =IFERROR(R37/$R$4,0) -> 0.083927577 | X37: =IFERROR(S37/$S$4,0) -> 0.62060837 | Y37: =IFERROR(T37/$T$4,0) -> 0
A38: Employee Vac and Hol Pay | B38: =$O38/12 -> 0 | C38: =$O38/12 -> 0 | D38: =$O38/12 -> 0 | E38: =$O38/12 -> 0 | F38: =$O38/12 -> 0 | G38: =$O38/12 -> 0 | H38: =$O38/12 -> 0 | I38: =$O38/12 -> 0 | ... M38: =$O38/12 -> 0 | N38: =SUM(B38:M38) -> 0 | O38: 0 | P38: =AVERAGE(Q38:S38) -> 16949.667 | Q38: =CVRIS!F52 -> 1906 | R38: 48943 | S38: 0 | T38: 0.0001 | U38: =AVERAGE(W38:Y38) -> 0.015615598 | V38: =IFERROR(Q38/$Q$4,0) -> 0.001042952 | W38: =IFERROR(R38/$R$4,0) -> 0.046846793 | X38: =IFERROR(S38/$S$4,0) -> 0 | Y38: =IFERROR(T38/$T$4,0) -> 0
A39: Office Supplies Expense | B39: =$O39/12 -> 550 | C39: =$O39/12 -> 550 | D39: =$O39/12 -> 550 | E39: =$O39/12 -> 550 | F39: =$O39/12 -> 550 | G39: =$O39/12 -> 550 | H39: =$O39/12 -> 550 | I39: =$O39/12 -> 550 | ... M39: =$O39/12 -> 550 | N39: =SUM(B39:M39) -> 6600 | O39: ='Labor Rates-DP'!J19 -> 6600 | P39: =AVERAGE(Q39:S39) -> 2244.3333 | Q39: =CVRIS!F53 -> 367 | R39: 1757 | S39: 4609 | T39: 0.0001 | U39: =AVERAGE(W39:Y39) -> 0.01454403 | V39: =IFERROR(Q39/$Q$4,0) -> 0.00020082024 | W39: =IFERROR(R39/$R$4,0) -> 0.0016817485 | X39: =IFERROR(S39/$S$4,0) -> 0.04195034 | Y39: =IFERROR(T39/$T$4,0) -> 0
A40: Office Equipment Rental Exp | B40: =$O40/12 -> 67.833333 | C40: =$O40/12 -> 67.833333 | D40: =$O40/12 -> 67.833333 | E40: =$O40/12 -> 67.833333 | F40: =$O40/12 -> 67.833333 | G40: =$O40/12 -> 67.833333 | H40: =$O40/12 -> 67.833333 | I40: =$O40/12 -> 67.833333 | ... M40: =$O40/12 -> 67.833333 | N40: =SUM(B40:M40) -> 814 | O40: =P40 -> 814 | P40: =AVERAGE(Q40:S40) -> 814 | Q40: =CVRIS!F54 -> 2058 | R40: 286 | S40: 98 | T40: 0.0001 | U40: =AVERAGE(W40:Y40) -> 0.00038857674 | V40: =IFERROR(Q40/$Q$4,0) -> 0.0011261255 | W40: =IFERROR(R40/$R$4,0) -> 0.00027375075 | X40: =IFERROR(S40/$S$4,0) -> 0.00089197947 | Y40: =IFERROR(T40/$T$4,0) -> 0
A41: Repair & Maintenance-Building | B41: =$O41/12 -> 275.5 | C41: =$O41/12 -> 275.5 | D41: =$O41/12 -> 275.5 | E41: =$O41/12 -> 275.5 | F41: =$O41/12 -> 275.5 | G41: =$O41/12 -> 275.5 | H41: =$O41/12 -> 275.5 | I41: =$O41/12 -> 275.5 | ... M41: =$O41/12 -> 275.5 | N41: =SUM(B41:M41) -> 3306 | O41: =P41 -> 3306 | P41: =AVERAGE(Q41:S41) -> 3306 | Q41: =CVRIS!F55 -> 5910 | R41: 1439 | S41: 2569 | T41: 0.0001 | U41: =AVERAGE(W41:Y41) -> 0.0082533243 | V41: =IFERROR(Q41/$Q$4,0) -> 0.0032339173 | W41: =IFERROR(R41/$R$4,0) -> 0.0013773683 | X41: =IFERROR(S41/$S$4,0) -> 0.023382605 | Y41: =IFERROR(T41/$T$4,0) -> 0
A42: Telephone | B42: =$O$42/12 -> 600 | C42: =$O$42/12 -> 600 | D42: =$O$42/12 -> 600 | E42: =$O$42/12 -> 600 | F42: =$O$42/12 -> 600 | G42: =$O$42/12 -> 600 | H42: =$O$42/12 -> 600 | I42: =$O$42/12 -> 600 | ... M42: =$O$42/12 -> 600 | N42: =SUM(B42:M42) -> 7200 | O42: ='Labor Rates-DP'!I19 -> 7200 | P42: =AVERAGE(Q42:S42) -> 3126 | Q42: =CVRIS!F56 -> 201 | R42: 4425 | S42: 4752 | T42: 0.0001 | U42: =AVERAGE(W42:Y42) -> 0.015829127 | V42: =IFERROR(Q42/$Q$4,0) -> 0.00010998602 | W42: =IFERROR(R42/$R$4,0) -> 0.0042354792 | X42: =IFERROR(S42/$S$4,0) -> 0.043251902 | Y42: =IFERROR(T42/$T$4,0) -> 0
A43: Taxes-Other | B43: =$O43/12 -> 317.08333 | C43: =$O43/12 -> 317.08333 | D43: =$O43/12 -> 317.08333 | E43: =$O43/12 -> 317.08333 | F43: =$O43/12 -> 317.08333 | G43: =$O43/12 -> 317.08333 | H43: =$O43/12 -> 317.08333 | I43: =$O43/12 -> 317.08333 | ... M43: =$O43/12 -> 317.08333 | N43: =SUM(B43:M43) -> 3805 | O43: =P43 -> 3805 | P43: =AVERAGE(Q43:S43) -> 3805 | Q43: =CVRIS!F57 -> 70 | R43: 11317 | S43: 28 | T43: 0.0001 | U43: =AVERAGE(W43:Y43) -> 0.0036957164 | V43: =IFERROR(Q43/$Q$4,0) -> 3.8303589e-05 | W43: =IFERROR(R43/$R$4,0) -> 0.010832298 | X43: =IFERROR(S43/$S$4,0) -> 0.00025485128 | Y43: =IFERROR(T43/$T$4,0) -> 0
A44: Corporate Overhead Allocation | B44: =$O44/12 -> 17250 | C44: =$O44/12 -> 17250 | D44: =$O44/12 -> 17250 | E44: =$O44/12 -> 17250 | F44: =$O44/12 -> 17250 | G44: =$O44/12 -> 17250 | H44: =$O44/12 -> 17250 | I44: =$O44/12 -> 17250 | ... M44: =$O44/12 -> 17250 | N44: =SUM(B44:M44) -> 207000 | O44: ='Corp OH Alloc & Interest Exp'!B5 -> 207000 | P44: =AVERAGE(Q44:S44) -> 278352.67 | Q44: =CVRIS!F58 -> 278036 | R44: 369009 | S44: 188013 | T44: 0.0001 | U44: =AVERAGE(W44:Y44) -> 0.68815571 | V44: =IFERROR(Q44/$Q$4,0) -> 0.15213967 | W44: =IFERROR(R44/$R$4,0) -> 0.35320451 | X44: =IFERROR(S44/$S$4,0) -> 1.7112626 | Y44: =IFERROR(T44/$T$4,0) -> 0
A45: Total Operating Expenses | B45: =SUM(B8:B44) -> 92497.017 | C45: =SUM(C8:C44) -> 92497.017 | D45: =SUM(D8:D44) -> 92497.017 | E45: =SUM(E8:E44) -> 92497.017 | F45: =SUM(F8:F44) -> 92497.017 | G45: =SUM(G8:G44) -> 92497.017 | H45: =SUM(H8:H44) -> 92497.017 | I45: =SUM(I8:I44) -> 92497.017 | ... T45: =SUM(T8:T44) -> 0.0037
Q46: (agrees) | R46: (agrees) | S46: (agrees) | T46: (agrees)
N53: Labor Tab Totals | O53: =O10+O11+O12+O20+O35+O36+O37 -> 311798.88
N54: Check | O54: =O53-Labor!O22 -> 0
N56: Labor Rates - DP Totals | O56: =O16+O19+O23+O24+O28+O33+O39+O42 -> 173600
N57: Check | O57: =O56-'Labor Rates-DP'!P19-'Labor Rates-DP'!P21 -> -67000

Sheet Corp OH Alloc & Interest Exp
B2: Corporate | C2: Interest
B3: Overhead | C3: Expense
B4: Allocation | C4: Allocation
A5: Year 2026 Allocation | B5: 207000 | C5: =0 -> 0
B6: (Used) | C6: (Used)
A11: Note:
A12: The detailed calculation is maintained in the USC budget file.

Sheet 06-60 EPC
C1: 06-60 EPC
C2: January | D2: February | E2: March | F2: April | G2: May | H2: June | I2: July | J2: August | K2: September | L2: October | M2: November | N2: December
A6: CUSTOMER | C6: Engineering
A7: CONFIDENCE LEVEL | C7: 1 | D7: 1 | E7: 1 | F7: 1 | G7: 1 | H7: 1 | I7: 1 | J7: 1 | K7: 1 | L7: 1 | M7: 1 | N7: 1
A8: Billable HOURS | C8: ='Labor Rates-DP'!Q51 -> 1183.75 | D8: ='Labor Rates-DP'!Q52 -> 1183.75 | E8: ='Labor Rates-DP'!Q53 -> 1183.75 | F8: ='Labor Rates-DP'!Q54 -> 1183.75 | G8: ='Labor Rates-DP'!Q55 -> 1183.75 | H8: ='Labor Rates-DP'!Q56 -> 1183.75 | I8: ='Labor Rates-DP'!Q57 -> 1183.75 | J8: ='Labor Rates-DP'!Q58 -> 1183.75 | K8: ='Labor Rates-DP'!Q59 -> 1183.75 | L8: ='Labor Rates-DP'!Q60 -> 1183.75 | M8: ='Labor Rates-DP'!Q61 -> 1183.75 | N8: ='Labor Rates-DP'!Q62 -> 1183.75 | O8: =SUM(C8:N8) -> 14205
A9: Composite Billable Hour Rate | C9: ='Labor Rates-DP'!I48 -> 142.84592 | D9: =$C$9 -> 142.84592 | E9: =$C$9 -> 142.84592 | F9: =$C$9 -> 142.84592 | G9: =$C$9 -> 142.84592 | H9: =$C$9 -> 142.84592 | I9: =$C$9 -> 142.84592 | J9: =$C$9 -> 142.84592 | K9: =$C$9 -> 142.84592 | ... N9: =$C$9 -> 142.84592
A10: Composite Labor Costing Rate | C10: =+Labor!$H$20 -> 54.893597 | D10: =+Labor!$H$20 -> 54.893597 | E10: =+Labor!$H$20 -> 54.893597 | F10: =+Labor!$H$20 -> 54.893597 | G10: =+Labor!$H$20 -> 54.893597 | H10: =+Labor!$H$20 -> 54.893597 | I10: =+Labor!$H$20 -> 54.893597 | J10: =+Labor!$H$20 -> 54.893597 | ... N10: =+Labor!$H$20 -> 54.893597
A11: DL REVENUE AT 100% | C11: =+C8*C9 -> 169093.86 | D11: =+D8*D9 -> 169093.86 | E11: =+E8*E9 -> 169093.86 | F11: =+F8*F9 -> 169093.86 | G11: =+G8*G9 -> 169093.86 | H11: =+H8*H9 -> 169093.86 | I11: =+I8*I9 -> 169093.86 | J11: =+J8*J9 -> 169093.86 | ... N11: =+N8*N9 -> 169093.86 | O11: =SUM(C11:N11) -> 2029126.3
A12: DL REVENUE W/CONFIDENCE LEVEL | C12: =C7*C11 -> 169093.86 | D12: =D7*D11 -> 169093.86 | E12: =E7*E11 -> 169093.86 | F12: =F7*F11 -> 169093.86 | G12: =G7*G11 -> 169093.86 | H12: =H7*H11 -> 169093.86 | I12: =I7*I11 -> 169093.86 | J12: =J7*J11 -> 169093.86 | ... N12: =N7*N11 -> 169093.86 | O12: =SUM(C12:N12) -> 2029126.3
A15: CUSTOMER | C15: CUSTOMER NAME
A16: CONFIDENCE LEVEL
A17: LOCAL
A18: CREW SIZE
A19: TOTAL PERSONNEL
A20: WEEKS OF PAYROLL
A21: WEEKLY HOURS
A22: EFFICIENCY
A23: TOTAL HOURS
A24: DIRECT LABOR RATE
A25: RATIO
A26: DL REVENUE AT 100% | C26: =IF(C24="",0,C23*C24*C25) -> 0 | D26: =IF(D24="",0,D23*D24*D25) -> 0 | E26: =IF(E24="",0,E23*E24*E25) -> 0 | F26: =IF(F24="",0,F23*F24*F25) -> 0 | G26: =IF(G24="",0,G23*G24*G25) -> 0 | H26: =IF(H24="",0,H23*H24*H25) -> 0 | I26: =IF(I24="",0,I23*I24*I25) -> 0 | J26: =IF(J24="",0,J23*J24*J25) -> 0 | ... N26: =IF(N24="",0,N23*N24*N25) -> 0
A27: DL REVENUE W/CONFIDENCE LEVEL | C27: =C16*C26 -> 0 | D27: =D16*D26 -> 0 | E27: =E16*E26 -> 0 | F27: =F16*F26 -> 0 | G27: =G16*G26 -> 0 | H27: =H16*H26 -> 0 | I27: =I16*I26 -> 0 | J27: =J16*J26 -> 0 | ... N27: =N16*N26 -> 0
A30: CUSTOMER | C30: CUSTOMER NAME
A31: CONFIDENCE LEVEL
A32: LOCAL
A33: CREW SIZE
A34: TOTAL PERSONNEL
A35: WEEKS OF PAYROLL
A36: WEEKLY HOURS
A37: EFFICIENCY
A38: TOTAL HOURS
A39: DIRECT LABOR RATE
A40: RATIO
A41: DL REVENUE AT 100%
A42: DL REVENUE W/CONFIDENCE LEVEL
A45: CUSTOMER | C45: CUSTOMER NAME
A46: CONFIDENCE LEVEL
A47: LOCAL
A48: CREW SIZE
A49: TOTAL PERSONNEL
A50: WEEKS OF PAYROLL
A51: WEEKLY HOURS
A52: EFFICIENCY
A53: TOTAL HOURS
A54: DIRECT LABOR RATE
A55: RATIO
A56: DL REVENUE AT 100%
A57: DL REVENUE W/CONFIDENCE LEVEL
A59: Total Revenue | C59: =+C11+C26+C41+C56 -> 169093.86 | D59: =+D11+D26+D41+D56 -> 169093.86 | E59: =+E11+E26+E41+E56 -> 169093.86 | F59: =+F11+F26+F41+F56 -> 169093.86 | G59: =+G11+G26+G41+G56 -> 169093.86 | H59: =+H11+H26+H41+H56 -> 169093.86 | I59: =+I11+I26+I41+I56 -> 169093.86 | J59: =+J11+J26+J41+J56 -> 169093.86 | ... N59: =+N11+N26+N41+N56 -> 169093.86 | O59: =SUM(C59:N59) -> 2029126.3
A60: Total Revenue w/Confidence Level | C60: =+C12+C27+C42+C57 -> 169093.86 | D60: =+D12+D27+D42+D57 -> 169093.86 | E60: =+E12+E27+E42+E57 -> 169093.86 | F60: =+F12+F27+F42+F57 -> 169093.86 | G60: =+G12+G27+G42+G57 -> 169093.86 | H60: =+H12+H27+H42+H57 -> 169093.86 | I60: =+I12+I27+I42+I57 -> 169093.86 | J60: =+J12+J27+J42+J57 -> 169093.86 | ... N60: =+N12+N27+N42+N57 -> 169093.86 | O60: =SUM(C60:N60) -> 2029126.3
A62: Total Cost | C62: =C8*C10 -> 64980.295 | D62: =D8*D10 -> 64980.295 | E62: =E8*E10 -> 64980.295 | F62: =F8*F10 -> 64980.295 | G62: =G8*G10 -> 64980.295 | H62: =H8*H10 -> 64980.295 | I62: =I8*I10 -> 64980.295 | J62: =J8*J10 -> 64980.295 | ... N62: =N8*N10 -> 64980.295 | O62: =SUM(C62:N62) -> 779763.54
A64: Total non billable Hours | C64: ='Labor Rates-DP'!T51 -> 501.25 | D64: ='Labor Rates-DP'!T52 -> 501.25 | E64: ='Labor Rates-DP'!T53 -> 501.25 | F64: ='Labor Rates-DP'!T54 -> 501.25 | G64: ='Labor Rates-DP'!T55 -> 501.25 | H64: ='Labor Rates-DP'!T56 -> 501.25 | I64: ='Labor Rates-DP'!T57 -> 501.25 | J64: ='Labor Rates-DP'!T58 -> 501.25 | K64: ='Labor Rates-DP'!T59 -> 501.25 | L64: ='Labor Rates-DP'!T60 -> 501.25 | M64: ='Labor Rates-DP'!T61 -> 501.25 | N64: ='Labor Rates-DP'!T62 -> 501.25 | O64: =SUM(C64:N64) -> 6015
A65: Average Labor Rate | C65: =C10 -> 54.893597 | D65: =D10 -> 54.893597 | E65: =E10 -> 54.893597 | F65: =F10 -> 54.893597 | G65: =G10 -> 54.893597 | H65: =H10 -> 54.893597 | I65: =I10 -> 54.893597 | J65: =J10 -> 54.893597 | ... N65: =N10 -> 54.893597
A66: Labor Cost Breakdown
A67: Direct Labor | C67: =C8*C10 -> 64980.295 | D67: =D8*D10 -> 64980.295 | E67: =E8*E10 -> 64980.295 | F67: =F8*F10 -> 64980.295 | G67: =G8*G10 -> 64980.295 | H67: =H8*H10 -> 64980.295 | I67: =I8*I10 -> 64980.295 | J67: =J8*J10 -> 64980.295 | ... N67: =N8*N10 -> 64980.295 | O67: =SUM(C67:N67) -> 779763.54
A68: Indirect Labor | C68: =C64*C65 -> 27515.415 | D68: =D64*D65 -> 27515.415 | E68: =E64*E65 -> 27515.415 | F68: =F64*F65 -> 27515.415 | G68: =G64*G65 -> 27515.415 | H68: =H64*H65 -> 27515.415 | I68: =I64*I65 -> 27515.415 | J68: =J64*J65 -> 27515.415 | ... N68: =N64*N65 -> 27515.415 | O68: =SUM(C68:N68) -> 330184.98
O69: =SUM(O67:O68) -> 1109948.5

Sheet Labor Rates-DP
A2: 2026 CVR Engineering Budget | O2: Revision Date | P2: 46002
A4: Labor & Expenses
B5: Annual | C5: Benefits | D5: Bonus% | E5: +Bonus | F5: Eff Hrly | H5: Meals/mo | I5: Phone/mo | J5: Supplies/mo | K5: Lodging/qtr | L5: Travel/qtr | M5: Training/qtr | N5: Licensure/qtr | O5: Software/yr | P5: Misc Total/yr
A6: Roy | B6: =Labor!H2 -> 198600.48 | C6: =B6*1.25 -> 248250.6 | D6: =Labor!X2 -> 0.15 | E6: =C6+(B6*D6) -> 278040.67 | F6: =E6/2000 -> 139.02034 | H6: 300 | I6: 60 | J6: 50 | K6: 500 | L6: 1000 | M6: 250 | N6: 250 | O6: 8000 | P6: =(H6*12)+(I6*12)+(J6*12)+(K6*4)+(L6*4)+(M6*4)+(N6*4)+O6 -> 20920 | S6: =B6/12 -> 16550.04
A7: Hayley | B7: =Labor!H3 -> 166335.73 | C7: =B7*1.25 -> 207919.66 | D7: =Labor!X3 -> 0.15 | E7: =C7+(B7*D7) -> 232870.02 | F7: =E7/2000 -> 116.43501 | H7: 100 | I7: 60 | J7: 50 | K7: 250 | L7: 750 | M7: 250 | N7: 100 | O7: 8000 | P7: =(H7*12)+(I7*12)+(J7*12)+(K7*4)+(L7*4)+(M7*4)+(N7*4)+O7 -> 15920 | S7: =B7/12 -> 13861.311
A8: Bhkti | B8: =Labor!H4 -> 120510 | C8: =B8*1.25 -> 150637.5 | D8: =Labor!X4 -> 0 | E8: =C8+(B8*D8) -> 150637.5 | F8: =E8/2000 -> 75.31875 | H8: 50 | I8: 60 | J8: 50 | K8: 250 | L8: 750 | M8: 250 | N8: 0 | O8: 8000 | P8: =(H8*12)+(I8*12)+(J8*12)+(K8*4)+(L8*4)+(M8*4)+(N8*4)+O8 -> 14920 | S8: =B8/12 -> 10042.5
A9: Joseph - PT | B9: =Labor!H5 -> 6427.2 | C9: =B9*1.25 -> 8034 | D9: =Labor!X5 -> 0 | E9: =C9+(B9*D9) -> 8034 | F9: =E9/2000 -> 4.017 | H9: 400 | I9: 60 | J9: 50 | K9: 500 | L9: 2000 | M9: 250 | N9: 100 | O9: 8000 | P9: =(H9*12)+(I9*12)+(J9*12)+(K9*4)+(L9*4)+(M9*4)+(N9*4)+O9 -> 25520 | S9: =B9/12 -> 535.6
A10: Kevin | B10: =Labor!H6 -> 126173.9 | C10: =B10*1.25 -> 157717.37 | D10: =Labor!X6 -> 0 | E10: =C10+(B10*D10) -> 157717.37 | F10: =E10/2000 -> 78.858686 | H10: 50 | I10: 60 | J10: 50 | K10: 250 | L10: 500 | M10: 250 | N10: 0 | O10: 8000 | P10: =(H10*12)+(I10*12)+(J10*12)+(K10*4)+(L10*4)+(M10*4)+(N10*4)+O10 -> 13920 | S10: =B10/12 -> 10514.491
A11: Craig | B11: =Labor!H7 -> 92288 | C11: =B11*1.25 -> 115360 | D11: =Labor!X7 -> 0 | E11: =C11+(B11*D11) -> 115360 | F11: =E11/2000 -> 57.68 | H11: 50 | I11: 60 | J11: 50 | K11: 250 | L11: 500 | M11: 250 | N11: 0 | O11: 8000 | P11: =(H11*12)+(I11*12)+(J11*12)+(K11*4)+(L11*4)+(M11*4)+(N11*4)+O11 -> 13920 | S11: =B11/12 -> 7690.6667
A12: Taylor | B12: =Labor!H8 -> 105575 | C12: =B12*1.25 -> 131968.75 | D12: =Labor!X8 -> 0 | E12: =C12+(B12*D12) -> 131968.75 | F12: =E12/2000 -> 65.984373 | H12: 50 | I12: 60 | J12: 50 | K12: 250 | L12: 500 | M12: 250 | N12: 0 | O12: 8000 | P12: =(H12*12)+(I12*12)+(J12*12)+(K12*4)+(L12*4)+(M12*4)+(N12*4)+O12 -> 13920 | S12: =B12/12 -> 8797.9165
A13: Collin | B13: =Labor!H9 -> 64272 | C13: =B13*1.25 -> 80340 | D13: =Labor!X9 -> 0 | E13: =C13+(B13*D13) -> 80340 | F13: =E13/2000 -> 40.17 | H13: 50 | I13: 60 | J13: 50 | K13: 250 | L13: 500 | M13: 250 | N13: 0 | O13: 8000 | P13: =(H13*12)+(I13*12)+(J13*12)+(K13*4)+(L13*4)+(M13*4)+(N13*4)+O13 -> 13920 | S13: =B13/12 -> 5356
A14: Francis | B14: =Labor!H10 -> 132355 | C14: =B14*1.25 -> 165443.75 | D14: =Labor!X10 -> 0 | E14: =C14+(B14*D14) -> 165443.75 | F14: =E14/2000 -> 82.721873 | H14: 50 | I14: 60 | J14: 50 | K14: 250 | L14: 750 | M14: 250 | N14: 100 | O14: 8000 | P14: =(H14*12)+(I14*12)+(J14*12)+(K14*4)+(L14*4)+(M14*4)+(N14*4)+O14 -> 15320 | S14: =B14/12 -> 11029.583
A15: Alicia | B15: =Labor!H11 -> 92082.002 | C15: =B15*1.25 -> 115102.5 | D15: =Labor!X11 -> 0 | E15: =C15+(B15*D15) -> 115102.5 | F15: 120 | H15: 50 | I15: 60 | J15: 50 | K15: 250 | L15: 500 | M15: 250 | N15: 0 | O15: 8000 | P15: =(H15*12)+(I15*12)+(J15*12)+(K15*4)+(L15*4)+(M15*4)+(N15*4)+O15 -> 13920 | S15: =B15/12 -> 7673.5001
A16: Auston - PT | B16: =Labor!H12 -> 1151.54 | C16: =B16*1.25 -> 1439.425 | D16: =Labor!X12 -> 0 | E16: =C16+(B16*D16) -> 1439.425 | F16: 20 | H16: 0 | I16: 0 | K16: 0 | L16: 0 | M16: 0 | N16: 0 | O16: 8000 | P16: =(H16*12)+(I16*12)+(J16*12)+(K16*4)+(L16*4)+(M16*4)+(N16*4)+O16 -> 8000 | S16: =B16/12 -> 95.961667
A17: Randy - PT | B17: =Labor!H13 -> 4177.68 | C17: =B17*1.25 -> 5222.1 | D17: =Labor!X13 -> 0 | E17: =C17+(B17*D17) -> 5222.1 | F17: 78 | H17: 0 | I17: 0 | J17: 50 | K17: 100 | L17: 100 | M17: 250 | N17: 0 | O17: 8000 | P17: =(H17*12)+(I17*12)+(J17*12)+(K17*4)+(L17*4)+(M17*4)+(N17*4)+O17 -> 10400 | S17: =B17/12 -> 348.14
B19: =SUM(B6:B17) -> 1109948.5 | C19: =SUM(C6:C17) -> 1387435.7 | D19: =E20-C19 -> 54740.432 | H19: =SUM(H6:H17)*12 -> 13800 | I19: =SUM(I6:I17)*12 -> 7200 | J19: =SUM(J6:J17)*12 -> 6600 | K19: =SUM(K6:K17)*4 -> 12400 | L19: =SUM(L6:L17)*4 -> 31400 | M19: =SUM(M6:M17)*4 -> 11000 | N19: =SUM(N6:N17)*4 -> 2200 | O19: =SUM(O6:O17) -> 96000 | P19: =SUM(P6:P18) -> 180600 | S19: =B19/12 -> 92495.71
D20: Labor Total | E20: =SUM(E6:E17) -> 1442176.1 | H20: Annual | I20: Annual | J20: Annual | K20: Annual | L20: Annual | M20: Annual | N20: Annual | O20: Annual | P20: Annual
B21: =B19/B45 -> 54.893597 | P21: 60000 | Q21: Insurance
C22: =C19-B19 -> 277487.13 | D22: Calc'd at 25% (previously used 35%) | O22: =SUM(P22:P24) -> 207000 | P22: 0 | Q22: 0.25
C23: =(B19+D19)*5% -> 58234.448 | D23: Retirement | P23: 0 | Q23: 0.2
C24: =Labor!N16 -> 118800 | D24: Health Ins | K24: USC Overhead Allocation | P24: ='Corp OH Alloc & Interest Exp'!B5 -> 207000
C25: =SUM(Labor!O16:R16)+D19*0.0765 -> 91177.437 | D25: Taxes
C26: 0 | D26: Life Ins/other? | O26: Group Total | P26: =(SUM(P6:P17)+SUM(P21:P24))+E20 -> 1889776.1
C27: =Labor!S16 -> 11099.485 | D27: Workers Comp | E27: =C22-C23-C24-C25-C26-C27 -> -1824.2391 | F27: Check
A28: Revenue | J28: Non-Billable | K28: Bids
B29: Total Hrs | C29: Vacation | D29: Non-Billable | E29: Bids | F29: Billable | H29: Bill Rate | I29: Billable $ | J29: Percentage | K29: Percentage | L29: Billable Utilization | N29: Vacation Annual Estimate
A30: Roy | B30: 2080 | C30: 120 | D30: =(B30-C30)*J30 -> 588 | E30: =(B30-C30)*K30 -> 490 | F30: =B30-C30-D30-E30 -> 882 | H30: 308.7 | I30: =H30*F30 -> 272273.4 | J30: 0.3 | K30: 0.25 | L30: =F30/B30 -> 0.42403846 | N30: =(B6/B30)*C30 -> 11457.72
A31: Hayley | B31: 2080 | C31: 120 | D31: =(B31-C31)*J31 -> 294 | E31: =(B31-C31)*K31 -> 392 | F31: =B31-C31-D31-E31 -> 1274 | H31: 241.57 | I31: =H31*F31 -> 307760.18 | J31: 0.15 | K31: 0.2 | L31: =F31/B31 -> 0.6125 | N31: =(B7/B31)*C31 -> 9596.2921
A32: Bhkti | B32: 2080 | C32: 120 | D32: =(B32-C32)*J32 -> 294 | E32: =(B32-C32)*K32 -> 196 | F32: =B32-C32-D32-E32 -> 1470 | H32: 152.21 | I32: =H32*F32 -> 223748.7 | J32: 0.15 | K32: 0.1 | L32: =F32/B32 -> 0.70673077 | N32: =(B8/B32)*C32 -> 6952.5
A33: Mike C. - PT | B33: 500 | C33: 0 | D33: =(B33-C33)*J33 -> 500 | E33: =(B33-C33)*K33 -> 0 | F33: =B33-C33-D33-E33 -> 0 | H33: 308.7 | I33: =H33*F33 -> 0 | J33: 1 | K33: 0 | L33: =F33/B33 -> 0 | N33: =(B9/B33)*C33 -> 0
A34: Kevin | B34: 2080 | C34: 120 | D34: =(B34-C34)*J34 -> 294 | E34: =(B34-C34)*K34 -> 98 | F34: =B34-C34-D34-E34 -> 1568 | H34: 132.6 | I34: =H34*F34 -> 207916.8 | J34: 0.15 | K34: 0.05 | L34: =F34/B34 -> 0.75384615 | N34: =(B10/B34)*C34 -> 7279.2633
A35: Craig | B35: 2080 | C35: 120 | D35: =(B35-C35)*J35 -> 294 | E35: =(B35-C35)*K35 -> 98 | F35: =B35-C35-D35-E35 -> 1568 | H35: 112.27 | I35: =H35*F35 -> 176039.36 | J35: 0.15 | K35: 0.05 | L35: =F35/B35 -> 0.75384615 | N35: =(B11/B35)*C35 -> 5324.3077
A36: Taylor | B36: 2080 | C36: 120 | D36: =(B36-C36)*J36 -> 294 | E36: =(B36-C36)*K36 -> 0 | F36: =B36-C36-D36-E36 -> 1666 | H36: 112.27 | I36: =H36*F36 -> 187041.82 | J36: 0.15 | K36: 0 | L36: =F36/B36 -> 0.80096154 | N36: =(B12/B36)*C36 -> 6090.8652
A37: Collin | B37: 2080 | C37: 120 | D37: =(B37-C37)*J37 -> 294 | E37: =(B37-C37)*K37 -> 0 | F37: =B37-C37-D37-E37 -> 1666 | H37: 76.14 | I37: =H37*F37 -> 126849.24 | J37: 0.15 | K37: 0 | L37: =F37/B37 -> 0.80096154 | N37: =(B13/B37)*C37 -> 3708
A38: Francis | B38: 2080 | C38: 120 | D38: =(B38-C38)*J38 -> 294 | E38: =(B38-C38)*K38 -> 196 | F38: =B38-C38-D38-E38 -> 1470 | H38: 152.21 | I38: =H38*F38 -> 223748.7 | J38: 0.15 | K38: 0.1 | L38: =F38/B38 -> 0.70673077 | N38: =(B14/B38)*C38 -> 7635.8652
A39: Alicia | B39: 2080 | C39: 120 | D39: =(B39-C39)*J39 -> 294 | E39: =(B39-C39)*K39 -> 0 | F39: =B39-C39-D39-E39 -> 1666 | H39: 102.1 | I39: =H39*F39 -> 170098.6 | J39: 0.15 | K39: 0 | L39: =F39/B39 -> 0.80096154 | N39: =(B15/B39)*C39 -> 5312.4232
A40: Auston - PT | B40: 500 | C40: 0 | D40: =(B40-C40)*J40 -> 0 | E40: =(B40-C40)*K40 -> 0 | F40: =B40-C40-D40-E40 -> 500 | H40: 76.14 | I40: =H40*F40 -> 38070 | J40: 0 | K40: 0 | L40: =F40/B40 -> 1 | N40: =(B16/B40)*C40 -> 0
A41: Randy - PT | B41: 500 | C41: 0 | D41: =(B41-C41)*J41 -> 0 | E41: =(B41-C41)*K41 -> 25 | F41: =B41-C41-D41-E41 -> 475 | H41: 201.22 | I41: =H41*F41 -> 95579.5 | J41: 0 | K41: 0.05 | L41: =F41/B41 -> 0.95 | N41: =(B17/B41)*C41 -> 0
O44: Net Profit | P44: =I46-P26 -> 139350.21
B45: =SUM(B30:B41) -> 20220 | C45: =SUM(C30:C41) -> 1080 | D45: =SUM(D30:D41) -> 3440 | E45: =SUM(E30:E41) -> 1495 | F45: =SUM(F30:F41) -> 14205 | M45: =SUM(N30:N41) -> 63357.237
F46: =+F45/B45 -> 0.70252226 | I46: =SUM(I30:I45) -> 2029126.3 | J46: Revenue | O46: Net Margin | P46: =(I46-P26)/I46 -> 0.068674982
I48: =+I46/F45 -> 142.84592 | J48: Composite Rate
A49: Assumptions
A50: 1 | B50: Revenue to be calculated based on amount of Billable Hours | N50: Revenue Breakdown | Q50: Billable Hrs at % of revenue | T50: Unbillable hrs-% of revenue
A51: 2 | B51: Total Hrs = (52 wks x 40 hrs/wk) | N51: Jan | O51: =$I$46/12 -> 169093.86 | P51: =O51/O$64 -> 0.083333333 | Q51: =F$45*P51 -> 1183.75 | T51: =(D$45+C$45+E$45)*P51 -> 501.25
A52: 3 | B52: Non-Billable Hours = administrative, down time, and other non-billable time - % determined by Roy and Bret | N52: Feb | O52: =$I$46/12 -> 169093.86 | P52: =O52/O$64 -> 0.083333333 | Q52: =F$45*P52 -> 1183.75 | T52: =(D$45+C$45+E$45)*P52 -> 501.25
A53: 4 | B53: Bids = preliminary design and proposal development efforts - % determined by Roy and Bret | N53: Mar | O53: =$I$46/12 -> 169093.86 | P53: =O53/O$64 -> 0.083333333 | Q53: =F$45*P53 -> 1183.75 | T53: =(D$45+C$45+E$45)*P53 -> 501.25
A54: 5 | B54: Bill Rate takes into account most conservativce hourly billing rate (e.g. Roy can be billed as Principal or Senior Engineer) | N54: Apr | O54: =$I$46/12 -> 169093.86 | P54: =O54/O$64 -> 0.083333333 | Q54: =F$45*P54 -> 1183.75 | T54: =(D$45+C$45+E$45)*P54 -> 501.25
A55: 6 | B55: CVR Engineering administrative tasks (invoicing, tracking, etc.) to be taken care of by Roy & Pamela | N55: May | O55: =$I$46/12 -> 169093.86 | P55: =O55/O$64 -> 0.083333333 | Q55: =F$45*P55 -> 1183.75 | T55: =(D$45+C$45+E$45)*P55 -> 501.25
A56: 7 | B56: USC Allocations based on time breakdown (%) as indicated on 2026 Special Projects Budget | N56: Jun | O56: =$I$46/12 -> 169093.86 | P56: =O56/O$64 -> 0.083333333 | Q56: =F$45*P56 -> 1183.75 | T56: =(D$45+C$45+E$45)*P56 -> 501.25
N57: Jul | O57: =$I$46/12 -> 169093.86 | P57: =O57/O$64 -> 0.083333333 | Q57: =F$45*P57 -> 1183.75 | T57: =(D$45+C$45+E$45)*P57 -> 501.25
N58: Aug | O58: =$I$46/12 -> 169093.86 | P58: =O58/O$64 -> 0.083333333 | Q58: =F$45*P58 -> 1183.75 | T58: =(D$45+C$45+E$45)*P58 -> 501.25
N59: Sep | O59: =$I$46/12 -> 169093.86 | P59: =O59/O$64 -> 0.083333333 | Q59: =F$45*P59 -> 1183.75 | T59: =(D$45+C$45+E$45)*P59 -> 501.25
N60: Oct | O60: =$I$46/12 -> 169093.86 | P60: =O60/O$64 -> 0.083333333 | Q60: =F$45*P60 -> 1183.75 | T60: =(D$45+C$45+E$45)*P60 -> 501.25
N61: Nov | O61: =$I$46/12 -> 169093.86 | P61: =O61/O$64 -> 0.083333333 | Q61: =F$45*P61 -> 1183.75 | T61: =(D$45+C$45+E$45)*P61 -> 501.25
N62: Dec | O62: =$I$46/12 -> 169093.86 | P62: =O62/O$64 -> 0.083333333 | Q62: =F$45*P62 -> 1183.75 | T62: =(D$45+C$45+E$45)*P62 -> 501.25
N64: Total | O64: =SUM(O51:O62) -> 2029126.3 | P64: =SUM(P51:P62) -> 1 | Q64: =SUM(Q51:Q62) -> 14205 | T64: =SUM(T51:T63) -> 6015

Sheet Revenue and Direct Lbr
B2: January | F2: February | J2: March | N2: April | R2: May | V2: June | Z2: July | AD2: August | AH2: September | AL2: October | AP2: November | AT2: December
B3: 2026 | C3: =B3 -> 2026 | D3: =B3 -> 2026 | F3: =+B3 -> 2026 | G3: =F3 -> 2026 | H3: =F3 -> 2026 | J3: =+B3 -> 2026 | K3: =J3 -> 2026 | L3: =J3 -> 2026 | N3: =+B3 -> 2026 | O3: =N3 -> 2026 | P3: =N3 -> 2026 | R3: =+B3 -> 2026 | S3: =R3 -> 2026 | T3: =R3 -> 2026 | V3: =+B3 -> 2026 | W3: =V3 -> 2026 | X3: =V3 -> 2026 | Z3: =+B3 -> 2026 | AA3: =Z3 -> 2026 | AB3: =Z3 -> 2026 | AD3: =+B3 -> 2026 | AE3: =AD3 -> 2026 | AF3: =AD3 -> 2026 | AH3: =+B3 -> 2026 | AI3: =AH3 -> 2026 | AJ3: =AH3 -> 2026 | AL3: =+B3 -> 2026 | AM3: =AL3 -> 2026 | AN3: =AL3 -> 2026 | AP3: =+B3 -> 2026 | AQ3: =AP3 -> 2026 | AR3: =AP3 -> 2026 | AT3: =+B3 -> 2026 | AU3: =AT3 -> 2026 | AV3: =AT3 -> 2026 | AX3: =+B3 -> 2026 | AY3: =AX3 -> 2026 | AZ3: =+AX3 -> 2026
B4: Budgeted | C4: Budgeted | D4: Budgeted | F4: Budgeted | G4: Budgeted | H4: Budgeted | J4: Budgeted | K4: Budgeted | L4: Budgeted | N4: Budgeted | O4: Budgeted | P4: Budgeted | R4: Budgeted | S4: Budgeted | T4: Budgeted | V4: Budgeted | W4: Budgeted | X4: Budgeted | Z4: Budgeted | AA4: Budgeted | AB4: Budgeted | AD4: Budgeted | AE4: Budgeted | AF4: Budgeted | AH4: Budgeted | AI4: Budgeted | AJ4: Budgeted | AL4: Budgeted | AM4: Budgeted | AN4: Budgeted | AP4: Budgeted | AQ4: Budgeted | AR4: Budgeted | AT4: Budgeted | AU4: Budgeted | AV4: Budgeted | AX4: Total Budgeted | AY4: Budgeted | AZ4: Total Budgeted
B5: $ | C5: Labor | D5: $ | F5: $ | G5: Labor | H5: $ | J5: $ | K5: Labor | L5: $ | N5: $ | O5: Labor | P5: $ | R5: $ | S5: Labor | T5: $ | V5: $ | W5: Labor | X5: $ | Z5: $ | AA5: Labor | AB5: $ | AD5: $ | AE5: Labor | AF5: $ | AH5: $ | AI5: Labor | AJ5: $ | AL5: $ | AM5: Labor | AN5: $ | AP5: $ | AQ5: Labor | AR5: $ | AT5: $ | AU5: Labor | AV5: $ | AX5: $ | AY5: Labor | AZ5: $
A6: Labor Sales | B6: Sales | C6: Ratio | D6: Labor | F6: Sales | G6: Ratio | H6: Labor | J6: Sales | K6: Ratio | L6: Labor | N6: Sales | O6: Ratio | P6: Labor | R6: Sales | S6: Ratio | T6: Labor | V6: Sales | W6: Ratio | X6: Labor | Z6: Sales | AA6: Ratio | AB6: Labor | AD6: Sales | AE6: Ratio | AF6: Labor | AH6: Sales | AI6: Ratio | AJ6: Labor | AL6: Sales | AM6: Ratio | AN6: Labor | AP6: Sales | AQ6: Ratio | AR6: Labor | AT6: Sales | AU6: Ratio | AV6: Labor | AX6: Sales | AY6: Ratio | AZ6: Labor
A7: =+'06-60 EPC'!C1 -> 06-60 EPC
A8: =+'06-60 EPC'!C6 -> Engineering | B8: ='06-60 EPC'!C12 -> 169093.86 | C8: =IF(B8=0,0,B8/D8) -> 2.6022328 | D8: =+'06-60 EPC'!C67 -> 64980.295 | F8: ='06-60 EPC'!D12 -> 169093.86 | G8: =C8 -> 2.6022328 | H8: =+F8/G8 -> 64980.295 | J8: ='06-60 EPC'!E12 -> 169093.86 | K8: =C8 -> 2.6022328 | L8: =+J8/K8 -> 64980.295 | N8: ='06-60 EPC'!F12 -> 169093.86 | O8: =C8 -> 2.6022328 | P8: =+N8/O8 -> 64980.295 | R8: ='06-60 EPC'!G12 -> 169093.86 | S8: =C8 -> 2.6022328 | T8: =+R8/S8 -> 64980.295 | V8: ='06-60 EPC'!H12 -> 169093.86 | W8: =C8 -> 2.6022328 | X8: =+V8/W8 -> 64980.295 | Z8: ='06-60 EPC'!I12 -> 169093.86 | AA8: =C8 -> 2.6022328 | AB8: =+Z8/AA8 -> 64980.295 | AD8: ='06-60 EPC'!J12 -> 169093.86 | AE8: =C8 -> 2.6022328 | AF8: =+AD8/AE8 -> 64980.295 | AH8: ='06-60 EPC'!K12 -> 169093.86 | AI8: =C8 -> 2.6022328 | AJ8: =+AH8/AI8 -> 64980.295 | AL8: ='06-60 EPC'!L12 -> 169093.86 | AM8: =C8 -> 2.6022328 | AN8: =+AL8/AM8 -> 64980.295 | AP8: ='06-60 EPC'!M12 -> 169093.86 | AQ8: =C8 -> 2.6022328 | AR8: =+AP8/AQ8 -> 64980.295 | AT8: ='06-60 EPC'!N12 -> 169093.86 | AU8: =C8 -> 2.6022328 | AV8: =+AT8/AU8 -> 64980.295 | AX8: =+B8+F8+J8+N8+R8+V8+Z8+AD8+AH8+AL8+AP8+AT8 -> 2029126.3 | AY8: =IF(AX8=0,0,AX8/AZ8) -> 2.6022328 | AZ8: =+D8+H8+L8+P8+T8+X8+AB8+AF8+AJ8+AN8+AR8+AV8 -> 779763.54
A9: =+'06-60 EPC'!C15 -> CUSTOMER NAME | B9: =+'06-60 EPC'!C27 -> 0 | C9: =+'06-60 EPC'!C25 -> 0 | D9: =IF(B9=0,0,B9/C9) -> 0 | F9: =+'06-60 EPC'!D27 -> 0 | G9: =+'06-60 EPC'!D25 -> 0 | H9: =IF(F9=0,0,F9/G9) -> 0 | J9: =+'06-60 EPC'!E27 -> 0 | K9: =+'06-60 EPC'!E25 -> 0 | L9: =IF(J9=0,0,J9/K9) -> 0 | N9: =+'06-60 EPC'!F27 -> 0 | O9: =+'06-60 EPC'!F25 -> 0 | P9: =IF(N9=0,0,N9/O9) -> 0 | R9: =+'06-60 EPC'!G27 -> 0 | S9: =+'06-60 EPC'!G25 -> 0 | T9: =IF(R9=0,0,R9/S9) -> 0 | V9: =+'06-60 EPC'!H27 -> 0 | W9: =+'06-60 EPC'!H25 -> 0 | X9: =IF(V9=0,0,V9/W9) -> 0 | Z9: =+'06-60 EPC'!I27 -> 0 | AA9: =+'06-60 EPC'!I25 -> 0 | AB9: =IF(Z9=0,0,Z9/AA9) -> 0 | AD9: =+'06-60 EPC'!J27 -> 0 | AE9: =+'06-60 EPC'!J25 -> 0 | AF9: =IF(AD9=0,0,AD9/AE9) -> 0 | AH9: =+'06-60 EPC'!K27 -> 0 | AI9: =+'06-60 EPC'!K25 -> 0 | AJ9: =IF(AH9=0,0,AH9/AI9) -> 0 | AL9: =+'06-60 EPC'!L27 -> 0 | AM9: =+'06-60 EPC'!L25 -> 0 | AN9: =IF(AL9=0,0,AL9/AM9) -> 0 | AP9: =+'06-60 EPC'!M27 -> 0 | AQ9: =+'06-60 EPC'!M25 -> 0 | AR9: =IF(AP9=0,0,AP9/AQ9) -> 0 | AT9: =+'06-60 EPC'!N27 -> 0 | AU9: =+'06-60 EPC'!N25 -> 0 | AV9: =IF(AT9=0,0,AT9/AU9) -> 0 | AX9: =+B9+F9+J9+N9+R9+V9+Z9+AD9+AH9+AL9+AP9+AT9 -> 0 | AY9: =IF(AX9=0,0,AX9/AZ9) -> 0 | AZ9: =+D9+H9+L9+P9+T9+X9+AB9+AF9+AJ9+AN9+AR9+AV9 -> 0
A10: =+'06-60 EPC'!C30 -> CUSTOMER NAME | B10: =+'06-60 EPC'!C42 -> 0 | C10: =+'06-60 EPC'!C40 -> 0 | D10: =IF(B10=0,0,B10/C10) -> 0 | F10: =+'06-60 EPC'!D42 -> 0 | G10: =+'06-60 EPC'!D40 -> 0 | H10: =IF(F10=0,0,F10/G10) -> 0 | J10: =+'06-60 EPC'!E42 -> 0 | K10: =+'06-60 EPC'!E40 -> 0 | L10: =IF(J10=0,0,J10/K10) -> 0 | N10: =+'06-60 EPC'!F42 -> 0 | O10: =+'06-60 EPC'!F40 -> 0 | P10: =IF(N10=0,0,N10/O10) -> 0 | R10: =+'06-60 EPC'!G42 -> 0 | S10: =+'06-60 EPC'!G40 -> 0 | T10: =IF(R10=0,0,R10/S10) -> 0 | V10: =+'06-60 EPC'!H42 -> 0 | W10: =+'06-60 EPC'!H40 -> 0 | X10: =IF(V10=0,0,V10/W10) -> 0 | Z10: =+'06-60 EPC'!I42 -> 0 | AA10: =+'06-60 EPC'!I40 -> 0 | AB10: =IF(Z10=0,0,Z10/AA10) -> 0 | AD10: =+'06-60 EPC'!J42 -> 0 | AE10: =+'06-60 EPC'!J40 -> 0 | AF10: =IF(AD10=0,0,AD10/AE10) -> 0 | AH10: =+'06-60 EPC'!K42 -> 0 | AI10: =+'06-60 EPC'!K40 -> 0 | AJ10: =IF(AH10=0,0,AH10/AI10) -> 0 | AL10: =+'06-60 EPC'!L42 -> 0 | AM10: =+'06-60 EPC'!L40 -> 0 | AN10: =IF(AL10=0,0,AL10/AM10) -> 0 | AP10: =+'06-60 EPC'!M42 -> 0 | AQ10: =+'06-60 EPC'!M40 -> 0 | AR10: =IF(AP10=0,0,AP10/AQ10) -> 0 | AT10: =+'06-60 EPC'!N42 -> 0 | AU10: =+'06-60 EPC'!N40 -> 0 | AV10: =IF(AT10=0,0,AT10/AU10) -> 0 | AX10: =+B10+F10+J10+N10+R10+V10+Z10+AD10+AH10+AL10+AP10+AT10 -> 0 | AY10: =IF(AX10=0,0,AX10/AZ10) -> 0 | AZ10: =+D10+H10+L10+P10+T10+X10+AB10+AF10+AJ10+AN10+AR10+AV10 -> 0
A11: =+'06-60 EPC'!C45 -> CUSTOMER NAME | B11: =+'06-60 EPC'!C57 -> 0 | C11: =+'06-60 EPC'!C55 -> 0 | D11: =IF(B11=0,0,B11/C11) -> 0 | F11: =+'06-60 EPC'!D57 -> 0 | G11: =+'06-60 EPC'!D55 -> 0 | H11: =IF(F11=0,0,F11/G11) -> 0 | J11: =+'06-60 EPC'!E57 -> 0 | K11: =+'06-60 EPC'!E55 -> 0 | L11: =IF(J11=0,0,J11/K11) -> 0 | N11: =+'06-60 EPC'!F57 -> 0 | O11: =+'06-60 EPC'!F55 -> 0 | P11: =IF(N11=0,0,N11/O11) -> 0 | R11: =+'06-60 EPC'!G57 -> 0 | S11: =+'06-60 EPC'!G55 -> 0 | T11: =IF(R11=0,0,R11/S11) -> 0 | V11: =+'06-60 EPC'!H57 -> 0 | W11: =+'06-60 EPC'!H55 -> 0 | X11: =IF(V11=0,0,V11/W11) -> 0 | Z11: =+'06-60 EPC'!I57 -> 0 | AA11: =+'06-60 EPC'!I55 -> 0 | AB11: =IF(Z11=0,0,Z11/AA11) -> 0 | AD11: =+'06-60 EPC'!J57 -> 0 | AE11: =+'06-60 EPC'!J55 -> 0 | AF11: =IF(AD11=0,0,AD11/AE11) -> 0 | AH11: =+'06-60 EPC'!K57 -> 0 | AI11: =+'06-60 EPC'!K55 -> 0 | AJ11: =IF(AH11=0,0,AH11/AI11) -> 0 | AL11: =+'06-60 EPC'!L57 -> 0 | AM11: =+'06-60 EPC'!L55 -> 0 | AN11: =IF(AL11=0,0,AL11/AM11) -> 0 | AP11: =+'06-60 EPC'!M57 -> 0 | AQ11: =+'06-60 EPC'!M55 -> 0 | AR11: =IF(AP11=0,0,AP11/AQ11) -> 0 | AT11: =+'06-60 EPC'!N57 -> 0 | AU11: =+'06-60 EPC'!N55 -> 0 | AV11: =IF(AT11=0,0,AT11/AU11) -> 0 | AX11: =+B11+F11+J11+N11+R11+V11+Z11+AD11+AH11+AL11+AP11+AT11 -> 0 | AY11: =IF(AX11=0,0,AX11/AZ11) -> 0 | AZ11: =+D11+H11+L11+P11+T11+X11+AB11+AF11+AJ11+AN11+AR11+AV11 -> 0
A12: Total Renewables | B12: =SUM(B8:B11) -> 169093.86 | C12: =IF(B12=0,0,B12/D12) -> 2.6022328 | D12: =SUM(D8:D11) -> 64980.295 | F12: =SUM(F8:F11) -> 169093.86 | G12: =IF(F12=0,0,F12/H12) -> 2.6022328 | H12: =SUM(H8:H11) -> 64980.295 | J12: =SUM(J8:J11) -> 169093.86 | K12: =IF(J12=0,0,J12/L12) -> 2.6022328 | L12: =SUM(L8:L11) -> 64980.295 | N12: =SUM(N8:N11) -> 169093.86 | O12: =IF(N12=0,0,N12/P12) -> 2.6022328 | P12: =SUM(P8:P11) -> 64980.295 | R12: =SUM(R8:R11) -> 169093.86 | S12: =IF(R12=0,0,R12/T12) -> 2.6022328 | T12: =SUM(T8:T11) -> 64980.295 | V12: =SUM(V8:V11) -> 169093.86 | W12: =IF(V12=0,0,V12/X12) -> 2.6022328 | X12: =SUM(X8:X11) -> 64980.295 | Z12: =SUM(Z8:Z11) -> 169093.86 | AA12: =IF(Z12=0,0,Z12/AB12) -> 2.6022328 | AB12: =SUM(AB8:AB11) -> 64980.295 | AD12: =SUM(AD8:AD11) -> 169093.86 | AE12: =IF(AD12=0,0,AD12/AF12) -> 2.6022328 | AF12: =SUM(AF8:AF11) -> 64980.295 | AH12: =SUM(AH8:AH11) -> 169093.86 | AI12: =IF(AH12=0,0,AH12/AJ12) -> 2.6022328 | AJ12: =SUM(AJ8:AJ11) -> 64980.295 | AL12: =SUM(AL8:AL11) -> 169093.86 | AM12: =IF(AL12=0,0,AL12/AN12) -> 2.6022328 | AN12: =SUM(AN8:AN11) -> 64980.295 | AP12: =SUM(AP8:AP11) -> 169093.86 | AQ12: =IF(AP12=0,0,AP12/AR12) -> 2.6022328 | AR12: =SUM(AR8:AR11) -> 64980.295 | AT12: =SUM(AT8:AT11) -> 169093.86 | AU12: =IF(AT12=0,0,AT12/AV12) -> 2.6022328 | AV12: =SUM(AV8:AV11) -> 64980.295 | AX12: =SUM(AX8:AX11) -> 2029126.3 | AY12: =IF(AX12=0,0,AX12/AZ12) -> 2.6022328 | AZ12: =SUM(AZ8:AZ11) -> 779763.54
A14: Total Labor Sales | B14: =+B12 -> 169093.86 | C14: =IF(B14=0,0,B14/D14) -> 2.6022328 | D14: =+D12 -> 64980.295 | F14: =+F12 -> 169093.86 | G14: =IF(F14=0,0,F14/H14) -> 2.6022328 | H14: =+H12 -> 64980.295 | J14: =+J12 -> 169093.86 | K14: =IF(J14=0,0,J14/L14) -> 2.6022328 | L14: =+L12 -> 64980.295 | N14: =+N12 -> 169093.86 | O14: =IF(N14=0,0,N14/P14) -> 2.6022328 | P14: =+P12 -> 64980.295 | R14: =+R12 -> 169093.86 | S14: =IF(R14=0,0,R14/T14) -> 2.6022328 | T14: =+T12 -> 64980.295 | V14: =+V12 -> 169093.86 | W14: =IF(V14=0,0,V14/X14) -> 2.6022328 | X14: =+X12 -> 64980.295 | Z14: =+Z12 -> 169093.86 | AA14: =IF(Z14=0,0,Z14/AB14) -> 2.6022328 | AB14: =+AB12 -> 64980.295 | AD14: =+AD12 -> 169093.86 | AE14: =IF(AD14=0,0,AD14/AF14) -> 2.6022328 | AF14: =+AF12 -> 64980.295 | AH14: =+AH12 -> 169093.86 | AI14: =IF(AH14=0,0,AH14/AJ14) -> 2.6022328 | AJ14: =+AJ12 -> 64980.295 | AL14: =+AL12 -> 169093.86 | AM14: =IF(AL14=0,0,AL14/AN14) -> 2.6022328 | AN14: =+AN12 -> 64980.295 | AP14: =+AP12 -> 169093.86 | AQ14: =IF(AP14=0,0,AP14/AR14) -> 2.6022328 | AR14: =+AR12 -> 64980.295 | AT14: =+AT12 -> 169093.86 | AU14: =IF(AT14=0,0,AT14/AV14) -> 2.6022328 | AV14: =+AV12 -> 64980.295 | AX14: =+AX12 -> 2029126.3 | AZ14: =+AZ12 -> 779763.54
B15: (Used) | D15: (Used) | F15: (Used) | H15: (Used) | J15: (Used) | L15: (Used) | N15: (Used) | P15: (Used) | R15: (Used) | T15: (Used) | V15: (Used) | X15: (Used) | Z15: (Used) | AB15: (Used) | AD15: (Used) | AF15: (Used) | AH15: (Used) | AJ15: (Used) | AL15: (Used) | AN15: (Used) | AP15: (Used) | AR15: (Used) | AT15: (Used) | AV15: (Used)
A18: Material & Subcontract Sales
A19: Material Sales
A20: WIP Adjustment-Material
A21: Subcontract Sales
A22: Total Material & Subcontract Sales
C24: =B25 -> 2026 | D24: =B25 -> 2026 | G24: =F25 -> 2026 | H24: =F25 -> 2026 | K24: =J25 -> 2026 | L24: =J25 -> 2026 | O24: =N25 -> 2026 | P24: =N25 -> 2026 | S24: =R25 -> 2026 | T24: =R25 -> 2026 | W24: =V25 -> 2026 | X24: =V25 -> 2026 | AA24: =Z25 -> 2026 | AB24: =Z25 -> 2026 | AE24: =AD25 -> 2026 | AF24: =AD25 -> 2026 | AI24: =AH25 -> 2026 | AJ24: =AH25 -> 2026 | AM24: =AL25 -> 2026 | AN24: =AL25 -> 2026 | AQ24: =AP25 -> 2026 | AR24: =AP25 -> 2026 | AU24: =AT25 -> 2026 | AV24: =AT25 -> 2026 | AX24: =+B3 -> 2026 | AZ24: =+B3 -> 2026
B25: =+B3 -> 2026 | C25: Mat'l & Sub | D25: Mat'l & Sub | F25: =+B25 -> 2026 | G25: Mat'l & Sub | H25: Mat'l & Sub | J25: =+B25 -> 2026 | K25: Mat'l & Sub | L25: Mat'l & Sub | N25: =+B25 -> 2026 | O25: Mat'l & Sub | P25: Mat'l & Sub | R25: =+B25 -> 2026 | S25: Mat'l & Sub | T25: Mat'l & Sub | V25: =+B25 -> 2026 | W25: Mat'l & Sub | X25: Mat'l & Sub | Z25: =+B25 -> 2026 | AA25: Mat'l & Sub | AB25: Mat'l & Sub | AD25: =+B25 -> 2026 | AE25: Mat'l & Sub | AF25: Mat'l & Sub | AH25: =+B25 -> 2026 | AI25: Mat'l & Sub | AJ25: Mat'l & Sub | AL25: =+B25 -> 2026 | AM25: Mat'l & Sub | AN25: Mat'l & Sub | AP25: =+B25 -> 2026 | AQ25: Mat'l & Sub | AR25: Mat'l & Sub | AT25: =+B25 -> 2026 | AU25: Mat'l & Sub | AV25: Mat'l & Sub | AX25: Total Budgeted | AZ25: Total Budgeted
B26: Mat'l & Sub | C26: Cost Of | D26: Gross | F26: Mat'l & Sub | G26: Cost Of | H26: Gross | J26: Mat'l & Sub | K26: Cost Of | L26: Gross | N26: Mat'l & Sub | O26: Cost Of | P26: Gross | R26: Mat'l & Sub | S26: Cost Of | T26: Gross | V26: Mat'l & Sub | W26: Cost Of | X26: Gross | Z26: Mat'l & Sub | AA26: Cost Of | AB26: Gross | AD26: Mat'l & Sub | AE26: Cost Of | AF26: Gross | AH26: Mat'l & Sub | AI26: Cost Of | AJ26: Gross | AL26: Mat'l & Sub | AM26: Cost Of | AN26: Gross | AP26: Mat'l & Sub | AQ26: Cost Of | AR26: Gross | AT26: Mat'l & Sub | AU26: Cost Of | AV26: Gross | AX26: $ | AZ26: $
A27: Material & Subcontract Sales | B27: Sales | C27: Sales | D27: Profit | F27: Sales | G27: Sales | H27: Profit | J27: Sales | K27: Sales | L27: Profit | N27: Sales | O27: Sales | P27: Profit | R27: Sales | S27: Sales | T27: Profit | V27: Sales | W27: Sales | X27: Profit | Z27: Sales | AA27: Sales | AB27: Profit | AD27: Sales | AE27: Sales | AF27: Profit | AH27: Sales | AI27: Sales | AJ27: Profit | AL27: Sales | AM27: Sales | AN27: Profit | AP27: Sales | AQ27: Sales | AR27: Profit | AT27: Sales | AU27: Sales | AV27: Profit | AX27: Sales | AZ27: Material
A28: Duke OH | B28: 0 | C28: =B28*(1-$B$38) -> 0 | D28: =B28-C28 -> 0 | F28: 0 | G28: =F28*(1-$B$38) -> 0 | H28: =F28-G28 -> 0 | I28: =IF(D28=0,0,D28/B28) -> 0 | J28: 0 | K28: =J28*(1-$B$38) -> 0 | L28: =J28-K28 -> 0 | N28: 0 | O28: =N28*(1-$B$38) -> 0 | P28: =N28-O28 -> 0 | R28: 0 | S28: =R28*(1-$B$38) -> 0 | T28: =R28-S28 -> 0 | V28: 0 | W28: =V28*(1-$B$38) -> 0 | X28: =V28-W28 -> 0 | Z28: 0 | AA28: =Z28*(1-$B$38) -> 0 | AB28: =Z28-AA28 -> 0 | AD28: 0 | AE28: =AD28*(1-$B$38) -> 0 | AF28: =AD28-AE28 -> 0 | AH28: 0 | AI28: =AH28*(1-$B$38) -> 0 | AJ28: =AH28-AI28 -> 0 | AL28: 0 | AM28: =AL28*(1-$B$38) -> 0 | AN28: =AL28-AM28 -> 0 | AP28: 0 | AQ28: =AP28*(1-$B$38) -> 0 | AR28: =AP28-AQ28 -> 0 | AT28: 0 | AU28: =AT28*(1-$B$38) -> 0 | AV28: =AT28-AU28 -> 0 | AX28: =+B28+F28+J28+N28+R28+V28+Z28+AD28+AH28+AL28+AP28+AT28 -> 0 | AZ28: =+C28+G28+K28+O28+S28+W28+AA28+AE28+AI28+AM28+AQ28+AU28 -> 0
A29: Duke IN | B29: 0 | C29: =B29*(1-$B$38) -> 0 | D29: =B29-C29 -> 0 | F29: 0 | G29: =F29*(1-$B$38) -> 0 | H29: =F29-G29 -> 0 | J29: 0 | K29: =J29*(1-$B$38) -> 0 | L29: =J29-K29 -> 0 | N29: 0 | O29: =N29*(1-$B$38) -> 0 | P29: =N29-O29 -> 0 | R29: 0 | S29: =R29*(1-$B$38) -> 0 | T29: =R29-S29 -> 0 | V29: 0 | W29: =V29*(1-$B$38) -> 0 | X29: =V29-W29 -> 0 | Z29: 0 | AA29: =Z29*(1-$B$38) -> 0 | AB29: =Z29-AA29 -> 0 | AD29: 0 | AE29: =AD29*(1-$B$38) -> 0 | AF29: =AD29-AE29 -> 0 | AH29: 0 | AI29: =AH29*(1-$B$38) -> 0 | AJ29: =AH29-AI29 -> 0 | AL29: 0 | AM29: =AL29*(1-$B$38) -> 0 | AN29: =AL29-AM29 -> 0 | AP29: 0 | AQ29: =AP29*(1-$B$38) -> 0 | AR29: =AP29-AQ29 -> 0 | AT29: 0 | AU29: =AT29*(1-$B$38) -> 0 | AV29: =AT29-AU29 -> 0 | AX29: =+B29+F29+J29+N29+R29+V29+Z29+AD29+AH29+AL29+AP29+AT29 -> 0 | AZ29: =+C29+G29+K29+O29+S29+W29+AA29+AE29+AI29+AM29+AQ29+AU29 -> 0
A30: AES - OH | B30: 0 | C30: =B30*(1-$B$38) -> 0 | D30: =B30-C30 -> 0 | F30: 0 | G30: =F30*(1-$B$38) -> 0 | H30: =F30-G30 -> 0 | J30: 0 | K30: =J30*(1-$B$38) -> 0 | L30: =J30-K30 -> 0 | N30: 0 | O30: =N30*(1-$B$38) -> 0 | P30: =N30-O30 -> 0 | R30: 0 | S30: =R30*(1-$B$38) -> 0 | T30: =R30-S30 -> 0 | V30: 0 | W30: =V30*(1-$B$38) -> 0 | X30: =V30-W30 -> 0 | Z30: 0 | AA30: =Z30*(1-$B$38) -> 0 | AB30: =Z30-AA30 -> 0 | AD30: 0 | AE30: =AD30*(1-$B$38) -> 0 | AF30: =AD30-AE30 -> 0 | AH30: 0 | AI30: =AH30*(1-$B$38) -> 0 | AJ30: =AH30-AI30 -> 0 | AL30: 0 | AM30: =AL30*(1-$B$38) -> 0 | AN30: =AL30-AM30 -> 0 | AP30: 0 | AQ30: =AP30*(1-$B$38) -> 0 | AR30: =AP30-AQ30 -> 0 | AT30: 0 | AU30: =AT30*(1-$B$38) -> 0 | AV30: =AT30-AU30 -> 0 | AX30: =+B30+F30+J30+N30+R30+V30+Z30+AD30+AH30+AL30+AP30+AT30 -> 0 | AZ30: =+C30+G30+K30+O30+S30+W30+AA30+AE30+AI30+AM30+AQ30+AU30 -> 0
A31: Miscellaneous | B31: 0 | C31: =B31*(1-$B$37) -> 0 | D31: =B31-C31 -> 0 | F31: 0 | G31: =F31*(1-$B$37) -> 0 | H31: =F31-G31 -> 0 | J31: 0 | K31: =J31*(1-$B$37) -> 0 | L31: =J31-K31 -> 0 | N31: 0 | O31: =N31*(1-$B$37) -> 0 | P31: =N31-O31 -> 0 | R31: 0 | S31: =R31*(1-$B$37) -> 0 | T31: =R31-S31 -> 0 | V31: 0 | W31: =V31*(1-$B$37) -> 0 | X31: =V31-W31 -> 0 | Z31: 0 | AA31: =Z31*(1-$B$37) -> 0 | AB31: =Z31-AA31 -> 0 | AD31: 0 | AE31: =AD31*(1-$B$37) -> 0 | AF31: =AD31-AE31 -> 0 | AH31: 0 | AI31: =AH31*(1-$B$37) -> 0 | AJ31: =AH31-AI31 -> 0 | AL31: 0 | AM31: =AL31*(1-$B$37) -> 0 | AN31: =AL31-AM31 -> 0 | AP31: 0 | AQ31: =AP31*(1-$B$37) -> 0 | AR31: =AP31-AQ31 -> 0 | AT31: 0 | AU31: =AT31*(1-$B$37) -> 0 | AV31: =AT31-AU31 -> 0 | AX31: =+B31+F31+J31+N31+R31+V31+Z31+AD31+AH31+AL31+AP31+AT31 -> 0 | AZ31: =+C31+G31+K31+O31+S31+W31+AA31+AE31+AI31+AM31+AQ31+AU31 -> 0
A32: Hoosier Substation | C32: =B32*(1-I32) -> 0 | D32: =B32-C32 -> 0 | G32: =F32*(1-L32) -> 0 | H32: =F32-G32 -> 0 | I32: 0.1 | K32: =J32*(1-O32) -> 0 | L32: =J32-K32 -> 0 | O32: =N32*(1-T32) -> 0 | P32: =N32-O32 -> 0 | S32: =R32*(1-X32) -> 0 | T32: =R32-S32 -> 0 | V32: 0 | W32: =V32*(1-AB32) -> 0 | X32: =V32-W32 -> 0 | Z32: 0 | AA32: =Z32*(1-AF32) -> 0 | AB32: =Z32-AA32 -> 0 | AD32: 0 | AE32: =AD32*(1-AJ32) -> 0 | AF32: =AD32-AE32 -> 0 | AI32: =AH32*(1-AN32) -> 0 | AJ32: =AH32-AI32 -> 0 | AM32: =AL32*(1-AR32) -> 0 | AN32: =AL32-AM32 -> 0 | AQ32: =AP32*(1-AV32) -> 0 | AR32: =AP32-AQ32 -> 0 | AU32: =AT32*(1-AZ32) -> 0 | AV32: =AT32-AU32 -> 0 | AX32: =+B32+F32+J32+N32+R32+V32+Z32+AD32+AH32+AL32+AP32+AT32 -> 0
A33: Total | B33: =SUM(B28:B32) -> 0 | C33: =SUM(C28:C32) -> 0 | D33: =SUM(D28:D32) -> 0 | F33: =SUM(F28:F32) -> 0 | G33: =SUM(G28:G32) -> 0 | H33: =SUM(H28:H32) -> 0 | I33: =D33/B33 -> #DIV/0! | J33: =SUM(J28:J32) -> 0 | K33: =SUM(K28:K32) -> 0 | L33: =SUM(L28:L32) -> 0 | N33: =SUM(N28:N32) -> 0 | O33: =SUM(O28:O32) -> 0 | P33: =SUM(P28:P32) -> 0 | R33: =SUM(R28:R32) -> 0 | S33: =SUM(S28:S32) -> 0 | T33: =SUM(T28:T32) -> 0 | V33: =SUM(V28:V32) -> 0 | W33: =SUM(W28:W32) -> 0 | X33: =SUM(X28:X32) -> 0 | Z33: =SUM(Z28:Z32) -> 0 | AA33: =SUM(AA28:AA32) -> 0 | AB33: =SUM(AB28:AB32) -> 0 | AD33: =SUM(AD28:AD32) -> 0 | AE33: =SUM(AE28:AE32) -> 0 | AF33: =SUM(AF28:AF32) -> 0 | AH33: =SUM(AH28:AH32) -> 0 | AI33: =SUM(AI28:AI32) -> 0 | AJ33: =SUM(AJ28:AJ32) -> 0 | AL33: =SUM(AL28:AL32) -> 0 | AM33: =SUM(AM28:AM32) -> 0 | AN33: =SUM(AN28:AN32) -> 0 | AP33: =SUM(AP28:AP32) -> 0 | AQ33: =SUM(AQ28:AQ32) -> 0 | AR33: =SUM(AR28:AR32) -> 0 | AT33: =SUM(AT28:AT32) -> 0 | AU33: =SUM(AU28:AU32) -> 0 | AV33: =SUM(AV28:AV32) -> 0 | AX33: =SUM(AX28:AX32) -> 0 | AZ33: =SUM(AZ28:AZ32) -> 0
B34: (Used) | C34: (Used) | F34: (Used) | G34: (Used) | I34: (Used) | J34: (Used) | K34: (Used) | N34: (Used) | O34: (Used) | R34: (Used) | S34: (Used) | V34: (Used) | W34: (Used) | Z34: (Used) | AA34: (Used) | AD34: (Used) | AE34: (Used) | AH34: (Used) | AI34: (Used) | AL34: (Used) | AM34: (Used) | AP34: (Used) | AQ34: (Used) | AT34: (Used) | AU34: (Used)
B37: 0.03
B38: 0.1 | F38: =10000000/12 -> 833333.33

Sheet WIP & AP
B1: Actual | C1: Actual | D1: Actual | E1: 3 Yr | F1: Budgeted
B2: 45291 | C2: 45657 | D2: 46022 | E2: Avg | F2: 12/31/26
A5: Sales $'s | B5: ='Operating Exp'!S4 -> 109868 | C5: ='Operating Exp'!R4 -> 1044746 | D5: ='Operating Exp'!Q4 -> 1827505 | E5: =AVERAGE(B5:D5) -> 994039.67 | F5: =CVRIS!T7 -> 2029126.3
A9: WIP $'s | B9: 0 | C9: 0 | D9: =CVRBS!D10 -> 0 | E9: =AVERAGE(B9:D9) -> 0 | F9: 0
A13: AP $'s | B13: 0 | C13: 81 | D13: =CVRBS!D37 -> 0 | E13: =AVERAGE(B13:D13) -> 27 | F13: 0

Sheet AR Turns
B1: Actual | C1: Actual | D1: Actual | E1: Actual | F1: Budgeted
B2: Y/E | C2: Y/E | D2: Y/E | E2: Y/E | F2: Y/E
B3: 44926 | C3: 45291 | D3: 45657 | E3: 46022 | F3: 46387
A5: Sales per F/S | B5: ='Operating Exp'!T4 -> 0 | C5: ='Operating Exp'!S4 -> 109868 | D5: ='Operating Exp'!R4 -> 1044746 | E5: ='Operating Exp'!Q4 -> 1827505 | F5: =CVRIS!T7 -> 2029126.3
A9: AR at BOY | B9: 0 | C9: =+B10 -> 0 | D9: =+C10 -> 0 | E9: =+D10 -> 17987 | F9: =E10 -> 40886
A10: AR at EOY | B10: 0 | C10: 0 | D10: 17987 | E10: =CVRBS!D8 -> 40886 | F10: =CVRBS!F8 -> 30000 | G10: =365/(F5/F10) -> 5.3964113
A11: Total | B11: =SUM(B9:B10) -> 0 | C11: =SUM(C9:C10) -> 0 | D11: =SUM(D9:D10) -> 17987 | E11: =SUM(E9:E10) -> 58873 | F11: =SUM(F9:F10) -> 70886
A13: Average AR | B13: =B11/2 -> 0 | C13: =C11/2 -> 0 | D13: =D11/2 -> 8993.5 | E13: =E11/2 -> 29436.5 | F13: =F11/2 -> 35443
A15: AR Turnover/Yr. | B15: =IFERROR(B5/B13,0) -> 0 | C15: =IFERROR(C5/C13,0) -> 0 | D15: =IFERROR(D5/D13,0) -> 116.16679 | E15: =IFERROR(E5/E13,0) -> 62.082958 | F15: =F5/F13 -> 57.250411
A17: Avg # Days O/S | B17: =IFERROR(365/B15,0) -> 0 | C17: =IFERROR(365/C15,0) -> 0 | D17: =IFERROR(365/D15,0) -> 3.142034 | E17: =IFERROR(365/E15,0) -> 5.8792302 | F17: =365/F15 -> 6.3755001
A21: Sales per F/S | B21: =+B5 -> 0 | C21: =+C5 -> 109868 | D21: =+D5 -> 1044746 | E21: =+E5 -> 1827505 | F21: =+F5 -> 2029126.3

Sheet 06-40 ITC Ware
A1: 06-40 ITC Warehouse
A3: MIDWEST
A4: PERSONNEL | B4: 0
A5: MONTHS | B5: 0
A6: WEEKLY HOURS | B6: 40
A7: EFFICIENCY | B7: 0.9
A8: TOTAL HOURS | B8: =(B4*(52*(B5/12)*B6))*B7 -> 0
A9: DIRECT LABOR RATE | B9: 32.07 | C9: (Actual Avg rate from Labor Accrual)
A10: RATIO | B10: 0 | C10: (12/31/14 = 1.8)
C11: =B8*B9*B10 -> 0
A14: ITC
A15: PERSONNEL | B15: 0
A16: MONTHS | B16: 0
A17: WEEKLY HOURS | B17: 40
A18: EFFICIENCY | B18: 0.9
A19: TOTAL HOURS | B19: =(B15*(52*(B16/12)*B17))*B18 -> 0
A20: DIRECT LABOR RATE | B20: 29.93 | C20: (Actual Avg rate from Labor Accrual)
A21: RATIO | B21: 0 | C21: (12/31/14 = 1.69)
C22: =B19*B20*B21 -> 0
A25: METC
A26: PERSONNEL | B26: 0
A27: MONTHS | B27: 0
A28: WEEKLY HOURS | B28: 40
A29: EFFICIENCY | B29: 0.9
A30: TOTAL HOURS | B30: =(B26*(52*(B27/12)*B28))*B29 -> 0
A31: DIRECT LABOR RATE | B31: 31.24 | C31: (Actual Avg rate from Labor Accrual)
A32: RATIO | B32: 0 | C32: (12/31/14 = 1.70)
C33: =B30*B31*B32 -> 0
A37: PERSONNEL | B37: 0
A38: MONTHS | B38: 0
A39: WEEKLY HOURS | B39: 40
A40: EFFICIENCY | B40: 0.9
A41: TOTAL HOURS | B41: =(B37*(52*(B38/12)*B39))*B40 -> 0
A42: DIRECT LABOR RATE | B42: 33
A43: RATIO | B43: 1.8
C44: =B41*B42*B43 -> 0
A48: PERSONNEL | B48: 0
A49: MONTHS | B49: 0
A50: WEEKLY HOURS | B50: 40
A51: EFFICIENCY | B51: 0.9
A52: TOTAL HOURS | B52: =(B48*(52*(B49/12)*B50))*B51 -> 0
A53: DIRECT LABOR RATE | B53: 33
A54: RATIO | B54: 1.8
C55: =B52*B53*B54 -> 0
A59: PERSONNEL | B59: 0
A60: MONTHS | B60: 0
A61: WEEKLY HOURS | B61: 50
A62: EFFICIENCY | B62: 0.9
A63: TOTAL HOURS | B63: =(B59*(52*(B60/12)*B61))*B62 -> 0
A64: DIRECT LABOR RATE | B64: 33
A65: RATIO | B65: 1.8
C66: =B63*B64*B65 -> 0
A70: PERSONNEL | B70: 0
A71: MONTHS | B71: 0
A72: WEEKLY HOURS | B72: 50
A73: EFFICIENCY | B73: 0.9
A74: TOTAL HOURS | B74: =(B70*(52*(B71/12)*B72))*B73 -> 0
A75: DIRECT LABOR RATE | B75: 33
A76: RATIO | B76: 1.8
C77: =B74*B75*B76 -> 0
A79: Total | C79: =SUM(C2:C78) -> 0
A80: Total Hours | C80: =B74+B63+B52+B41+B30+B19+B8 -> 0
A81: Average Direct Labor Rate | C81: =AVERAGE(B75,B64,B53,B42,B31,B20,B9) -> 32.177143
